Workbook

Sheet balance_sheet
A1: item | B1: 2018 | C1: 2019 | D1: 2020 | E1: 2021 | F1: 2022 | G1: 2023 | H1: 2024 | I1: 2025
A2: TÀI SẢN NGẮN HẠN | B2: 25308725187618 | C2: 30436936909894 | D2: 56747258197010 | E2: 94154859648304 | F2: 80514708725456 | G2: 82716439173043 | H2: 86674276272995 | I2: 103659402759724
A3: Tiền và tương đương tiền | B3: 2515617135457 | C3: 4544900252204 | D3: 13696099298228 | E3: 22471375562130 | F3: 8324588920227 | G3: 12252001160884 | H3: 6887646139852 | I3: 8300890304205
A4: Tiền | B4: 1822302135457 | C4: 1678314252204 | D4: 2094314298228 | E4: 6316299666510 | F4: 3458049733104 | G4: 3771595160884 | H4: 2919531945908 | I4: 4602047650138
A5: Các khoản tương đương tiền | B5: 693315000000 | C5: 2866586000000 | D5: 11601785000000 | E5: 16155075895620 | F5: 4866539187123 | G5: 8480406000000 | H5: 3968114193944 | I5: 3698842654067
A6: Đầu tư ngắn hạn | B6: 0 | C6: 0 | D6: 0 | E6: 0 | F6: 0 | G6: 0 | H6: 0 | I6: 0
A7: Đầu tư ngắn hạn | F7: 0 | G7: 0 | H7: 0 | I7: 0
A8: Dự phòng giảm giá | B8: 0 | C8: 0 | D8: 0 | E8: 0 | F8: 0 | G8: 0 | H8: 0 | I8: 0
A9: Các khoản phải thu | B9: 3210278608751 | C9: 3561397190688 | D9: 6124790460291 | E9: 7662680796645 | F9: 9892867373309 | G9: 10702136439996 | H9: 7647800286988 | I9: 15042323117690
A10: Phải thu khách hàng | B10: 2281760501157 | C10: 2699937350329 | D10: 3949486943250 | E10: 4973095672343 | F10: 2958587125337 | G10: 5999539831497 | H10: 4352135419872 | I10: 10971774018235
A11: Trả trước người bán | B11: 810319171039 | C11: 757832561191 | D11: 1303037835829 | E11: 1722371823278 | F11: 5366251939739 | G11: 2583940446585 | H11: 2118824427004 | I11: 1878084035938
A12: Phải thu nội bộ | B12: 0 | C12: 0 | D12: 0 | E12: 0 | F12: 0 | G12: 0 | H12: 0 | I12: 0
A13: Phải thu hợp đồng xây dựng đang thực hiện | B13: 0 | C13: 0 | D13: 0 | E13: 0 | F13: 0 | G13: 0 | H13: 0 | I13: 0
A14: Phải thu khác | B14: 150952350749 | C14: 139273246353 | D14: 910365502671 | E14: 981799066828 | F14: 1482978249031 | G14: 1961601875298 | H14: 1248992845378 | I14: 2318283126429
A15: Dự phòng nợ khó đòi | B15: -37693842866 | C15: -37145790132 | D15: -39336197606 | E15: -39275168162 | F15: -41074336139 | G15: -46628415158 | H15: -159993736285 | I15: -132548698812
A16: Hàng tồn kho, ròng | B16: 14115139048908 | C16: 19411922748095 | D16: 26286822229202 | E16: 42134493932210 | F16: 34491111096123 | G16: 34504487406261 | H16: 46091222189472 | I16: 52828227344442
A17: Hàng tồn kho | B17: 14188336169734 | C17: 19480666530260 | D17: 26373360826788 | E17: 42370012405544 | F17: 35727277739296 | G17: 34628367844950 | H17: 46192292081813 | I17: 52892273238885
A18: Dự phòng giảm giá hàng tồn kho | B18: -73197120826 | C18: -68743782165 | D18: -86538597586 | E18: -235518473334 | F18: -1236166643173 | G18: -123880438689 | H18: -101069892341 | I18: -64045894443
A19: Tài sản lưu động khác | B19: 0 | C19: 0 | D19: 0 | E19: 0 | F19: 0 | G19: 0 | H19: 0 | I19: 0
... A22: Phải thu thuế khác | B22: 18750136896 | C22: 25665176119 | D22: 13816802000 | E22: 17769142467 | F22: 100170236943 | G22: 11704488524 | H22: 10074967536 | I22: 6371103672
A23: Tài sản lưu động khác | F23: 0 | G23: 0 | H23: 0 | I23: 0
A24: TÀI SẢN DÀI HẠN | B24: 52914282483307 | C24: 71339093190006 | D24: 74764176191827 | E24: 84081562709945 | F24: 89820810782676 | G24: 105066147390758 | H24: 137815431280986 | I24: 154239798057823
A25: Phải thu dài hạn | B25: 22301804672 | C25: 27717594984 | D25: 305165547431 | E25: 809234947969 | F25: 894484456379 | G25: 1880922130348 | H25: 923400123614 | I25: 290327516308
A26: Phải thu khách hàng dài hạn | B26: 0 | C26: 0 | D26: 0 | E26: 0 | F26: 0 | G26: 0 | H26: 0 | I26: 0
A27: Phải thu nội bộ dài hạn | B27: 0 | C27: 0 | D27: 0 | E27: 0 | F27: 0 | G27: 0 | H27: 0 | I27: 0
A28: Phải thu dài hạn khác | B28: 22301804672 | C28: 22807248984 | D28: 209158308631 | E28: 690833578689 | F28: 792790894665 | G28: 781079548004 | H28: 840594835822 | I28: 248919079879
A29: Dự phòng phải thu dài hạn | B29: 0 | C29: 0 | D29: 0 | E29: 0 | F29: 0 | G29: 0 | H29: 0 | I29: 0
A30: Tài sản cố định | B30: 12782560625001 | C30: 31249493917960 | D30: 65561657180137 | E30: 69280841784004 | F30: 70832915657865 | G30: 71998370737871 | H30: 67428366953514 | I30: 133608057859977
A31: GTCL TSCĐ hữu hình | B31: 12565363529879 | C31: 30980122434704 | D31: 65307819877543 | E31: 68744125939109 | F31: 70199153681536 | G31: 71787251586301 | H31: 67244150975048 | I31: 133420846696083
A32: Nguyên giá TSCĐ hữu hình | B32: 22992663946845 | C32: 43804940121895 | D32: 82616810188887 | E32: 91026106008677 | F32: 98976369133844 | G32: 106923132503430 | H32: 108146566348954 | I32: 182308655292963
A33: Khấu hao lũy kế TSCĐ hữu hình | B33: -10427300416966 | C33: -12824817687191 | D33: -17308990311344 | E33: -22281980069568 | F33: -28777215452308 | G33: -35135880917129 | H33: -40902415373906 | I33: -48887808596880
A34: GTCL tài sản thuê tài chính | B34: 0 | C34: 0 | D34: 0 | E34: 0 | F34: 0 | G34: 0 | H34: 0 | I34: 0
A35: Nguyên giá tài sản thuê tài chính | B35: 0 | C35: 0 | D35: 0 | E35: 0 | F35: 0 | G35: 0 | H35: 0 | I35: 0
... A72: Vay dài hạn | B72: 12810996979972 | C72: 19842099219720 | D72: 17343247551512 | E72: 13464931998700 | F72: 11151651204402 | G72: 10399119292481 | H72: 27080443256096 | I72: 27479194057074
A73: Thuế thu nhập hoãn lại | F73: 31207164756 | G73: 30012518415 | H73: 29268483140 | I73: 31013808361
A74: Dự phòng trợ cấp thôi việc | B74: 0 | C74: 0 | D74: 0 | E74: 0 | F74: 0 | G74: 0 | H74: 0 | I74: 0
A75: Dự phòng các khoản nợ dài hạn | B75: 18238256789 | C75: 20413737584 | D75: 26000932740 | E75: 49310752616 | F75: 57568259201 | G75: 55168639369 | H75: 121495546940 | I75: 119373951692
A76: Doanh thu chưa thực hiện | B76: 0 | C76: 3369818100 | D76: 16127650192 | E76: 8803217550 | F76: 4109316288 | G76: 174647128 | H76: 0 | I76: 0
A77: Quỹ phát triển khoa học công nghệ | B77: 0 | C77: 0 | D77: 0 | E77: 0 | F77: 0 | G77: 0 | H77: 0 | I77: 0
A78: Vốn chủ sở hữu | B78: 40622949840810 | C78: 47786636143695 | D78: 59219786306111 | E78: 90780625511439 | F78: 96112939615783 | G78: 102836419239379 | H78: 114647457983699 | I78: 131220010876575
A79: Vốn và các quỹ | B79: 40622949840810 | C79: 47786636143695 | D79: 59219786306111 | E79: 90780625511439 | F79: 96112939615783 | G79: 102836419239379 | H79: 114647457983699 | I79: 131220010876575
A80: Vốn góp | B80: 21239071660000 | C80: 27610741150000 | D80: 33132826590000 | E80: 44729227060000 | F80: 58147857000000 | G80: 58147857000000 | H80: 63962502000000 | I80: 76754658550000
A81: Thặng dư vốn cổ phần | B81: 3211560416270 | C81: 3211560416270 | D81: 3211560416270 | E81: 3211560416270 | F81: 3211560416270 | G81: 3211560416270 | H81: 0 | I81: 0
A82: Vốn khác | B82: 0 | C82: 0 | D82: 0 | E82: 0 | F82: 0 | G82: 0 | H82: 0 | I82: 0
A83: Cổ phiếu quỹ | B83: 0 | C83: 0 | D83: 0 | E83: 0 | F83: 0 | G83: 0 | H83: 0 | I83: 0
A84: Chênh lệch đánh giá lại tài sản | B84: 0 | C84: 0 | D84: 0 | E84: 0 | F84: 0 | G84: 0 | H84: 0 | I84: 0
A85: Chênh lệch tỷ giá | B85: 276819257 | C85: 565534994 | D85: 5568369072 | E85: -1925960852 | F85: -20652355005 | G85: 0 | H85: 0 | I85: 0
... A105: Chi phí sản xuất, kinh doanh dở dang dài hạn | B105: 910420483699 | C105: 750146398723 | D105: 918470731946 | E105: 1409414047105 | F105: 28953988212 | G105: 46356652469 | H105: 94859885024 | I105: 148814839011
A106: Đầu tư nắm giữ đến ngày đáo hạn | F106: 0 | G106: 40000000000 | H106: 136500000000 | I106: 2248000000000
A107: Thiết bị, vật tư, phụ tùng thay thế dài hạn | B107: 0 | C107: 0 | D107: 0 | E107: 0 | F107: 0 | G107: 0 | H107: 429422385383 | I107: 335208284895
A108: Doanh thu chưa thực hiện ngắn hạn | B108: 9929720982 | C108: 27406111996 | D108: 34564307818 | E108: 16951911160 | F108: 16974936888 | G108: 9979596501 | H108: 11060479431 | I108: 152519279244
A109: Quỹ bình ổn giá | B109: 0 | C109: 0 | D109: 0 | E109: 0 | F109: 0 | G109: 0 | H109: 0 | I109: 0
A110: Giao dịch mua bán lại trái phiếu chính phủ | B110: 0 | C110: 0 | D110: 0 | E110: 0 | F110: 0 | G110: 0 | H110: 0 | I110: 0
A111: Người mua trả tiền trước dài hạn | B111: 0 | C111: 0 | D111: 0 | E111: 0 | F111: 0 | G111: 0 | H111: 0 | I111: 0
A112: Chi phí phải trả dài hạn | B112: 451100573027 | C112: 427328992030 | D112: 223664493846 | E112: 410407940262 | F112: 531620146455 | G112: 610552512045 | H112: 1089692237207 | I112: 607363800426
A113: Phải trả nội bộ về vốn kinh doanh | B113: 0 | C113: 0 | D113: 0 | E113: 0 | F113: 0 | G113: 0 | H113: 0 | I113: 0
A114: Trái phiếu chuyển đổi | B114: 0 | C114: 0 | D114: 0 | E114: 0 | F114: 0 | G114: 0 | H114: 0 | I114: 0
A115: Cổ phiếu ưu đãi | F115: 0 | G115: 0 | H115: 0 | I115: 0
A116: Cổ phiếu phổ thông | B116: 21239071660000 | C116: 27610741150000 | D116: 33132826590000 | E116: 44729227060000 | F116: 58147857000000 | G116: 58147857000000 | H116: 63962502000000 | I116: 76754658550000
A117: Quyền chọn chuyển đổi trái phiếu | B117: 0 | C117: 0 | D117: 0 | E117: 0 | F117: 0 | G117: 0 | H117: 0 | I117: 0
A118: LNST chưa phân phối lũy kế đến cuối kỳ trước | B118: 6553423653491 | C118: 8349470883074 | D118: 8342142580473 | E118: 7285282773452 | F118: 25350319419956 | G118: 33796166741483 | H118: 37624250548129 | I118: 35657348003468
A119: LNST chưa phân phối kỳ này | B119: 8573014210414 | C119: 7527442867874 | D119: 13450300052812 | E119: 34478143197460 | F119: 8483510554031 | G119: 6796864921171 | H119: 11974873561074 | I119: 15380553745875
A120: Xây dựng cơ bản đang dở dang | B120: 37196900023418 | C120: 36685174068291 | D120: 5328742775048 | E120: 8289285350608 | F120: 13334320924143 | G120: 26052572725032 | H120: 63655857440382 | I120: 10721076531961
A121: Lợi thế thương mại | B121: 88234324237 | C121: 61185171517 | D121: 43109950665 | E121: 37121950665 | F121: 88008959996 | G121: 75909018692 | H121: 63613126723 | I121: 51513185419
A122: Lợi ích cổ đông không kiểm soát | B122: 126961469222 | C122: 163213679327 | D122: 148746685328 | E122: 154788720987 | F122: 105562146315 | G122: 65769846491 | H122: 290990632368 | I122: 2039012776403
A123: Nguồn kinh phí đã hình thành TSCĐ | B123: 0 | C123: 0 | D123: 0 | E123: 0 | F123: 0 | G123: 0 | H123: 0 | I123: 0

Sheet income_statement
A1: item | B1: 2018 | C1: 2019 | D1: 2020 | E1: 2021 | F1: 2022 | G1: 2023 | H1: 2024 | I1: 2025
A2: Doanh thu bán hàng và cung cấp dịch vụ | B2: 56580423695083 | C2: 64677906575644 | D2: 91279041771826 | E2: 150865359967200 | F2: 142770810676858 | G2: 120355231616139 | H2: 140561387448572 | I2: 158332317934212
A3: Các khoản giảm trừ doanh thu | B3: -743965315324 | C3: -1019713901853 | D3: -1160538345109 | E3: -1185569987855 | F3: -1361536216226 | G3: -1402203722485 | H3: -1706275317185 | I3: -2216223315730
A4: Doanh thu thuần | B4: 55836458379759 | C4: 63658192673791 | D4: 90118503426717 | E4: 149679789979345 | F4: 141409274460632 | G4: 118953027893654 | H4: 138855112131387 | I4: 156116094618482
A5: Giá vốn hàng bán | B5: -44165626148685 | C5: -52472820451654 | D5: -71214453522563 | E5: -108571380446353 | F5: -124645848221080 | G5: -106015187198082 | H5: -120357563003703 | I5: -131618306435300
A6: Lợi nhuận gộp | B6: 11670832231074 | C6: 11185372222137 | D6: 18904049904154 | E6: 41108409532992 | F6: 16763426239552 | G6: 12937840695572 | H6: 18497549127684 | I6: 24497788183182
A7: Doanh thu hoạt động tài chính | B7: 294408270741 | C7: 471053832011 | D7: 1004789766270 | E7: 3071440640188 | F7: 3743650707331 | G7: 3173086404949 | H7: 2618917240287 | I7: 2081789823040
A8: Chi phí tài chính | B8: -772317161901 | C8: -1181675710916 | D8: -2837406430588 | E8: -3731542257873 | F8: -7026723285241 | G8: -5191511844389 | H8: -3966636074605 | I8: -4603575989190
A9: Chi phí lãi vay | B9: -539861243640 | C9: -936710218359 | D9: -2191680923417 | E9: -2525823258237 | F9: -3083638131818 | G9: -3585077683881 | H9: -2287360810880 | I9: -3114855868974
A10: Chi phí bán hàng | B10: -676809221259 | C10: -873333584688 | D10: -1090795558423 | E10: -2120068223228 | F10: -2665806087302 | G10: -1961362129952 | H10: -2337308685264 | I10: -2633630711908
A11: Chi phí quản lý doanh nghiệp | B11: -444024985823 | C11: -569005805722 | D11: -690298504185 | E11: -1324261548679 | F11: -1019444279447 | G11: -1307290336873 | H11: -1545516022772 | I11: -1436537357489
A12: Lãi/(lỗ) từ hoạt động kinh doanh | B12: 10072089132832 | C12: 9030979639207 | D12: 15292303808992 | E12: 37008443446265 | F12: 9794030627309 | G12: 7650762789307 | H12: 13267005585330 | I12: 17905833947635
A13: Thu nhập khác | B13: 488856588036 | C13: 657680931477 | D13: 654081334225 | E13: 796666105925 | F13: 872024724926 | G13: 771973465495 | H13: 1159769685093 | I13: 305593357911
... A26: Lãi/(lỗ) từ công ty liên doanh (từ năm 2015) | B26: 0 | C26: -1431313615 | D26: 1964631764 | E26: 4465302865 | F26: -1072667584 | G26: 0 | H26: 0 | I26: 0

Sheet cash_flow
A1: item | B1: 2018 | C1: 2019 | D1: 2020 | E1: 2021 | F1: 2022 | G1: 2023 | H1: 2024 | I1: 2025
A2: Lợi nhuận/(lỗ) trước thuế | B2: 10071072872302 | C2: 9096662123386 | D2: 15356966791701 | E2: 37056777714190 | F2: 9922941127284 | G2: 7792728743173 | H2: 13693502261178 | I2: 18040591977880
A3: Khấu hao TSCĐ và BĐSĐT | B3: 2259594298268 | C3: 2593232573029 | D3: 4775781721269 | E3: 6076516295417 | F3: 6759462100582 | G3: 6761933539397 | H3: 6915671331197 | I3: 8470683260156
A4: Chi phí dự phòng | B4: -72990493823 | C4: -5772614376 | D4: 28314185442 | E4: 163177531627 | F4: 1010922330886 | G4: -1094201952159 | H4: 108500407214 | I4: -49830475782
A5: Lãi/lỗ chênh lệch tỷ giá hối đoái do đánh giá lại các khoản mục tiền tệ có gốc ngoại tệ | B5: 29910869480 | C5: 24183514856 | D5: 52078870772 | E5: 41938831417 | F5: 333983153559 | G5: 291243752578 | H5: 173470579978 | I5: 349627160986
A6: Lãi/(lỗ) từ thanh lý tài sản cố định | B6: 0 | C6: 0 | D6: 0 | E6: 0 | F6: 0 | G6: 0 | H6: 0 | I6: 0
A7: (Lãi)/lỗ từ hoạt động đầu tư | B7: -112985971103 | C7: -286185193464 | D7: -490559694590 | E7: -1661082595981 | F7: -1832298259730 | G7: -1927836792719 | H7: -1718310403845 | I7: -1298854971642
A8: Chi phí lãi vay | B8: 539861243640 | C8: 936710218359 | D8: 2191680923417 | E8: 2525823258237 | F8: 3083638131818 | G8: 3585077683881 | H8: 2287360810880 | I8: 3114855868974
A9: Thu lãi và cổ tức | B9: 0 | C9: 0 | D9: 0 | E9: 0 | F9: 0 | G9: 0 | H9: 0 | I9: 0
A10: Lợi nhuận/(lỗ) từ hoạt động kinh doanh trước những thay đổi vốn lưu động | B10: 12740513971484 | C10: 12358830621790 | D10: 21932338018863 | E10: 44209139034907 | F10: 19291327380767 | G10: 15421044915455 | H10: 21472490878571 | I10: 28627072820572
A11: (Tăng)/giảm các khoản phải thu | B11: -1423156571992 | C11: -288519564021 | D11: -3374026162649 | E11: -3039385771765 | F11: 4711117735355 | G11: -5601896103470 | H11: -1818671846432 | I11: -8743129086281
A12: (Tăng)/giảm hàng tồn kho | B12: -2301594154020 | C12: -5132237172021 | D12: -7061024985401 | E12: -16949192989135 | F12: 8023194725141 | G12: 1026315216371 | H12: -10759800904696 | I12: -7241774532693
A13: Tăng/(giảm) các khoản phải trả | B13: 1459709130157 | C13: 3557798129583 | D13: 4251742399296 | E13: 9250111116260 | F13: -14666409808394 | G13: 2609540999740 | H13: 1994355381518 | I13: 11393151396033
... A42: (Tăng)/giảm chứng khoán kinh doanh | B42: 0 | C42: 0 | D42: 0 | E42: 0 | F42: 0 | G42: 0 | H42: 0 | I42: 0

Sheet chi_so_tai_chinh
A1: Chỉ tiêu | B1: =balance_sheet!B1 | C1: =balance_sheet!C1 | D1: =balance_sheet!D1 | E1: =balance_sheet!E1 | F1: =balance_sheet!F1 | G1: =balance_sheet!G1 | H1: =balance_sheet!H1 | I1: =balance_sheet!I1 | J1: 2026
A2: ROE (LNST CĐ Cty mẹ / VCSH bình quân) | B2: n/a | C2: =IFERROR(C$51/((C$39+B$39)/2),"n/a") | D2: =IFERROR(D$51/((D$39+C$39)/2),"n/a") | E2: =IFERROR(E$51/((E$39+D$39)/2),"n/a") | F2: =IFERROR(F$51/((F$39+E$39)/2),"n/a") | G2: =IFERROR(G$51/((G$39+F$39)/2),"n/a") | H2: =IFERROR(H$51/((H$39+G$39)/2),"n/a") | I2: =IFERROR(I$51/((I$39+H$39)/2),"n/a") | J2: =IFERROR(J$51/((J$39+I$39)/2),"n/a")
A3: ROA (LNST / Tổng tài sản bình quân) | B3: n/a | C3: =IFERROR(C$50/((C$31+B$31)/2),"n/a") | D3: =IFERROR(D$50/((D$31+C$31)/2),"n/a") | E3: =IFERROR(E$50/((E$31+D$31)/2),"n/a") | F3: =IFERROR(F$50/((F$31+E$31)/2),"n/a") | G3: =IFERROR(G$50/((G$31+F$31)/2),"n/a") | H3: =IFERROR(H$50/((H$31+G$31)/2),"n/a") | I3: =IFERROR(I$50/((I$31+H$31)/2),"n/a")
A4: Tăng trưởng LN Cổ đông Cty mẹ | B4: n/a | C4: =IFERROR((C$51-B$51)/ABS(B$51),"n/a") | D4: =IFERROR((D$51-C$51)/ABS(C$51),"n/a") | E4: =IFERROR((E$51-D$51)/ABS(D$51),"n/a") | F4: =IFERROR((F$51-E$51)/ABS(E$51),"n/a") | G4: =IFERROR((G$51-F$51)/ABS(F$51),"n/a") | H4: =IFERROR((H$51-G$51)/ABS(G$51),"n/a") | I4: =IFERROR((I$51-H$51)/ABS(H$51),"n/a") | J4: =IFERROR((J$51-I$51)/ABS(I$51),"n/a")
A5: Tăng trưởng Doanh thu thuần | B5: n/a | C5: =IFERROR((C$43-B$43)/ABS(B$43),"n/a") | D5: =IFERROR((D$43-C$43)/ABS(C$43),"n/a") | E5: =IFERROR((E$43-D$43)/ABS(D$43),"n/a") | F5: =IFERROR((F$43-E$43)/ABS(E$43),"n/a") | G5: =IFERROR((G$43-F$43)/ABS(F$43),"n/a") | H5: =IFERROR((H$43-G$43)/ABS(G$43),"n/a") | I5: =IFERROR((I$43-H$43)/ABS(H$43),"n/a") | J5: =IFERROR((J$43-I$43)/ABS(I$43),"n/a")
A6: Biên lợi nhuận gộp | B6: =IFERROR(B$45/B$43,"n/a") | C6: =IFERROR(C$45/C$43,"n/a") | D6: =IFERROR(D$45/D$43,"n/a") | E6: =IFERROR(E$45/E$43,"n/a") | F6: =IFERROR(F$45/F$43,"n/a") | G6: =IFERROR(G$45/G$43,"n/a") | H6: =IFERROR(H$45/H$43,"n/a") | I6: =IFERROR(I$45/I$43,"n/a")
A7: Biên lợi nhuận ròng | B7: =IFERROR(B$51/B$43,"n/a") | C7: =IFERROR(C$51/C$43,"n/a") | D7: =IFERROR(D$51/D$43,"n/a") | E7: =IFERROR(E$51/E$43,"n/a") | F7: =IFERROR(F$51/F$43,"n/a") | G7: =IFERROR(G$51/G$43,"n/a") | H7: =IFERROR(H$51/H$43,"n/a") | I7: =IFERROR(I$51/I$43,"n/a") | J7: =IFERROR(J$51/J$43,"n/a")
A8: D/E (Nợ vay / Vốn chủ sở hữu) | B8: =IFERROR((B$34+B$36)/B$39,"n/a") | C8: =IFERROR((C$34+C$36)/C$39,"n/a") | D8: =IFERROR((D$34+D$36)/D$39,"n/a") | E8: =IFERROR((E$34+E$36)/E$39,"n/a") | F8: =IFERROR((F$34+F$36)/F$39,"n/a") | G8: =IFERROR((G$34+G$36)/G$39,"n/a") | H8: =IFERROR((H$34+H$36)/H$39,"n/a") | I8: =IFERROR((I$34+I$36)/I$39,"n/a")
A9: - Nợ vay dài hạn/Vốn chủ sở hữu | B9: =IFERROR(B$36/B$39,"n/a") | C9: =IFERROR(C$36/C$39,"n/a") | D9: =IFERROR(D$36/D$39,"n/a") | E9: =IFERROR(E$36/E$39,"n/a") | F9: =IFERROR(F$36/F$39,"n/a") | G9: =IFERROR(G$36/G$39,"n/a") | H9: =IFERROR(H$36/H$39,"n/a") | I9: =IFERROR(I$36/I$39,"n/a")
A10: - Nợ vay ngắn hạn/Vốn chủ sở hữu | B10: =IFERROR(B$34/B$39,"n/a") | C10: =IFERROR(C$34/C$39,"n/a") | D10: =IFERROR(D$34/D$39,"n/a") | E10: =IFERROR(E$34/E$39,"n/a") | F10: =IFERROR(F$34/F$39,"n/a") | G10: =IFERROR(G$34/G$39,"n/a") | H10: =IFERROR(H$34/H$39,"n/a") | I10: =IFERROR(I$34/I$39,"n/a")
A11: Nợ phải trả/Vốn chủ sở hữu | B11: =IFERROR(B$38/B$39,"n/a") | C11: =IFERROR(C$38/C$39,"n/a") | D11: =IFERROR(D$38/D$39,"n/a") | E11: =IFERROR(E$38/E$39,"n/a") | F11: =IFERROR(F$38/F$39,"n/a") | G11: =IFERROR(G$38/G$39,"n/a") | H11: =IFERROR(H$38/H$39,"n/a") | I11: =IFERROR(I$38/I$39,"n/a")
A12: - Nợ dài hạn/Vốn chủ sở hữu | B12: =IFERROR(B$37/B$39,"n/a") | C12: =IFERROR(C$37/C$39,"n/a") | D12: =IFERROR(D$37/D$39,"n/a") | E12: =IFERROR(E$37/E$39,"n/a") | F12: =IFERROR(F$37/F$39,"n/a") | G12: =IFERROR(G$37/G$39,"n/a") | H12: =IFERROR(H$37/H$39,"n/a") | I12: =IFERROR(I$37/I$39,"n/a")
A13: - Nợ ngắn hạn/Vốn chủ sở hữu | B13: =IFERROR(B$35/B$39,"n/a") | C13: =IFERROR(C$35/C$39,"n/a") | D13: =IFERROR(D$35/D$39,"n/a") | E13: =IFERROR(E$35/E$39,"n/a") | F13: =IFERROR(F$35/F$39,"n/a") | G13: =IFERROR(G$35/G$39,"n/a") | H13: =IFERROR(H$35/H$39,"n/a") | I13: =IFERROR(I$35/I$39,"n/a")
A14: Chi phí bán hàng, quản lý/LN gộp | B14: =IFERROR((ABS(B$46)+ABS(B$47))/B$45,"n/a") | C14: =IFERROR((ABS(C$46)+ABS(C$47))/C$45,"n/a") | D14: =IFERROR((ABS(D$46)+ABS(D$47))/D$45,"n/a") | E14: =IFERROR((ABS(E$46)+ABS(E$47))/E$45,"n/a") | F14: =IFERROR((ABS(F$46)+ABS(F$47))/F$45,"n/a") | G14: =IFERROR((ABS(G$46)+ABS(G$47))/G$45,"n/a") | H14: =IFERROR((ABS(H$46)+ABS(H$47))/H$45,"n/a") | I14: =IFERROR((ABS(I$46)+ABS(I$47))/I$45,"n/a")
A15: Chi phí lãi vay/LN từ hoạt động kinh doanh | B15: =IFERROR(ABS(B$49)/B$48,"n/a") | C15: =IFERROR(ABS(C$49)/C$48,"n/a") | D15: =IFERROR(ABS(D$49)/D$48,"n/a") | E15: =IFERROR(ABS(E$49)/E$48,"n/a") | F15: =IFERROR(ABS(F$49)/F$48,"n/a") | G15: =IFERROR(ABS(G$49)/G$48,"n/a") | H15: =IFERROR(ABS(H$49)/H$48,"n/a") | I15: =IFERROR(ABS(I$49)/I$48,"n/a")
A16: Số ngày phải trả (DPO) | B16: n/a | C16: =IFERROR(((C$33+B$33)/2)/ABS(C$44)*365,"n/a") | D16: =IFERROR(((D$33+C$33)/2)/ABS(D$44)*365,"n/a") | E16: =IFERROR(((E$33+D$33)/2)/ABS(E$44)*365,"n/a") | F16: =IFERROR(((F$33+E$33)/2)/ABS(F$44)*365,"n/a") | G16: =IFERROR(((G$33+F$33)/2)/ABS(G$44)*365,"n/a") | H16: =IFERROR(((H$33+G$33)/2)/ABS(H$44)*365,"n/a") | I16: =IFERROR(((I$33+H$33)/2)/ABS(I$44)*365,"n/a")
A17: Số ngày phải thu (DSO) | B17: n/a | C17: =IFERROR(((C$27+B$27)/2)/C$43*365,"n/a") | D17: =IFERROR(((D$27+C$27)/2)/D$43*365,"n/a") | E17: =IFERROR(((E$27+D$27)/2)/E$43*365,"n/a") | F17: =IFERROR(((F$27+E$27)/2)/F$43*365,"n/a") | G17: =IFERROR(((G$27+F$27)/2)/G$43*365,"n/a") | H17: =IFERROR(((H$27+G$27)/2)/H$43*365,"n/a") | I17: =IFERROR(((I$27+H$27)/2)/I$43*365,"n/a")
A18: Số ngày tồn kho (DIO) | B18: n/a | C18: =IFERROR(((C$28+B$28)/2)/ABS(C$44)*365,"n/a") | D18: =IFERROR(((D$28+C$28)/2)/ABS(D$44)*365,"n/a") | E18: =IFERROR(((E$28+D$28)/2)/ABS(E$44)*365,"n/a") | F18: =IFERROR(((F$28+E$28)/2)/ABS(F$44)*365,"n/a") | G18: =IFERROR(((G$28+F$28)/2)/ABS(G$44)*365,"n/a") | H18: =IFERROR(((H$28+G$28)/2)/ABS(H$44)*365,"n/a") | I18: =IFERROR(((I$28+H$28)/2)/ABS(I$44)*365,"n/a")
A19: Tiền và tương đương tiền/Tài sản | B19: =IFERROR(B$26/B$31,"n/a") | C19: =IFERROR(C$26/C$31,"n/a") | D19: =IFERROR(D$26/D$31,"n/a") | E19: =IFERROR(E$26/E$31,"n/a") | F19: =IFERROR(F$26/F$31,"n/a") | G19: =IFERROR(G$26/G$31,"n/a") | H19: =IFERROR(H$26/H$31,"n/a") | I19: =IFERROR(I$26/I$31,"n/a")
A20: Hàng tồn kho/Tài sản | B20: =IFERROR(B$28/B$31,"n/a") | C20: =IFERROR(C$28/C$31,"n/a") | D20: =IFERROR(D$28/D$31,"n/a") | E20: =IFERROR(E$28/E$31,"n/a") | F20: =IFERROR(F$28/F$31,"n/a") | G20: =IFERROR(G$28/G$31,"n/a") | H20: =IFERROR(H$28/H$31,"n/a") | I20: =IFERROR(I$28/I$31,"n/a")
A22: II. DỮ LIỆU TRÍCH XUẤT (tự động dò theo tên khoản mục)
A23: Khoản mục | B23: =balance_sheet!B1 | C23: =balance_sheet!C1 | D23: =balance_sheet!D1 | E23: =balance_sheet!E1 | F23: =balance_sheet!F1 | G23: =balance_sheet!G1 | H23: =balance_sheet!H1 | I23: =balance_sheet!I1
A24: CĐKT
A25: Tài sản
A26: Tiền và tương đương tiền | B26: =IFERROR(INDEX(balance_sheet!$B:$I,MATCH("Tiền và tương đương tiền",balance_sheet!$A:$A,0),MATCH(B$23,balance_sheet!$B$1:$I$1,0)),"") | C26: =IFERROR(INDEX(balance_sheet!$B:$I,MATCH("Tiền và tương đương tiền",balance_sheet!$A:$A,0),MATCH(C$23,balance_sheet!$B$1:$I$1,0)),"") | D26: =IFERROR(INDEX(balance_sheet!$B:$I,MATCH("Tiền và tương đương tiền",balance_sheet!$A:$A,0),MATCH(D$23,balance_sheet!$B$1:$I$1,0)),"") | E26: =IFERROR(INDEX(balance_sheet!$B:$I,MATCH("Tiền và tương đương tiền",balance_sheet!$A:$A,0),MATCH(E$23,balance_sheet!$B$1:$I$1,0)),"") | F26: =IFERROR(INDEX(balance_sheet!$B:$I,MATCH("Tiền và tương đương tiền",balance_sheet!$A:$A,0),MATCH(F$23,balance_sheet!$B$1:$I$1,0)),"") | G26: =IFERROR(INDEX(balance_sheet!$B:$I,MATCH("Tiền và tương đương tiền",balance_sheet!$A:$A,0),MATCH(G$23,balance_sheet!$B$1:$I$1,0)),"") | H26: =IFERROR(INDEX(balance_sheet!$B:$I,MATCH("Tiền và tương đương tiền",balance_sheet!$A:$A,0),MATCH(H$23,balance_sheet!$B$1:$I$1,0)),"") | I26: =IFERROR(INDEX(balance_sheet!$B:$I,MATCH("Tiền và tương đương tiền",balance_sheet!$A:$A,0),MATCH(I$23,balance_sheet!$B$1:$I$1,0)),"")
A27: Phải thu khách hàng | B27: =IFERROR(INDEX(balance_sheet!$B:$I,MATCH("Phải thu khách hàng",balance_sheet!$A:$A,0),MATCH(B$23,balance_sheet!$B$1:$I$1,0)),"") | C27: =IFERROR(INDEX(balance_sheet!$B:$I,MATCH("Phải thu khách hàng",balance_sheet!$A:$A,0),MATCH(C$23,balance_sheet!$B$1:$I$1,0)),"") | D27: =IFERROR(INDEX(balance_sheet!$B:$I,MATCH("Phải thu khách hàng",balance_sheet!$A:$A,0),MATCH(D$23,balance_sheet!$B$1:$I$1,0)),"") | E27: =IFERROR(INDEX(balance_sheet!$B:$I,MATCH("Phải thu khách hàng",balance_sheet!$A:$A,0),MATCH(E$23,balance_sheet!$B$1:$I$1,0)),"") | F27: =IFERROR(INDEX(balance_sheet!$B:$I,MATCH("Phải thu khách hàng",balance_sheet!$A:$A,0),MATCH(F$23,balance_sheet!$B$1:$I$1,0)),"") | G27: =IFERROR(INDEX(balance_sheet!$B:$I,MATCH("Phải thu khách hàng",balance_sheet!$A:$A,0),MATCH(G$23,balance_sheet!$B$1:$I$1,0)),"") | H27: =IFERROR(INDEX(balance_sheet!$B:$I,MATCH("Phải thu khách hàng",balance_sheet!$A:$A,0),MATCH(H$23,balance_sheet!$B$1:$I$1,0)),"") | I27: =IFERROR(INDEX(balance_sheet!$B:$I,MATCH("Phải thu khách hàng",balance_sheet!$A:$A,0),MATCH(I$23,balance_sheet!$B$1:$I$1,0)),"")
A28: Hàng tồn kho, ròng | B28: =IFERROR(INDEX(balance_sheet!$B:$I,MATCH("Hàng tồn kho, ròng",balance_sheet!$A:$A,0),MATCH(B$23,balance_sheet!$B$1:$I$1,0)),"") | C28: =IFERROR(INDEX(balance_sheet!$B:$I,MATCH("Hàng tồn kho, ròng",balance_sheet!$A:$A,0),MATCH(C$23,balance_sheet!$B$1:$I$1,0)),"") | D28: =IFERROR(INDEX(balance_sheet!$B:$I,MATCH("Hàng tồn kho, ròng",balance_sheet!$A:$A,0),MATCH(D$23,balance_sheet!$B$1:$I$1,0)),"") | E28: =IFERROR(INDEX(balance_sheet!$B:$I,MATCH("Hàng tồn kho, ròng",balance_sheet!$A:$A,0),MATCH(E$23,balance_sheet!$B$1:$I$1,0)),"") | F28: =IFERROR(INDEX(balance_sheet!$B:$I,MATCH("Hàng tồn kho, ròng",balance_sheet!$A:$A,0),MATCH(F$23,balance_sheet!$B$1:$I$1,0)),"") | G28: =IFERROR(INDEX(balance_sheet!$B:$I,MATCH("Hàng tồn kho, ròng",balance_sheet!$A:$A,0),MATCH(G$23,balance_sheet!$B$1:$I$1,0)),"") | H28: =IFERROR(INDEX(balance_sheet!$B:$I,MATCH("Hàng tồn kho, ròng",balance_sheet!$A:$A,0),MATCH(H$23,balance_sheet!$B$1:$I$1,0)),"") | I28: =IFERROR(INDEX(balance_sheet!$B:$I,MATCH("Hàng tồn kho, ròng",balance_sheet!$A:$A,0),MATCH(I$23,balance_sheet!$B$1:$I$1,0)),"")
A29: TÀI SẢN NGẮN HẠN | B29: =IFERROR(INDEX(balance_sheet!$B:$I,MATCH("TÀI SẢN NGẮN HẠN",balance_sheet!$A:$A,0),MATCH(B$23,balance_sheet!$B$1:$I$1,0)),"") | C29: =IFERROR(INDEX(balance_sheet!$B:$I,MATCH("TÀI SẢN NGẮN HẠN",balance_sheet!$A:$A,0),MATCH(C$23,balance_sheet!$B$1:$I$1,0)),"") | D29: =IFERROR(INDEX(balance_sheet!$B:$I,MATCH("TÀI SẢN NGẮN HẠN",balance_sheet!$A:$A,0),MATCH(D$23,balance_sheet!$B$1:$I$1,0)),"") | E29: =IFERROR(INDEX(balance_sheet!$B:$I,MATCH("TÀI SẢN NGẮN HẠN",balance_sheet!$A:$A,0),MATCH(E$23,balance_sheet!$B$1:$I$1,0)),"") | F29: =IFERROR(INDEX(balance_sheet!$B:$I,MATCH("TÀI SẢN NGẮN HẠN",balance_sheet!$A:$A,0),MATCH(F$23,balance_sheet!$B$1:$I$1,0)),"") | G29: =IFERROR(INDEX(balance_sheet!$B:$I,MATCH("TÀI SẢN NGẮN HẠN",balance_sheet!$A:$A,0),MATCH(G$23,balance_sheet!$B$1:$I$1,0)),"") | H29: =IFERROR(INDEX(balance_sheet!$B:$I,MATCH("TÀI SẢN NGẮN HẠN",balance_sheet!$A:$A,0),MATCH(H$23,balance_sheet!$B$1:$I$1,0)),"") | I29: =IFERROR(INDEX(balance_sheet!$B:$I,MATCH("TÀI SẢN NGẮN HẠN",balance_sheet!$A:$A,0),MATCH(I$23,balance_sheet!$B$1:$I$1,0)),"")
A30: GTCL tài sản cố định vô hình | B30: =IFERROR(INDEX(balance_sheet!$B:$I,MATCH("GTCL tài sản cố định vô hình",balance_sheet!$A:$A,0),MATCH(B$23,balance_sheet!$B$1:$I$1,0)),"") | C30: =IFERROR(INDEX(balance_sheet!$B:$I,MATCH("GTCL tài sản cố định vô hình",balance_sheet!$A:$A,0),MATCH(C$23,balance_sheet!$B$1:$I$1,0)),"") | D30: =IFERROR(INDEX(balance_sheet!$B:$I,MATCH("GTCL tài sản cố định vô hình",balance_sheet!$A:$A,0),MATCH(D$23,balance_sheet!$B$1:$I$1,0)),"") | E30: =IFERROR(INDEX(balance_sheet!$B:$I,MATCH("GTCL tài sản cố định vô hình",balance_sheet!$A:$A,0),MATCH(E$23,balance_sheet!$B$1:$I$1,0)),"") | F30: =IFERROR(INDEX(balance_sheet!$B:$I,MATCH("GTCL tài sản cố định vô hình",balance_sheet!$A:$A,0),MATCH(F$23,balance_sheet!$B$1:$I$1,0)),"") | G30: =IFERROR(INDEX(balance_sheet!$B:$I,MATCH("GTCL tài sản cố định vô hình",balance_sheet!$A:$A,0),MATCH(G$23,balance_sheet!$B$1:$I$1,0)),"") | H30: =IFERROR(INDEX(balance_sheet!$B:$I,MATCH("GTCL tài sản cố định vô hình",balance_sheet!$A:$A,0),MATCH(H$23,balance_sheet!$B$1:$I$1,0)),"") | I30: =IFERROR(INDEX(balance_sheet!$B:$I,MATCH("GTCL tài sản cố định vô hình",balance_sheet!$A:$A,0),MATCH(I$23,balance_sheet!$B$1:$I$1,0)),"")
A31: TỔNG CỘNG TÀI SẢN | B31: =IFERROR(INDEX(balance_sheet!$B:$I,MATCH("TỔNG CỘNG TÀI SẢN",balance_sheet!$A:$A,0),MATCH(B$23,balance_sheet!$B$1:$I$1,0)),"") | C31: =IFERROR(INDEX(balance_sheet!$B:$I,MATCH("TỔNG CỘNG TÀI SẢN",balance_sheet!$A:$A,0),MATCH(C$23,balance_sheet!$B$1:$I$1,0)),"") | D31: =IFERROR(INDEX(balance_sheet!$B:$I,MATCH("TỔNG CỘNG TÀI SẢN",balance_sheet!$A:$A,0),MATCH(D$23,balance_sheet!$B$1:$I$1,0)),"") | E31: =IFERROR(INDEX(balance_sheet!$B:$I,MATCH("TỔNG CỘNG TÀI SẢN",balance_sheet!$A:$A,0),MATCH(E$23,balance_sheet!$B$1:$I$1,0)),"") | F31: =IFERROR(INDEX(balance_sheet!$B:$I,MATCH("TỔNG CỘNG TÀI SẢN",balance_sheet!$A:$A,0),MATCH(F$23,balance_sheet!$B$1:$I$1,0)),"") | G31: =IFERROR(INDEX(balance_sheet!$B:$I,MATCH("TỔNG CỘNG TÀI SẢN",balance_sheet!$A:$A,0),MATCH(G$23,balance_sheet!$B$1:$I$1,0)),"") | H31: =IFERROR(INDEX(balance_sheet!$B:$I,MATCH("TỔNG CỘNG TÀI SẢN",balance_sheet!$A:$A,0),MATCH(H$23,balance_sheet!$B$1:$I$1,0)),"") | I31: =IFERROR(INDEX(balance_sheet!$B:$I,MATCH("TỔNG CỘNG TÀI SẢN",balance_sheet!$A:$A,0),MATCH(I$23,balance_sheet!$B$1:$I$1,0)),"")
A32: Nguồn vốn
A33: Phải trả người bán | B33: =IFERROR(INDEX(balance_sheet!$B:$I,MATCH("Phải trả người bán",balance_sheet!$A:$A,0),MATCH(B$23,balance_sheet!$B$1:$I$1,0)),"") | C33: =IFERROR(INDEX(balance_sheet!$B:$I,MATCH("Phải trả người bán",balance_sheet!$A:$A,0),MATCH(C$23,balance_sheet!$B$1:$I$1,0)),"") | D33: =IFERROR(INDEX(balance_sheet!$B:$I,MATCH("Phải trả người bán",balance_sheet!$A:$A,0),MATCH(D$23,balance_sheet!$B$1:$I$1,0)),"") | E33: =IFERROR(INDEX(balance_sheet!$B:$I,MATCH("Phải trả người bán",balance_sheet!$A:$A,0),MATCH(E$23,balance_sheet!$B$1:$I$1,0)),"") | F33: =IFERROR(INDEX(balance_sheet!$B:$I,MATCH("Phải trả người bán",balance_sheet!$A:$A,0),MATCH(F$23,balance_sheet!$B$1:$I$1,0)),"") | G33: =IFERROR(INDEX(balance_sheet!$B:$I,MATCH("Phải trả người bán",balance_sheet!$A:$A,0),MATCH(G$23,balance_sheet!$B$1:$I$1,0)),"") | H33: =IFERROR(INDEX(balance_sheet!$B:$I,MATCH("Phải trả người bán",balance_sheet!$A:$A,0),MATCH(H$23,balance_sheet!$B$1:$I$1,0)),"") | I33: =IFERROR(INDEX(balance_sheet!$B:$I,MATCH("Phải trả người bán",balance_sheet!$A:$A,0),MATCH(I$23,balance_sheet!$B$1:$I$1,0)),"")
A34: Vay ngắn hạn | B34: =IFERROR(INDEX(balance_sheet!$B:$I,MATCH("Vay ngắn hạn",balance_sheet!$A:$A,0),MATCH(B$23,balance_sheet!$B$1:$I$1,0)),"") | C34: =IFERROR(INDEX(balance_sheet!$B:$I,MATCH("Vay ngắn hạn",balance_sheet!$A:$A,0),MATCH(C$23,balance_sheet!$B$1:$I$1,0)),"") | D34: =IFERROR(INDEX(balance_sheet!$B:$I,MATCH("Vay ngắn hạn",balance_sheet!$A:$A,0),MATCH(D$23,balance_sheet!$B$1:$I$1,0)),"") | E34: =IFERROR(INDEX(balance_sheet!$B:$I,MATCH("Vay ngắn hạn",balance_sheet!$A:$A,0),MATCH(E$23,balance_sheet!$B$1:$I$1,0)),"") | F34: =IFERROR(INDEX(balance_sheet!$B:$I,MATCH("Vay ngắn hạn",balance_sheet!$A:$A,0),MATCH(F$23,balance_sheet!$B$1:$I$1,0)),"") | G34: =IFERROR(INDEX(balance_sheet!$B:$I,MATCH("Vay ngắn hạn",balance_sheet!$A:$A,0),MATCH(G$23,balance_sheet!$B$1:$I$1,0)),"") | H34: =IFERROR(INDEX(balance_sheet!$B:$I,MATCH("Vay ngắn hạn",balance_sheet!$A:$A,0),MATCH(H$23,balance_sheet!$B$1:$I$1,0)),"") | I34: =IFERROR(INDEX(balance_sheet!$B:$I,MATCH("Vay ngắn hạn",balance_sheet!$A:$A,0),MATCH(I$23,balance_sheet!$B$1:$I$1,0)),"")
A35: Nợ ngắn hạn | B35: =IFERROR(INDEX(balance_sheet!$B:$I,MATCH("Nợ ngắn hạn",balance_sheet!$A:$A,0),MATCH(B$23,balance_sheet!$B$1:$I$1,0)),"") | C35: =IFERROR(INDEX(balance_sheet!$B:$I,MATCH("Nợ ngắn hạn",balance_sheet!$A:$A,0),MATCH(C$23,balance_sheet!$B$1:$I$1,0)),"") | D35: =IFERROR(INDEX(balance_sheet!$B:$I,MATCH("Nợ ngắn hạn",balance_sheet!$A:$A,0),MATCH(D$23,balance_sheet!$B$1:$I$1,0)),"") | E35: =IFERROR(INDEX(balance_sheet!$B:$I,MATCH("Nợ ngắn hạn",balance_sheet!$A:$A,0),MATCH(E$23,balance_sheet!$B$1:$I$1,0)),"") | F35: =IFERROR(INDEX(balance_sheet!$B:$I,MATCH("Nợ ngắn hạn",balance_sheet!$A:$A,0),MATCH(F$23,balance_sheet!$B$1:$I$1,0)),"") | G35: =IFERROR(INDEX(balance_sheet!$B:$I,MATCH("Nợ ngắn hạn",balance_sheet!$A:$A,0),MATCH(G$23,balance_sheet!$B$1:$I$1,0)),"") | H35: =IFERROR(INDEX(balance_sheet!$B:$I,MATCH("Nợ ngắn hạn",balance_sheet!$A:$A,0),MATCH(H$23,balance_sheet!$B$1:$I$1,0)),"") | I35: =IFERROR(INDEX(balance_sheet!$B:$I,MATCH("Nợ ngắn hạn",balance_sheet!$A:$A,0),MATCH(I$23,balance_sheet!$B$1:$I$1,0)),"")
A36: Vay dài hạn | B36: =IFERROR(INDEX(balance_sheet!$B:$I,MATCH("Vay dài hạn",balance_sheet!$A:$A,0),MATCH(B$23,balance_sheet!$B$1:$I$1,0)),"") | C36: =IFERROR(INDEX(balance_sheet!$B:$I,MATCH("Vay dài hạn",balance_sheet!$A:$A,0),MATCH(C$23,balance_sheet!$B$1:$I$1,0)),"") | D36: =IFERROR(INDEX(balance_sheet!$B:$I,MATCH("Vay dài hạn",balance_sheet!$A:$A,0),MATCH(D$23,balance_sheet!$B$1:$I$1,0)),"") | E36: =IFERROR(INDEX(balance_sheet!$B:$I,MATCH("Vay dài hạn",balance_sheet!$A:$A,0),MATCH(E$23,balance_sheet!$B$1:$I$1,0)),"") | F36: =IFERROR(INDEX(balance_sheet!$B:$I,MATCH("Vay dài hạn",balance_sheet!$A:$A,0),MATCH(F$23,balance_sheet!$B$1:$I$1,0)),"") | G36: =IFERROR(INDEX(balance_sheet!$B:$I,MATCH("Vay dài hạn",balance_sheet!$A:$A,0),MATCH(G$23,balance_sheet!$B$1:$I$1,0)),"") | H36: =IFERROR(INDEX(balance_sheet!$B:$I,MATCH("Vay dài hạn",balance_sheet!$A:$A,0),MATCH(H$23,balance_sheet!$B$1:$I$1,0)),"") | I36: =IFERROR(INDEX(balance_sheet!$B:$I,MATCH("Vay dài hạn",balance_sheet!$A:$A,0),MATCH(I$23,balance_sheet!$B$1:$I$1,0)),"")
A37: Nợ dài hạn | B37: =IFERROR(INDEX(balance_sheet!$B:$I,MATCH("Nợ dài hạn",balance_sheet!$A:$A,0),MATCH(B$23,balance_sheet!$B$1:$I$1,0)),"") | C37: =IFERROR(INDEX(balance_sheet!$B:$I,MATCH("Nợ dài hạn",balance_sheet!$A:$A,0),MATCH(C$23,balance_sheet!$B$1:$I$1,0)),"") | D37: =IFERROR(INDEX(balance_sheet!$B:$I,MATCH("Nợ dài hạn",balance_sheet!$A:$A,0),MATCH(D$23,balance_sheet!$B$1:$I$1,0)),"") | E37: =IFERROR(INDEX(balance_sheet!$B:$I,MATCH("Nợ dài hạn",balance_sheet!$A:$A,0),MATCH(E$23,balance_sheet!$B$1:$I$1,0)),"") | F37: =IFERROR(INDEX(balance_sheet!$B:$I,MATCH("Nợ dài hạn",balance_sheet!$A:$A,0),MATCH(F$23,balance_sheet!$B$1:$I$1,0)),"") | G37: =IFERROR(INDEX(balance_sheet!$B:$I,MATCH("Nợ dài hạn",balance_sheet!$A:$A,0),MATCH(G$23,balance_sheet!$B$1:$I$1,0)),"") | H37: =IFERROR(INDEX(balance_sheet!$B:$I,MATCH("Nợ dài hạn",balance_sheet!$A:$A,0),MATCH(H$23,balance_sheet!$B$1:$I$1,0)),"") | I37: =IFERROR(INDEX(balance_sheet!$B:$I,MATCH("Nợ dài hạn",balance_sheet!$A:$A,0),MATCH(I$23,balance_sheet!$B$1:$I$1,0)),"")
A38: NỢ PHẢI TRẢ | B38: =IFERROR(INDEX(balance_sheet!$B:$I,MATCH("NỢ PHẢI TRẢ",balance_sheet!$A:$A,0),MATCH(B$23,balance_sheet!$B$1:$I$1,0)),"") | C38: =IFERROR(INDEX(balance_sheet!$B:$I,MATCH("NỢ PHẢI TRẢ",balance_sheet!$A:$A,0),MATCH(C$23,balance_sheet!$B$1:$I$1,0)),"") | D38: =IFERROR(INDEX(balance_sheet!$B:$I,MATCH("NỢ PHẢI TRẢ",balance_sheet!$A:$A,0),MATCH(D$23,balance_sheet!$B$1:$I$1,0)),"") | E38: =IFERROR(INDEX(balance_sheet!$B:$I,MATCH("NỢ PHẢI TRẢ",balance_sheet!$A:$A,0),MATCH(E$23,balance_sheet!$B$1:$I$1,0)),"") | F38: =IFERROR(INDEX(balance_sheet!$B:$I,MATCH("NỢ PHẢI TRẢ",balance_sheet!$A:$A,0),MATCH(F$23,balance_sheet!$B$1:$I$1,0)),"") | G38: =IFERROR(INDEX(balance_sheet!$B:$I,MATCH("NỢ PHẢI TRẢ",balance_sheet!$A:$A,0),MATCH(G$23,balance_sheet!$B$1:$I$1,0)),"") | H38: =IFERROR(INDEX(balance_sheet!$B:$I,MATCH("NỢ PHẢI TRẢ",balance_sheet!$A:$A,0),MATCH(H$23,balance_sheet!$B$1:$I$1,0)),"") | I38: =IFERROR(INDEX(balance_sheet!$B:$I,MATCH("NỢ PHẢI TRẢ",balance_sheet!$A:$A,0),MATCH(I$23,balance_sheet!$B$1:$I$1,0)),"")
A39: Vốn chủ sở hữu | B39: =IFERROR(INDEX(balance_sheet!$B:$I,MATCH("Vốn chủ sở hữu",balance_sheet!$A:$A,0),MATCH(B$23,balance_sheet!$B$1:$I$1,0)),"") | C39: =IFERROR(INDEX(balance_sheet!$B:$I,MATCH("Vốn chủ sở hữu",balance_sheet!$A:$A,0),MATCH(C$23,balance_sheet!$B$1:$I$1,0)),"") | D39: =IFERROR(INDEX(balance_sheet!$B:$I,MATCH("Vốn chủ sở hữu",balance_sheet!$A:$A,0),MATCH(D$23,balance_sheet!$B$1:$I$1,0)),"") | E39: =IFERROR(INDEX(balance_sheet!$B:$I,MATCH("Vốn chủ sở hữu",balance_sheet!$A:$A,0),MATCH(E$23,balance_sheet!$B$1:$I$1,0)),"") | F39: =IFERROR(INDEX(balance_sheet!$B:$I,MATCH("Vốn chủ sở hữu",balance_sheet!$A:$A,0),MATCH(F$23,balance_sheet!$B$1:$I$1,0)),"") | G39: =IFERROR(INDEX(balance_sheet!$B:$I,MATCH("Vốn chủ sở hữu",balance_sheet!$A:$A,0),MATCH(G$23,balance_sheet!$B$1:$I$1,0)),"") | H39: =IFERROR(INDEX(balance_sheet!$B:$I,MATCH("Vốn chủ sở hữu",balance_sheet!$A:$A,0),MATCH(H$23,balance_sheet!$B$1:$I$1,0)),"") | I39: =IFERROR(INDEX(balance_sheet!$B:$I,MATCH("Vốn chủ sở hữu",balance_sheet!$A:$A,0),MATCH(I$23,balance_sheet!$B$1:$I$1,0)),"") | J39: =I39+0.95*J51
A40: Tăng VCSH/LN cổ đông cty mẹ | C40: =(C39-B39)/C51 | D40: =(D39-C39)/D51 | E40: =(E39-D39)/E51 | F40: =(F39-E39)/F51 | G40: =(G39-F39)/G51 | H40: =(H39-G39)/H51 | I40: =(I39-H39)/I51
A41: Lợi ích cổ đông không kiểm soát | B41: =IFERROR(INDEX(balance_sheet!$B:$I,MATCH("Lợi ích cổ đông không kiểm soát",balance_sheet!$A:$A,0),MATCH(B$23,balance_sheet!$B$1:$I$1,0)),"") | C41: =IFERROR(INDEX(balance_sheet!$B:$I,MATCH("Lợi ích cổ đông không kiểm soát",balance_sheet!$A:$A,0),MATCH(C$23,balance_sheet!$B$1:$I$1,0)),"") | D41: =IFERROR(INDEX(balance_sheet!$B:$I,MATCH("Lợi ích cổ đông không kiểm soát",balance_sheet!$A:$A,0),MATCH(D$23,balance_sheet!$B$1:$I$1,0)),"") | E41: =IFERROR(INDEX(balance_sheet!$B:$I,MATCH("Lợi ích cổ đông không kiểm soát",balance_sheet!$A:$A,0),MATCH(E$23,balance_sheet!$B$1:$I$1,0)),"") | F41: =IFERROR(INDEX(balance_sheet!$B:$I,MATCH("Lợi ích cổ đông không kiểm soát",balance_sheet!$A:$A,0),MATCH(F$23,balance_sheet!$B$1:$I$1,0)),"") | G41: =IFERROR(INDEX(balance_sheet!$B:$I,MATCH("Lợi ích cổ đông không kiểm soát",balance_sheet!$A:$A,0),MATCH(G$23,balance_sheet!$B$1:$I$1,0)),"") | H41: =IFERROR(INDEX(balance_sheet!$B:$I,MATCH("Lợi ích cổ đông không kiểm soát",balance_sheet!$A:$A,0),MATCH(H$23,balance_sheet!$B$1:$I$1,0)),"") | I41: =IFERROR(INDEX(balance_sheet!$B:$I,MATCH("Lợi ích cổ đông không kiểm soát",balance_sheet!$A:$A,0),MATCH(I$23,balance_sheet!$B$1:$I$1,0)),"")
A42: Kết quả hoạt động kinh doanh
A43: Doanh thu thuần | B43: =IFERROR(INDEX(income_statement!$B:$I,MATCH("Doanh thu thuần",income_statement!$A:$A,0),MATCH(B$23,income_statement!$B$1:$I$1,0)),"") | C43: =IFERROR(INDEX(income_statement!$B:$I,MATCH("Doanh thu thuần",income_statement!$A:$A,0),MATCH(C$23,income_statement!$B$1:$I$1,0)),"") | D43: =IFERROR(INDEX(income_statement!$B:$I,MATCH("Doanh thu thuần",income_statement!$A:$A,0),MATCH(D$23,income_statement!$B$1:$I$1,0)),"") | E43: =IFERROR(INDEX(income_statement!$B:$I,MATCH("Doanh thu thuần",income_statement!$A:$A,0),MATCH(E$23,income_statement!$B$1:$I$1,0)),"") | F43: =IFERROR(INDEX(income_statement!$B:$I,MATCH("Doanh thu thuần",income_statement!$A:$A,0),MATCH(F$23,income_statement!$B$1:$I$1,0)),"") | G43: =IFERROR(INDEX(income_statement!$B:$I,MATCH("Doanh thu thuần",income_statement!$A:$A,0),MATCH(G$23,income_statement!$B$1:$I$1,0)),"") | H43: =IFERROR(INDEX(income_statement!$B:$I,MATCH("Doanh thu thuần",income_statement!$A:$A,0),MATCH(H$23,income_statement!$B$1:$I$1,0)),"") | I43: =IFERROR(INDEX(income_statement!$B:$I,MATCH("Doanh thu thuần",income_statement!$A:$A,0),MATCH(I$23,income_statement!$B$1:$I$1,0)),"") | J43: 210000000000000
A44: Giá vốn hàng bán | B44: =IFERROR(INDEX(income_statement!$B:$I,MATCH("Giá vốn hàng bán",income_statement!$A:$A,0),MATCH(B$23,income_statement!$B$1:$I$1,0)),"") | C44: =IFERROR(INDEX(income_statement!$B:$I,MATCH("Giá vốn hàng bán",income_statement!$A:$A,0),MATCH(C$23,income_statement!$B$1:$I$1,0)),"") | D44: =IFERROR(INDEX(income_statement!$B:$I,MATCH("Giá vốn hàng bán",income_statement!$A:$A,0),MATCH(D$23,income_statement!$B$1:$I$1,0)),"") | E44: =IFERROR(INDEX(income_statement!$B:$I,MATCH("Giá vốn hàng bán",income_statement!$A:$A,0),MATCH(E$23,income_statement!$B$1:$I$1,0)),"") | F44: =IFERROR(INDEX(income_statement!$B:$I,MATCH("Giá vốn hàng bán",income_statement!$A:$A,0),MATCH(F$23,income_statement!$B$1:$I$1,0)),"") | G44: =IFERROR(INDEX(income_statement!$B:$I,MATCH("Giá vốn hàng bán",income_statement!$A:$A,0),MATCH(G$23,income_statement!$B$1:$I$1,0)),"") | H44: =IFERROR(INDEX(income_statement!$B:$I,MATCH("Giá vốn hàng bán",income_statement!$A:$A,0),MATCH(H$23,income_statement!$B$1:$I$1,0)),"") | I44: =IFERROR(INDEX(income_statement!$B:$I,MATCH("Giá vốn hàng bán",income_statement!$A:$A,0),MATCH(I$23,income_statement!$B$1:$I$1,0)),"")
A45: Lợi nhuận gộp | B45: =IFERROR(INDEX(income_statement!$B:$I,MATCH("Lợi nhuận gộp",income_statement!$A:$A,0),MATCH(B$23,income_statement!$B$1:$I$1,0)),"") | C45: =IFERROR(INDEX(income_statement!$B:$I,MATCH("Lợi nhuận gộp",income_statement!$A:$A,0),MATCH(C$23,income_statement!$B$1:$I$1,0)),"") | D45: =IFERROR(INDEX(income_statement!$B:$I,MATCH("Lợi nhuận gộp",income_statement!$A:$A,0),MATCH(D$23,income_statement!$B$1:$I$1,0)),"") | E45: =IFERROR(INDEX(income_statement!$B:$I,MATCH("Lợi nhuận gộp",income_statement!$A:$A,0),MATCH(E$23,income_statement!$B$1:$I$1,0)),"") | F45: =IFERROR(INDEX(income_statement!$B:$I,MATCH("Lợi nhuận gộp",income_statement!$A:$A,0),MATCH(F$23,income_statement!$B$1:$I$1,0)),"") | G45: =IFERROR(INDEX(income_statement!$B:$I,MATCH("Lợi nhuận gộp",income_statement!$A:$A,0),MATCH(G$23,income_statement!$B$1:$I$1,0)),"") | H45: =IFERROR(INDEX(income_statement!$B:$I,MATCH("Lợi nhuận gộp",income_statement!$A:$A,0),MATCH(H$23,income_statement!$B$1:$I$1,0)),"") | I45: =IFERROR(INDEX(income_statement!$B:$I,MATCH("Lợi nhuận gộp",income_statement!$A:$A,0),MATCH(I$23,income_statement!$B$1:$I$1,0)),"")
A46: Chi phí bán hàng | B46: =IFERROR(INDEX(income_statement!$B:$I,MATCH("Chi phí bán hàng",income_statement!$A:$A,0),MATCH(B$23,income_statement!$B$1:$I$1,0)),"") | C46: =IFERROR(INDEX(income_statement!$B:$I,MATCH("Chi phí bán hàng",income_statement!$A:$A,0),MATCH(C$23,income_statement!$B$1:$I$1,0)),"") | D46: =IFERROR(INDEX(income_statement!$B:$I,MATCH("Chi phí bán hàng",income_statement!$A:$A,0),MATCH(D$23,income_statement!$B$1:$I$1,0)),"") | E46: =IFERROR(INDEX(income_statement!$B:$I,MATCH("Chi phí bán hàng",income_statement!$A:$A,0),MATCH(E$23,income_statement!$B$1:$I$1,0)),"") | F46: =IFERROR(INDEX(income_statement!$B:$I,MATCH("Chi phí bán hàng",income_statement!$A:$A,0),MATCH(F$23,income_statement!$B$1:$I$1,0)),"") | G46: =IFERROR(INDEX(income_statement!$B:$I,MATCH("Chi phí bán hàng",income_statement!$A:$A,0),MATCH(G$23,income_statement!$B$1:$I$1,0)),"") | H46: =IFERROR(INDEX(income_statement!$B:$I,MATCH("Chi phí bán hàng",income_statement!$A:$A,0),MATCH(H$23,income_statement!$B$1:$I$1,0)),"") | I46: =IFERROR(INDEX(income_statement!$B:$I,MATCH("Chi phí bán hàng",income_statement!$A:$A,0),MATCH(I$23,income_statement!$B$1:$I$1,0)),"")
A47: Chi phí quản lý doanh nghiệp | B47: =IFERROR(INDEX(income_statement!$B:$I,MATCH("Chi phí quản lý doanh nghiệp",income_statement!$A:$A,0),MATCH(B$23,income_statement!$B$1:$I$1,0)),"") | C47: =IFERROR(INDEX(income_statement!$B:$I,MATCH("Chi phí quản lý doanh nghiệp",income_statement!$A:$A,0),MATCH(C$23,income_statement!$B$1:$I$1,0)),"") | D47: =IFERROR(INDEX(income_statement!$B:$I,MATCH("Chi phí quản lý doanh nghiệp",income_statement!$A:$A,0),MATCH(D$23,income_statement!$B$1:$I$1,0)),"") | E47: =IFERROR(INDEX(income_statement!$B:$I,MATCH("Chi phí quản lý doanh nghiệp",income_statement!$A:$A,0),MATCH(E$23,income_statement!$B$1:$I$1,0)),"") | F47: =IFERROR(INDEX(income_statement!$B:$I,MATCH("Chi phí quản lý doanh nghiệp",income_statement!$A:$A,0),MATCH(F$23,income_statement!$B$1:$I$1,0)),"") | G47: =IFERROR(INDEX(income_statement!$B:$I,MATCH("Chi phí quản lý doanh nghiệp",income_statement!$A:$A,0),MATCH(G$23,income_statement!$B$1:$I$1,0)),"") | H47: =IFERROR(INDEX(income_statement!$B:$I,MATCH("Chi phí quản lý doanh nghiệp",income_statement!$A:$A,0),MATCH(H$23,income_statement!$B$1:$I$1,0)),"") | I47: =IFERROR(INDEX(income_statement!$B:$I,MATCH("Chi phí quản lý doanh nghiệp",income_statement!$A:$A,0),MATCH(I$23,income_statement!$B$1:$I$1,0)),"")
A48: Lãi/(lỗ) từ hoạt động kinh doanh | B48: =IFERROR(INDEX(income_statement!$B:$I,MATCH("Lãi/(lỗ) từ hoạt động kinh doanh",income_statement!$A:$A,0),MATCH(B$23,income_statement!$B$1:$I$1,0)),"") | C48: =IFERROR(INDEX(income_statement!$B:$I,MATCH("Lãi/(lỗ) từ hoạt động kinh doanh",income_statement!$A:$A,0),MATCH(C$23,income_statement!$B$1:$I$1,0)),"") | D48: =IFERROR(INDEX(income_statement!$B:$I,MATCH("Lãi/(lỗ) từ hoạt động kinh doanh",income_statement!$A:$A,0),MATCH(D$23,income_statement!$B$1:$I$1,0)),"") | E48: =IFERROR(INDEX(income_statement!$B:$I,MATCH("Lãi/(lỗ) từ hoạt động kinh doanh",income_statement!$A:$A,0),MATCH(E$23,income_statement!$B$1:$I$1,0)),"") | F48: =IFERROR(INDEX(income_statement!$B:$I,MATCH("Lãi/(lỗ) từ hoạt động kinh doanh",income_statement!$A:$A,0),MATCH(F$23,income_statement!$B$1:$I$1,0)),"") | G48: =IFERROR(INDEX(income_statement!$B:$I,MATCH("Lãi/(lỗ) từ hoạt động kinh doanh",income_statement!$A:$A,0),MATCH(G$23,income_statement!$B$1:$I$1,0)),"") | H48: =IFERROR(INDEX(income_statement!$B:$I,MATCH("Lãi/(lỗ) từ hoạt động kinh doanh",income_statement!$A:$A,0),MATCH(H$23,income_statement!$B$1:$I$1,0)),"") | I48: =IFERROR(INDEX(income_statement!$B:$I,MATCH("Lãi/(lỗ) từ hoạt động kinh doanh",income_statement!$A:$A,0),MATCH(I$23,income_statement!$B$1:$I$1,0)),"")
A49: Chi phí lãi vay | B49: =IFERROR(INDEX(income_statement!$B:$I,MATCH("Chi phí lãi vay",income_statement!$A:$A,0),MATCH(B$23,income_statement!$B$1:$I$1,0)),"") | C49: =IFERROR(INDEX(income_statement!$B:$I,MATCH("Chi phí lãi vay",income_statement!$A:$A,0),MATCH(C$23,income_statement!$B$1:$I$1,0)),"") | D49: =IFERROR(INDEX(income_statement!$B:$I,MATCH("Chi phí lãi vay",income_statement!$A:$A,0),MATCH(D$23,income_statement!$B$1:$I$1,0)),"") | E49: =IFERROR(INDEX(income_statement!$B:$I,MATCH("Chi phí lãi vay",income_statement!$A:$A,0),MATCH(E$23,income_statement!$B$1:$I$1,0)),"") | F49: =IFERROR(INDEX(income_statement!$B:$I,MATCH("Chi phí lãi vay",income_statement!$A:$A,0),MATCH(F$23,income_statement!$B$1:$I$1,0)),"") | G49: =IFERROR(INDEX(income_statement!$B:$I,MATCH("Chi phí lãi vay",income_statement!$A:$A,0),MATCH(G$23,income_statement!$B$1:$I$1,0)),"") | H49: =IFERROR(INDEX(income_statement!$B:$I,MATCH("Chi phí lãi vay",income_statement!$A:$A,0),MATCH(H$23,income_statement!$B$1:$I$1,0)),"") | I49: =IFERROR(INDEX(income_statement!$B:$I,MATCH("Chi phí lãi vay",income_statement!$A:$A,0),MATCH(I$23,income_statement!$B$1:$I$1,0)),"")
A50: Lãi/(lỗ) thuần sau thuế | B50: =IFERROR(INDEX(income_statement!$B:$I,MATCH("Lãi/(lỗ) thuần sau thuế",income_statement!$A:$A,0),MATCH(B$23,income_statement!$B$1:$I$1,0)),"") | C50: =IFERROR(INDEX(income_statement!$B:$I,MATCH("Lãi/(lỗ) thuần sau thuế",income_statement!$A:$A,0),MATCH(C$23,income_statement!$B$1:$I$1,0)),"") | D50: =IFERROR(INDEX(income_statement!$B:$I,MATCH("Lãi/(lỗ) thuần sau thuế",income_statement!$A:$A,0),MATCH(D$23,income_statement!$B$1:$I$1,0)),"") | E50: =IFERROR(INDEX(income_statement!$B:$I,MATCH("Lãi/(lỗ) thuần sau thuế",income_statement!$A:$A,0),MATCH(E$23,income_statement!$B$1:$I$1,0)),"") | F50: =IFERROR(INDEX(income_statement!$B:$I,MATCH("Lãi/(lỗ) thuần sau thuế",income_statement!$A:$A,0),MATCH(F$23,income_statement!$B$1:$I$1,0)),"") | G50: =IFERROR(INDEX(income_statement!$B:$I,MATCH("Lãi/(lỗ) thuần sau thuế",income_statement!$A:$A,0),MATCH(G$23,income_statement!$B$1:$I$1,0)),"") | H50: =IFERROR(INDEX(income_statement!$B:$I,MATCH("Lãi/(lỗ) thuần sau thuế",income_statement!$A:$A,0),MATCH(H$23,income_statement!$B$1:$I$1,0)),"") | I50: =IFERROR(INDEX(income_statement!$B:$I,MATCH("Lãi/(lỗ) thuần sau thuế",income_statement!$A:$A,0),MATCH(I$23,income_statement!$B$1:$I$1,0)),"") | J50: 22000000000000
A51: Lợi nhuận của Cổ đông của Công ty mẹ | B51: =IFERROR(INDEX(income_statement!$B:$I,MATCH("Lợi nhuận của Cổ đông của Công ty mẹ",income_statement!$A:$A,0),MATCH(B$23,income_statement!$B$1:$I$1,0)),"") | C51: =IFERROR(INDEX(income_statement!$B:$I,MATCH("Lợi nhuận của Cổ đông của Công ty mẹ",income_statement!$A:$A,0),MATCH(C$23,income_statement!$B$1:$I$1,0)),"") | D51: =IFERROR(INDEX(income_statement!$B:$I,MATCH("Lợi nhuận của Cổ đông của Công ty mẹ",income_statement!$A:$A,0),MATCH(D$23,income_statement!$B$1:$I$1,0)),"") | E51: =IFERROR(INDEX(income_statement!$B:$I,MATCH("Lợi nhuận của Cổ đông của Công ty mẹ",income_statement!$A:$A,0),MATCH(E$23,income_statement!$B$1:$I$1,0)),"") | F51: =IFERROR(INDEX(income_statement!$B:$I,MATCH("Lợi nhuận của Cổ đông của Công ty mẹ",income_statement!$A:$A,0),MATCH(F$23,income_statement!$B$1:$I$1,0)),"") | G51: =IFERROR(INDEX(income_statement!$B:$I,MATCH("Lợi nhuận của Cổ đông của Công ty mẹ",income_statement!$A:$A,0),MATCH(G$23,income_statement!$B$1:$I$1,0)),"") | H51: =IFERROR(INDEX(income_statement!$B:$I,MATCH("Lợi nhuận của Cổ đông của Công ty mẹ",income_statement!$A:$A,0),MATCH(H$23,income_statement!$B$1:$I$1,0)),"") | I51: =IFERROR(INDEX(income_statement!$B:$I,MATCH("Lợi nhuận của Cổ đông của Công ty mẹ",income_statement!$A:$A,0),MATCH(I$23,income_statement!$B$1:$I$1,0)),"") | J51: 22000000000000
A52: Lưu chuyển tiền tệ
A53: Khấu hao TSCĐ và BĐSĐT | B53: =IFERROR(INDEX(cash_flow!$B:$I,MATCH("Khấu hao TSCĐ và BĐSĐT",cash_flow!$A:$A,0),MATCH(B$23,cash_flow!$B$1:$I$1,0)),"") | C53: =IFERROR(INDEX(cash_flow!$B:$I,MATCH("Khấu hao TSCĐ và BĐSĐT",cash_flow!$A:$A,0),MATCH(C$23,cash_flow!$B$1:$I$1,0)),"") | D53: =IFERROR(INDEX(cash_flow!$B:$I,MATCH("Khấu hao TSCĐ và BĐSĐT",cash_flow!$A:$A,0),MATCH(D$23,cash_flow!$B$1:$I$1,0)),"") | E53: =IFERROR(INDEX(cash_flow!$B:$I,MATCH("Khấu hao TSCĐ và BĐSĐT",cash_flow!$A:$A,0),MATCH(E$23,cash_flow!$B$1:$I$1,0)),"") | F53: =IFERROR(INDEX(cash_flow!$B:$I,MATCH("Khấu hao TSCĐ và BĐSĐT",cash_flow!$A:$A,0),MATCH(F$23,cash_flow!$B$1:$I$1,0)),"") | G53: =IFERROR(INDEX(cash_flow!$B:$I,MATCH("Khấu hao TSCĐ và BĐSĐT",cash_flow!$A:$A,0),MATCH(G$23,cash_flow!$B$1:$I$1,0)),"") | H53: =IFERROR(INDEX(cash_flow!$B:$I,MATCH("Khấu hao TSCĐ và BĐSĐT",cash_flow!$A:$A,0),MATCH(H$23,cash_flow!$B$1:$I$1,0)),"") | I53: =IFERROR(INDEX(cash_flow!$B:$I,MATCH("Khấu hao TSCĐ và BĐSĐT",cash_flow!$A:$A,0),MATCH(I$23,cash_flow!$B$1:$I$1,0)),"")
A54: Tiền chi để mua sắm, xây dựng TSCĐ và các tài sản dài hạn khác | B54: =IFERROR(INDEX(cash_flow!$B:$I,MATCH("Tiền chi để mua sắm, xây dựng TSCĐ và các tài sản dài hạn khác",cash_flow!$A:$A,0),MATCH(B$23,cash_flow!$B$1:$I$1,0)),"") | C54: =IFERROR(INDEX(cash_flow!$B:$I,MATCH("Tiền chi để mua sắm, xây dựng TSCĐ và các tài sản dài hạn khác",cash_flow!$A:$A,0),MATCH(C$23,cash_flow!$B$1:$I$1,0)),"") | D54: =IFERROR(INDEX(cash_flow!$B:$I,MATCH("Tiền chi để mua sắm, xây dựng TSCĐ và các tài sản dài hạn khác",cash_flow!$A:$A,0),MATCH(D$23,cash_flow!$B$1:$I$1,0)),"") | E54: =IFERROR(INDEX(cash_flow!$B:$I,MATCH("Tiền chi để mua sắm, xây dựng TSCĐ và các tài sản dài hạn khác",cash_flow!$A:$A,0),MATCH(E$23,cash_flow!$B$1:$I$1,0)),"") | F54: =IFERROR(INDEX(cash_flow!$B:$I,MATCH("Tiền chi để mua sắm, xây dựng TSCĐ và các tài sản dài hạn khác",cash_flow!$A:$A,0),MATCH(F$23,cash_flow!$B$1:$I$1,0)),"") | G54: =IFERROR(INDEX(cash_flow!$B:$I,MATCH("Tiền chi để mua sắm, xây dựng TSCĐ và các tài sản dài hạn khác",cash_flow!$A:$A,0),MATCH(G$23,cash_flow!$B$1:$I$1,0)),"") | H54: =IFERROR(INDEX(cash_flow!$B:$I,MATCH("Tiền chi để mua sắm, xây dựng TSCĐ và các tài sản dài hạn khác",cash_flow!$A:$A,0),MATCH(H$23,cash_flow!$B$1:$I$1,0)),"") | I54: =IFERROR(INDEX(cash_flow!$B:$I,MATCH("Tiền chi để mua sắm, xây dựng TSCĐ và các tài sản dài hạn khác",cash_flow!$A:$A,0),MATCH(I$23,cash_flow!$B$1:$I$1,0)),"")
A55: Lưu chuyển tiền tệ ròng từ các hoạt động sản xuất kinh doanh | B55: =IFERROR(INDEX(cash_flow!$B:$I,MATCH("Lưu chuyển tiền tệ ròng từ các hoạt động sản xuất kinh doanh",cash_flow!$A:$A,0),MATCH(B$23,cash_flow!$B$1:$I$1,0)),"") | C55: =IFERROR(INDEX(cash_flow!$B:$I,MATCH("Lưu chuyển tiền tệ ròng từ các hoạt động sản xuất kinh doanh",cash_flow!$A:$A,0),MATCH(C$23,cash_flow!$B$1:$I$1,0)),"") | D55: =IFERROR(INDEX(cash_flow!$B:$I,MATCH("Lưu chuyển tiền tệ ròng từ các hoạt động sản xuất kinh doanh",cash_flow!$A:$A,0),MATCH(D$23,cash_flow!$B$1:$I$1,0)),"") | E55: =IFERROR(INDEX(cash_flow!$B:$I,MATCH("Lưu chuyển tiền tệ ròng từ các hoạt động sản xuất kinh doanh",cash_flow!$A:$A,0),MATCH(E$23,cash_flow!$B$1:$I$1,0)),"") | F55: =IFERROR(INDEX(cash_flow!$B:$I,MATCH("Lưu chuyển tiền tệ ròng từ các hoạt động sản xuất kinh doanh",cash_flow!$A:$A,0),MATCH(F$23,cash_flow!$B$1:$I$1,0)),"") | G55: =IFERROR(INDEX(cash_flow!$B:$I,MATCH("Lưu chuyển tiền tệ ròng từ các hoạt động sản xuất kinh doanh",cash_flow!$A:$A,0),MATCH(G$23,cash_flow!$B$1:$I$1,0)),"") | H55: =IFERROR(INDEX(cash_flow!$B:$I,MATCH("Lưu chuyển tiền tệ ròng từ các hoạt động sản xuất kinh doanh",cash_flow!$A:$A,0),MATCH(H$23,cash_flow!$B$1:$I$1,0)),"") | I55: =IFERROR(INDEX(cash_flow!$B:$I,MATCH("Lưu chuyển tiền tệ ròng từ các hoạt động sản xuất kinh doanh",cash_flow!$A:$A,0),MATCH(I$23,cash_flow!$B$1:$I$1,0)),"")
A59: CHỈ SỐ THÊM | B59: 2018 | C59: 2019 | D59: 2020 | E59: 2021 | F59: 2022 | G59: 2023 | H59: 2024 | I59: 2025
A60: Khả năng sinh lời & hiệu quả sử dụng vốn
A61: ROCE | B61: =IFERROR(B$63/(B$31-B$35),"n/a") | C61: =IFERROR(C$63/(C$31-C$35),"n/a") | D61: =IFERROR(D$63/(D$31-D$35),"n/a") | E61: =IFERROR(E$63/(E$31-E$35),"n/a") | F61: =IFERROR(F$63/(F$31-F$35),"n/a") | G61: =IFERROR(G$63/(G$31-G$35),"n/a") | H61: =IFERROR(H$63/(H$31-H$35),"n/a") | I61: =IFERROR(I$63/(I$31-I$35),"n/a")
A62: CROIC | B62: =IFERROR(B$67/(B$31-B$35),"n/a") | C62: =IFERROR(C$67/(C$31-C$35),"n/a") | D62: =IFERROR(D$67/(D$31-D$35),"n/a") | E62: =IFERROR(E$67/(E$31-E$35),"n/a") | F62: =IFERROR(F$67/(F$31-F$35),"n/a") | G62: =IFERROR(G$67/(G$31-G$35),"n/a") | H62: =IFERROR(H$67/(H$31-H$35),"n/a") | I62: =IFERROR(I$67/(I$31-I$35),"n/a")
A63: EBIT | B63: =IFERROR(B$48+ABS(B$49),"n/a") | C63: =IFERROR(C$48+ABS(C$49),"n/a") | D63: =IFERROR(D$48+ABS(D$49),"n/a") | E63: =IFERROR(E$48+ABS(E$49),"n/a") | F63: =IFERROR(F$48+ABS(F$49),"n/a") | G63: =IFERROR(G$48+ABS(G$49),"n/a") | H63: =IFERROR(H$48+ABS(H$49),"n/a") | I63: =IFERROR(I$48+ABS(I$49),"n/a")
A64: EBIT/DT | B64: =IFERROR(B$63/B$43,"n/a") | C64: =IFERROR(C$63/C$43,"n/a") | D64: =IFERROR(D$63/D$43,"n/a") | E64: =IFERROR(E$63/E$43,"n/a") | F64: =IFERROR(F$63/F$43,"n/a") | G64: =IFERROR(G$63/G$43,"n/a") | H64: =IFERROR(H$63/H$43,"n/a") | I64: =IFERROR(I$63/I$43,"n/a")
A65: DT/TS | B65: =IFERROR(B$43/B$31,"n/a") | C65: =IFERROR(C$43/C$31,"n/a") | D65: =IFERROR(D$43/D$31,"n/a") | E65: =IFERROR(E$43/E$31,"n/a") | F65: =IFERROR(F$43/F$31,"n/a") | G65: =IFERROR(G$43/G$31,"n/a") | H65: =IFERROR(H$43/H$31,"n/a") | I65: =IFERROR(I$43/I$31,"n/a")
A66: Dòng tiền & tái đầu tư
A67: FCF | B67: =IFERROR(B$55-ABS(B$54),"n/a") | C67: =IFERROR(C$55-ABS(C$54),"n/a") | D67: =IFERROR(D$55-ABS(D$54),"n/a") | E67: =IFERROR(E$55-ABS(E$54),"n/a") | F67: =IFERROR(F$55-ABS(F$54),"n/a") | G67: =IFERROR(G$55-ABS(G$54),"n/a") | H67: =IFERROR(H$55-ABS(H$54),"n/a") | I67: =IFERROR(I$55-ABS(I$54),"n/a")
A68: FCF/DT | B68: =IFERROR(B$67/B$43,"n/a") | C68: =IFERROR(C$67/C$43,"n/a") | D68: =IFERROR(D$67/D$43,"n/a") | E68: =IFERROR(E$67/E$43,"n/a") | F68: =IFERROR(F$67/F$43,"n/a") | G68: =IFERROR(G$67/G$43,"n/a") | H68: =IFERROR(H$67/H$43,"n/a") | I68: =IFERROR(I$67/I$43,"n/a")
A69: FCF/Nợ ngắn hạn | B69: =IFERROR(B$67/B$35,"n/a") | C69: =IFERROR(C$67/C$35,"n/a") | D69: =IFERROR(D$67/D$35,"n/a") | E69: =IFERROR(E$67/E$35,"n/a") | F69: =IFERROR(F$67/F$35,"n/a") | G69: =IFERROR(G$67/G$35,"n/a") | H69: =IFERROR(H$67/H$35,"n/a") | I69: =IFERROR(I$67/I$35,"n/a")
A70: Capex | B70: =IFERROR(ABS(B$54),"n/a") | C70: =IFERROR(ABS(C$54),"n/a") | D70: =IFERROR(ABS(D$54),"n/a") | E70: =IFERROR(ABS(E$54),"n/a") | F70: =IFERROR(ABS(F$54),"n/a") | G70: =IFERROR(ABS(G$54),"n/a") | H70: =IFERROR(ABS(H$54),"n/a") | I70: =IFERROR(ABS(I$54),"n/a")
A71: Capex/TS | B71: =IFERROR(B$70/B$31,"n/a") | C71: =IFERROR(C$70/C$31,"n/a") | D71: =IFERROR(D$70/D$31,"n/a") | E71: =IFERROR(E$70/E$31,"n/a") | F71: =IFERROR(F$70/F$31,"n/a") | G71: =IFERROR(G$70/G$31,"n/a") | H71: =IFERROR(H$70/H$31,"n/a") | I71: =IFERROR(I$70/I$31,"n/a")
A72: Capex/LNST | B72: =IFERROR(B$70/ABS(B$50),"n/a") | C72: =IFERROR(C$70/ABS(C$50),"n/a") | D72: =IFERROR(D$70/ABS(D$50),"n/a") | E72: =IFERROR(E$70/ABS(E$50),"n/a") | F72: =IFERROR(F$70/ABS(F$50),"n/a") | G72: =IFERROR(G$70/ABS(G$50),"n/a") | H72: =IFERROR(H$70/ABS(H$50),"n/a") | I72: =IFERROR(I$70/ABS(I$50),"n/a")
A73: Chi phí khấu hao/Lợi nhuận gộp | B73: =IFERROR(ABS(B$53)/B$45,"n/a") | C73: =IFERROR(ABS(C$53)/C$45,"n/a") | D73: =IFERROR(ABS(D$53)/D$45,"n/a") | E73: =IFERROR(ABS(E$53)/E$45,"n/a") | F73: =IFERROR(ABS(F$53)/F$45,"n/a") | G73: =IFERROR(ABS(G$53)/G$45,"n/a") | H73: =IFERROR(ABS(H$53)/H$45,"n/a") | I73: =IFERROR(ABS(I$53)/I$45,"n/a")
A74: EBIT/Chi phí lãi vay | B74: =IFERROR(B$63/ABS(B$49),"n/a") | C74: =IFERROR(C$63/ABS(C$49),"n/a") | D74: =IFERROR(D$63/ABS(D$49),"n/a") | E74: =IFERROR(E$63/ABS(E$49),"n/a") | F74: =IFERROR(F$63/ABS(F$49),"n/a") | G74: =IFERROR(G$63/ABS(G$49),"n/a") | H74: =IFERROR(H$63/ABS(H$49),"n/a") | I74: =IFERROR(I$63/ABS(I$49),"n/a")
A75: Vốn lưu động & hiệu quả hoạt động
A76: Vòng quay tiền mặt | B76: =IFERROR(B$17+B$18-B$16,"n/a") | C76: =IFERROR(C$17+C$18-C$16,"n/a") | D76: =IFERROR(D$17+D$18-D$16,"n/a") | E76: =IFERROR(E$17+E$18-E$16,"n/a") | F76: =IFERROR(F$17+F$18-F$16,"n/a") | G76: =IFERROR(G$17+G$18-G$16,"n/a") | H76: =IFERROR(H$17+H$18-H$16,"n/a") | I76: =IFERROR(I$17+I$18-I$16,"n/a")
A77: HTK/DT | B77: =IFERROR(B$28/B$43,"n/a") | C77: =IFERROR(C$28/C$43,"n/a") | D77: =IFERROR(D$28/D$43,"n/a") | E77: =IFERROR(E$28/E$43,"n/a") | F77: =IFERROR(F$28/F$43,"n/a") | G77: =IFERROR(G$28/G$43,"n/a") | H77: =IFERROR(H$28/H$43,"n/a") | I77: =IFERROR(I$28/I$43,"n/a")
A78: HTK/TS | B78: =IFERROR(B$28/B$31,"n/a") | C78: =IFERROR(C$28/C$31,"n/a") | D78: =IFERROR(D$28/D$31,"n/a") | E78: =IFERROR(E$28/E$31,"n/a") | F78: =IFERROR(F$28/F$31,"n/a") | G78: =IFERROR(G$28/G$31,"n/a") | H78: =IFERROR(H$28/H$31,"n/a") | I78: =IFERROR(I$28/I$31,"n/a")
A79: DT/TS | B79: =IFERROR(B$43/B$31,"n/a") | C79: =IFERROR(C$43/C$31,"n/a") | D79: =IFERROR(D$43/D$31,"n/a") | E79: =IFERROR(E$43/E$31,"n/a") | F79: =IFERROR(F$43/F$31,"n/a") | G79: =IFERROR(G$43/G$31,"n/a") | H79: =IFERROR(H$43/H$31,"n/a") | I79: =IFERROR(I$43/I$31,"n/a")
A80: Khả năng thanh toán
A81: (TS ngắn hạn − HTK)/Nợ ngắn hạn | B81: =IFERROR((B$29-B$28)/B$35,"n/a") | C81: =IFERROR((C$29-C$28)/C$35,"n/a") | D81: =IFERROR((D$29-D$28)/D$35,"n/a") | E81: =IFERROR((E$29-E$28)/E$35,"n/a") | F81: =IFERROR((F$29-F$28)/F$35,"n/a") | G81: =IFERROR((G$29-G$28)/G$35,"n/a") | H81: =IFERROR((H$29-H$28)/H$35,"n/a") | I81: =IFERROR((I$29-I$28)/I$35,"n/a")
A82: TS ngắn hạn/Nợ ngắn hạn | B82: =IFERROR(B$29/B$35,"n/a") | C82: =IFERROR(C$29/C$35,"n/a") | D82: =IFERROR(D$29/D$35,"n/a") | E82: =IFERROR(E$29/E$35,"n/a") | F82: =IFERROR(F$29/F$35,"n/a") | G82: =IFERROR(G$29/G$35,"n/a") | H82: =IFERROR(H$29/H$35,"n/a") | I82: =IFERROR(I$29/I$35,"n/a")
A83: Tài sản & cơ cấu tài sản
A84: TSCĐ vô hình | B84: =IFERROR(B$30,"n/a") | C84: =IFERROR(C$30,"n/a") | D84: =IFERROR(D$30,"n/a") | E84: =IFERROR(E$30,"n/a") | F84: =IFERROR(F$30,"n/a") | G84: =IFERROR(G$30,"n/a") | H84: =IFERROR(H$30,"n/a") | I84: =IFERROR(I$30,"n/a")
A85: Tài sản vô hình/Giá trị sổ sách | B85: =IFERROR(B$30/B$39,"n/a") | C85: =IFERROR(C$30/C$39,"n/a") | D85: =IFERROR(D$30/D$39,"n/a") | E85: =IFERROR(E$30/E$39,"n/a") | F85: =IFERROR(F$30/F$39,"n/a") | G85: =IFERROR(G$30/G$39,"n/a") | H85: =IFERROR(H$30/H$39,"n/a") | I85: =IFERROR(I$30/I$39,"n/a")

Sheet Dự báo tăng trưởng
B1: Q1/2026 | C1: Q2/2026 | D1: Q3/2026 | E1: Q4/2026
A2: Số CP | B2: 8442964520 | C2: 8442964520 | D2: 8442964520 | E2: 8442964520
A3: Thị giá | B3: 22250 | C3: 22250 | D3: 22250 | E3: 22250
A4: Vốn hoá | B4: =B2*B3 | C4: =C2*C3 | D4: =D2*D3 | E4: =E2*E3
A6: VCSH | B6: 139782000000000 | C6: 141516000000000 | D6: =B6*(($E$6/$B$6)^(2/3)) | E6: =chi_so_tai_chinh!J39
A7: LICĐKKS | B7: =B6*0.35/100 | C7: =C6*0.35/100 | D7: =D6*0.35/100 | E7: =E6*0.35/100
A8: BV | B8: =B6-B7 | C8: =C6-C7 | D8: =D6-D7 | E8: =E6-E7
A9: BVPS | B9: =B8/B2 | C9: =C8/C2 | D9: =D8/D2 | E9: =E8/E2
A10: PB | B10: =$E$3/B9 | C10: =$E$3/C9 | D10: =$E$3/D9 | E10: =$E$3/E9

Sheet Hiệu quả thực hiện KH
A1: Chỉ tiêu | B1: 2020 | C1: 2021 | D1: 2022 | E1: 2023 | F1: 2024 | G1: 2025
A2: Doanh thu kế hoạch | B2: 86000000 | C2: 120000000 | D2: 160000000 | E2: 150000000 | F2: 140000000 | G2: 170000000
A3: Doanh thu thuần về bán hàng và cung cấp dịch vụ | B3: =chi_so_tai_chinh!D43/1000000 | C3: =chi_so_tai_chinh!E43/1000000 | D3: =chi_so_tai_chinh!F43/1000000 | E3: =chi_so_tai_chinh!G43/1000000 | F3: =chi_so_tai_chinh!H43/1000000
A4: %thực hiện | B4: =B3/B2 | C4: =C3/C2 | D4: =D3/D2 | E4: =E3/E2 | F4: =F3/F2
A5: Lợi nhuận sau thuế kế hoạch | B5: 9000000 | C5: 18000000 | D5: 30000000 | E5: 8000000 | F5: 10000000 | G5: 15000000
A6: Lợi nhuận sau thuế thu nhập doanh nghiệp | B6: =chi_so_tai_chinh!D50/1000000 | C6: =chi_so_tai_chinh!E50/1000000 | D6: =chi_so_tai_chinh!F50/1000000 | E6: =chi_so_tai_chinh!G50/1000000 | F6: =chi_so_tai_chinh!H50/1000000
A7: %thực hiện | B7: =B6/B5 | C7: =C6/C5 | D7: =D6/D5 | E7: =E6/E5 | F7: =F6/F5
A9: Trung vị %thực hiện DT | B9: =MEDIAN(B4:F4)
A10: Trung vị %thực hiện LNST | B10: =MEDIAN(B7:F7)
A12: Tỷ lệ hoàn thành DT trên 95% | B12: =COUNTIF(B4:F4,">=95%")/COUNT(B4:F4)
A13: Tỷ lệ hoàn thành LNST trên 95% | B13: =COUNTIF(B7:F7,">=95%")/COUNT(B7:F7)
