Workbook

Sheet balance_sheet
A1: item | B1: 2018-Q1 | C1: 2018-Q2 | D1: 2018-Q3 | E1: 2018-Q4 | F1: 2024-Q3 | G1: 2024-Q4 | H1: 2025-Q1 | I1: 2025-Q2 | J1: 2025-Q3 | K1: 2025-Q4 | L1: 2026-Q1 | M1: 2026-Q2
A2: TÀI SẢN NGẮN HẠN | B2: 32950886918408 | C2: 33311681394721 | D2: 31834300607121 | E2: 26013633267830 | F2: 80841803394106 | G2: 86674276272995 | H2: 88914195573724 | I2: 97613904938535 | J2: 95425988115582 | K2: 103659402759724 | L2: 104365180994071 | M2: 119968988853207
A3: Tiền và tương đương tiền | B3: 6662968459743 | C3: 5319038225154 | D3: 3976151668262 | E3: 2515617135457 | F3: 8500998079280 | G3: 6887646139852 | H3: 7459035818129 | I3: 10688024277258 | J3: 9092562739415 | K3: 8300890304205 | L3: 11455231038505 | M3: 9782057360909
A4: Tiền | B4: 846812895854 | C4: 1063073003002 | D4: 937606668262 | E4: 1822302135457 | F4: 2781657706285 | G4: 2919531945908 | H4: 3098950890534 | I4: 3313840111274 | J4: 2690506955882 | K4: 4602047650138 | L4: 3614809922085 | M4: 2221354791923
A5: Các khoản tương đương tiền | B5: 5816155563889 | C5: 4255965222152 | D5: 3038545000000 | E5: 693315000000 | F5: 5719340372995 | G5: 3968114193944 | H5: 4360084927595 | I5: 7374184165984 | J5: 6402055783533 | K5: 3698842654067 | L5: 7840421116420 | M5: 7560702568986
A6: Đầu tư ngắn hạn | B6: 0 | C6: 0 | D6: 0 | E6: 0 | F6: 0 | G6: 0 | H6: 0 | I6: 0 | J6: 0 | K6: 0 | L6: 0 | M6: 0
A7: Đầu tư ngắn hạn
A8: Dự phòng giảm giá | B8: 0 | C8: 0 | D8: 0 | E8: 0 | F8: 0 | G8: 0 | H8: 0 | I8: 0 | J8: 0 | K8: 0 | L8: 0 | M8: 0
A9: Các khoản phải thu | B9: 7178547741042 | C9: 6176268736830 | D9: 5640203890272 | E9: 3915158043554 | F9: 9140948029240 | G9: 7647800286988 | H9: 10856053423195 | I9: 12334925649801 | J9: 13727194725111 | K9: 15042323117690 | L9: 16692782771439 | M9: 18040238952446
A10: Phải thu khách hàng | B10: 1982714902404 | C10: 2028079364820 | D10: 2748733518605 | E10: 2281760501157 | F10: 4980712149392 | G10: 4352135419872 | H10: 7405241282190 | I10: 8196017496272 | J10: 7979265010316 | K10: 10971774018235 | L10: 10919196457706 | M10: 12869807539960
A11: Trả trước người bán | B11: 4856000991045 | C11: 3893429128203 | D11: 2338017297368 | E11: 810319171039 | F11: 2948440731905 | G11: 2118824427004 | H11: 2349213570061 | I11: 2755989948090 | J11: 4219935549920 | K11: 1878084035938 | L11: 3188267235957 | M11: 3362889032465
A12: Phải thu nội bộ | B12: 0 | C12: 0 | D12: 0 | E12: 0 | F12: 0 | G12: 0 | H12: 0 | I12: 0 | J12: 0 | K12: 0 | L12: 0 | M12: 0
A13: Phải thu hợp đồng xây dựng đang thực hiện | B13: 0 | C13: 0 | D13: 0 | E13: 0 | F13: 0 | G13: 0 | H13: 0 | I13: 0 | J13: 0 | K13: 0 | L13: 0 | M13: 0
A14: Phải thu khác | B14: 373123574564 | C14: 289244825538 | D14: 588652040210 | E14: 855831785552 | F14: 938808369599 | G14: 1248992845378 | H14: 1170323249843 | I14: 1443182617677 | J14: 1614044195296 | K14: 2318283126429 | L14: 2710787542005 | M14: 1933150942736
A15: Dự phòng nợ khó đòi | B15: -34932619381 | C15: -35812771992 | D15: -36934899098 | E15: -37693842866 | F15: -46670304885 | G15: -159993736285 | H15: -158638815710 | I15: -157971873885 | J15: -158272660342 | K15: -132548698812 | L15: -132284501806 | M15: -132596386675
A16: Hàng tồn kho, ròng | B16: 11333204635800 | C16: 12887026543733 | D16: 14770217336303 | E16: 14115158052529 | F16: 40197821463879 | G16: 46091222189472 | H16: 46603844415849 | I16: 48853408114115 | J16: 45623656431728 | K16: 52828227344442 | L16: 43515585272210 | M16: 55607877088316
A17: Hàng tồn kho | B17: 11473029927631 | C17: 13024194419202 | D17: 14859260924492 | E17: 14188355173355 | F17: 40480715224028 | G17: 46192292081813 | H17: 46713899534932 | I17: 48900263257832 | J17: 45675711221795 | K17: 52892273238885 | L17: 43571823623004 | M17: 55683418417281
A18: Dự phòng giảm giá hàng tồn kho | B18: -139825291831 | C18: -137167875469 | D18: -89043588189 | E18: -73197120826 | F18: -282893760149 | G18: -101069892341 | H18: -110055119083 | I18: -46855143717 | J18: -52054790067 | K18: -64045894443 | L18: -56238350794 | M18: -75541328965
A19: Tài sản lưu động khác | B19: 0 | C19: 0 | D19: 0 | E19: 0 | F19: 0 | G19: 0 | H19: 0 | I19: 0 | J19: 0 | K19: 0 | L19: 0 | M19: 0
... A22: Phải thu thuế khác | B22: 17366234169 | C22: 16059788009 | D22: 15950589606 | E22: 18748840104 | F22: 10150638821 | G22: 10074967536 | H22: 12522814414 | I22: 5696703666 | J22: 4419092905 | K22: 6371103672 | L22: 11832647902 | M22: 9542625532
A23: Tài sản lưu động khác
A24: TÀI SẢN DÀI HẠN | B24: 21486597050953 | C24: 28766660537419 | D24: 38268471313713 | E24: 52211329380109 | F24: 130544540534012 | G24: 137815431280986 | H24: 139947392214583 | I24: 144610625980515 | J24: 150745350172070 | K24: 154239798057823 | L24: 154962319211157 | M24: 158960797394565
A25: Phải thu dài hạn | B25: 22307347172 | C25: 70312568404 | D25: 22307347172 | E25: 22301804672 | F25: 1031145036427 | G25: 923400123614 | H25: 920743791614 | I25: 900453913211 | J25: 849788287676 | K25: 290327516308 | L25: 548069920526 | M25: 2142595494949
A26: Phải thu khách hàng dài hạn | B26: 0 | C26: 0 | D26: 0 | E26: 0 | F26: 0 | G26: 0 | H26: 0 | I26: 0 | J26: 0 | K26: 0 | L26: 0 | M26: 0
A27: Phải thu nội bộ dài hạn | B27: 0 | C27: 0 | D27: 0 | E27: 0 | F27: 0 | G27: 0 | H27: 0 | I27: 0 | J27: 0 | K27: 0 | L27: 0 | M27: 0
A28: Phải thu dài hạn khác | B28: 22307347172 | C28: 70312568404 | D28: 22307347172 | E28: 22301804672 | F28: 841682562478 | G28: 840594835822 | H28: 848015622228 | I28: 827053815447 | J28: 825562606009 | K28: 248919079879 | L28: 508303099491 | M28: 2107205522415
A29: Dự phòng phải thu dài hạn | B29: 0 | C29: 0 | D29: 0 | E29: 0 | F29: 0 | G29: 0 | H29: 0 | I29: 0 | J29: 0 | K29: 0 | L29: 0 | M29: 0
A30: Tài sản cố định | B30: 13075194506203 | C30: 13072518388579 | D30: 13086355600772 | E30: 12782560625001 | F30: 68475648874477 | G30: 67428366953514 | H30: 85838135705767 | I30: 65302976358571 | J30: 104711263391250 | K30: 133608057859977 | L30: 134574365284040 | M30: 132716228895558
A31: GTCL TSCĐ hữu hình | B31: 12879619300176 | C31: 12866787781557 | D31: 12882494190986 | E31: 12565363529879 | F31: 68286049668351 | G31: 67244150975048 | H31: 85662860787586 | I31: 65120521330076 | J31: 104533248655101 | K31: 133420846696083 | L31: 134372566192062 | M31: 132512652285273
A32: Nguyên giá TSCĐ hữu hình | B32: 21704460370910 | C32: 22222714327948 | D32: 22762070447420 | E32: 22992663946845 | F32: 108153947400446 | G32: 108146566348954 | H32: 128260224636169 | I32: 109249187040644 | J32: 150704510599924 | K32: 182308655292963 | L32: 185925994763538 | M32: 186818108004847
A33: Khấu hao lũy kế TSCĐ hữu hình | B33: -8824841070734 | C33: -9355926546391 | D33: -9879576256434 | E33: -10427300416966 | F33: -39867897732095 | G33: -40902415373906 | H33: -42597363848583 | I33: -44128665710568 | J33: -46171261944823 | K33: -48887808596880 | L33: -51553428571476 | M33: -54305455719574
A34: GTCL tài sản thuê tài chính | B34: 0 | C34: 0 | D34: 0 | E34: 0 | F34: 0 | G34: 0 | H34: 0 | I34: 0 | J34: 0 | K34: 0 | L34: 0 | M34: 0
A35: Nguyên giá tài sản thuê tài chính | B35: 0 | C35: 0 | D35: 0 | E35: 0 | F35: 0 | G35: 0 | H35: 0 | I35: 0 | J35: 0 | K35: 0 | L35: 0 | M35: 0
... A72: Vay dài hạn | B72: 2077143669720 | C72: 4976499450228 | D72: 9011900651509 | E72: 12810996979972 | F72: 24517626484538 | G72: 27080443256096 | H72: 27256965869238 | I72: 27312288660990 | J72: 28356095137594 | K72: 27479194057074 | L72: 27817253418546 | M72: 27096593831648
A73: Thuế thu nhập hoãn lại
A74: Dự phòng trợ cấp thôi việc | B74: 0 | C74: 0 | D74: 0 | E74: 0 | F74: 0 | G74: 0 | H74: 0 | I74: 0 | J74: 0 | K74: 0 | L74: 0 | M74: 0
A75: Dự phòng các khoản nợ dài hạn | B75: 18899407699 | C75: 20422803081 | D75: 20166210731 | E75: 18238256789 | F75: 62449868760 | G75: 67495546940 | H75: 68073293346 | I75: 125073293346 | J75: 79659762484 | K75: 119373951692 | L75: 122633161280 | M75: 128615967000
A76: Doanh thu chưa thực hiện | B76: 0 | C76: 0 | D76: 0 | E76: 0 | F76: 174647128 | G76: 0 | H76: 0 | I76: 0 | J76: 0 | K76: 0 | L76: 0 | M76: 0
A77: Quỹ phát triển khoa học công nghệ | B77: 0 | C77: 0 | D77: 0 | E77: 0 | F77: 0 | G77: 0 | H77: 0 | I77: 0 | J77: 0 | K77: 0 | L77: 0 | M77: 0
A78: Vốn chủ sở hữu | B78: 34428192910709 | C78: 36626843816306 | D78: 39033700617587 | E78: 40608949840810 | F78: 111779097236460 | G78: 114647457983699 | H78: 117996879089129 | I78: 122359504913282 | J78: 127516012099269 | K78: 131220010876575 | L78: 139781792206472 | M78: 141516026790697
A79: Vốn và các quỹ | B79: 34428192910709 | C79: 36626843816306 | D79: 39033700617587 | E79: 40608949840810 | F79: 111779097236460 | G79: 114647457983699 | H79: 117996879089129 | I79: 122359504913282 | J79: 127516012099269 | K79: 131220010876575 | L79: 139781792206472 | M79: 141516026790697
A80: Vốn góp | B80: 15170790000000 | C80: 15170790000000 | D80: 21239071660000 | E80: 21239071660000 | F80: 63962502000000 | G80: 63962502000000 | H80: 63962502000000 | I80: 63962502000000 | J80: 76754658550000 | K80: 76754658550000 | L80: 76754658550000 | M80: 76754658550000
A81: Thặng dư vốn cổ phần | B81: 3202198967068 | C81: 3211560416270 | D81: 3211560416270 | E81: 3211560416270 | F81: 0 | G81: 0 | H81: 0 | I81: 0 | J81: 0 | K81: 0 | L81: 911866210000 | M81: 0
A82: Vốn khác | B82: 0 | C82: 0 | D82: 0 | E82: 0 | F82: 0 | G82: 0 | H82: 0 | I82: 0 | J82: 0 | K82: 0 | L82: 0 | M82: 7674986650000
A83: Cổ phiếu quỹ | B83: -2063270000 | C83: 0 | D83: 0 | E83: 0 | F83: 0 | G83: 0 | H83: 0 | I83: 0 | J83: 0 | K83: 0 | L83: 0 | M83: 0
A84: Chênh lệch đánh giá lại tài sản | B84: 0 | C84: 0 | D84: 0 | E84: 0 | F84: 0 | G84: 0 | H84: 0 | I84: 0 | J84: 0 | K84: 0 | L84: 0 | M84: 0
A85: Chênh lệch tỷ giá | B85: 0 | C85: 23097859 | D85: 422577406 | E85: 276819257 | F85: 0 | G85: 0 | H85: 0 | I85: 0 | J85: 0 | K85: 0 | L85: 0 | M85: 0
... A105: Chi phí sản xuất, kinh doanh dở dang dài hạn | B105: 780351307517 | C105: 760182257089 | D105: 426629621112 | E105: 205541048896 | F105: 94525874980 | G105: 94859885024 | H105: 113250593821 | I105: 117828507706 | J105: 82652761496 | K105: 148814839011 | L105: 395261847976 | M105: 633946116238
A106: Đầu tư nắm giữ đến ngày đáo hạn
A107: Thiết bị, vật tư, phụ tùng thay thế dài hạn | B107: 0 | C107: 0 | D107: 94996612417 | E107: 0 | F107: 0 | G107: 429422385383 | H107: 416060319178 | I107: 391044882231 | J107: 365844862496 | K107: 335208284895 | L107: 317522413091 | M107: 308165854922
A108: Doanh thu chưa thực hiện ngắn hạn | B108: 20403665550 | C108: 14940535241 | D108: 10559835911 | E108: 9929720982 | F108: 192726170767 | G108: 11060479431 | H108: 55479217611 | I108: 34948909558 | J108: 46062427795 | K108: 152519279244 | L108: 60310161581 | M108: 56565429771
A109: Quỹ bình ổn giá | B109: 0 | C109: 0 | D109: 0 | E109: 0 | F109: 0 | G109: 0 | H109: 0 | I109: 0 | J109: 0 | K109: 0 | L109: 0 | M109: 0
A110: Giao dịch mua bán lại trái phiếu chính phủ | B110: 0 | C110: 0 | D110: 0 | E110: 0 | F110: 0 | G110: 0 | H110: 0 | I110: 0 | J110: 0 | K110: 0 | L110: 0 | M110: 0
A111: Người mua trả tiền trước dài hạn | B111: 0 | C111: 0 | D111: 0 | E111: 0 | F111: 0 | G111: 0 | H111: 0 | I111: 0 | J111: 0 | K111: 0 | L111: 0 | M111: 0
A112: Chi phí phải trả dài hạn | B112: 411943997721 | C112: 456843080513 | D112: 540911158271 | E112: 451100573027 | F112: 1041997895349 | G112: 1143692237207 | H112: 1174882156922 | I112: 673108219760 | J112: 473791239533 | K112: 607363800426 | L112: 625835616595 | M112: 602032288625
A113: Phải trả nội bộ về vốn kinh doanh | B113: 0 | C113: 0 | D113: 0 | E113: 0 | F113: 0 | G113: 0 | H113: 0 | I113: 0 | J113: 0 | K113: 0 | L113: 0 | M113: 0
A114: Trái phiếu chuyển đổi | B114: 0 | C114: 0 | D114: 0 | E114: 0 | F114: 0 | G114: 0 | H114: 0 | I114: 0 | J114: 0 | K114: 0 | L114: 0 | M114: 0
A115: Cổ phiếu ưu đãi
A116: Cổ phiếu phổ thông | B116: 15170790000000 | C116: 15170790000000 | D116: 21239071660000 | E116: 21239071660000 | F116: 63962502000000 | G116: 63962502000000 | H116: 63962502000000 | I116: 63962502000000 | J116: 76754658550000 | K116: 76754658550000 | L116: 76754658550000 | M116: 76754658550000
A117: Quyền chọn chuyển đổi trái phiếu | B117: 0 | C117: 0 | D117: 0 | E117: 0 | F117: 0 | G117: 0 | H117: 0 | I117: 0 | J117: 0 | K117: 0 | L117: 0 | M117: 0
A118: LNST chưa phân phối lũy kế đến cuối kỳ trước | B118: 12806120845975 | C118: 12793083437867 | D118: 11131501988924 | E118: 13346921317605 | F118: 43786272254536 | G118: 37624250548129 | H118: 49599304233846 | I118: 48575874508844 | J118: 43299860299829 | K118: 35657348003468 | L118: 50895610901437 | M118: 39473241264695
A119: LNST chưa phân phối kỳ này | B119: 2211253974571 | C119: 4406840900635 | D119: 2401952451707 | E119: 1764220746300 | F119: 3022946632050 | G119: 11974873561074 | H119: 3344284694388 | I119: 7600771906152 | J119: 3988318474539 | K119: 15380553745875 | L119: 8994003244142 | M119: 15365022248705
A120: Xây dựng cơ bản đang dở dang | B120: 5999451011252 | C120: 13029039469654 | D120: 22914110558728 | E120: 37198826355023 | F120: 55595915396651 | G120: 63655857440382 | H120: 47507058874968 | I120: 72703729846961 | J120: 39484904426635 | K120: 10721076531961 | L120: 10328735819240 | M120: 13986814689231
A121: Lợi thế thương mại | B121: 108631365039 | C121: 101977257121 | D121: 0 | E121: 88234324237 | F121: 66834062714 | G121: 63613126723 | H121: 60588141397 | I121: 57563156071 | J121: 52097751283 | K121: 51513185419 | L121: 0 | M121: 0
A122: Lợi ích cổ đông không kiểm soát | B122: 121250780939 | C122: 125904351519 | D122: 130549911124 | E122: 128257269222 | F122: 189176035910 | G122: 290990632368 | H122: 295946918767 | I122: 825515256158 | J122: 2078333532773 | K122: 2039012776403 | L122: 837215500064 | M122: 859680276468
A123: Nguồn kinh phí đã hình thành TSCĐ | B123: 0 | C123: 0 | D123: 0 | E123: 0 | F123: 0 | G123: 0 | H123: 0 | I123: 0 | J123: 0 | K123: 0 | L123: 0 | M123: 0

Sheet income_statement
A1: item | B1: 2018-Q1 | C1: 2018-Q2 | D1: 2018-Q3 | E1: 2018-Q4 | F1: 2024-Q3 | G1: 2024-Q4 | H1: 2025-Q1 | I1: 2025-Q2 | J1: 2025-Q3 | K1: 2025-Q4 | L1: 2026-Q1 | M1: 2026-Q2
A2: Doanh thu bán hàng và cung cấp dịch vụ | B2: 13161793754293 | C2: 14432746600541 | D2: 14393503062099 | E2: 14592380278150 | F2: 34300352057045 | G2: 35232197602514 | H2: 37950635502050 | I2: 36286185846409 | J2: 36793873449413 | K2: 47301623136340 | L2: 53312910120686 | M2: 55557246173846
A3: Các khoản giảm trừ doanh thu | B3: -160830333055 | C3: -171808499990 | D3: -205156935686 | E3: -206169546593 | F3: -344091771518 | G3: -741215175825 | H3: -328960948472 | I3: -375666735200 | J3: -386457045489 | K3: -1125138586569 | L3: -412062818033 | M3: -398343874945
A4: Doanh thu thuần | B4: 13000963421238 | C4: 14260938100551 | D4: 14188346126413 | E4: 14386210731557 | F4: 33956260285527 | G4: 34490982426689 | H4: 37621674553578 | I4: 35910519111209 | J4: 36407416403924 | K4: 46176484549771 | L4: 52900847302653 | M4: 55158902298901
A5: Giá vốn hàng bán | B5: -10035454240162 | C5: -11379662995694 | D5: -10925130035885 | E5: -11825378876944 | F5: -29225083561286 | G5: -30126073473488 | H5: -32197520628446 | I5: -29320796625500 | J5: -30320155128758 | K5: -39779834052596 | L5: -44535778694658 | M5: -44671115105470
A6: Lợi nhuận gộp | B6: 2965509181076 | C6: 2881275104857 | D6: 3263216090528 | E6: 2560831854613 | F6: 4731176724241 | G6: 4364908953201 | H6: 5424153925132 | I6: 6589722485709 | J6: 6087261275166 | K6: 6396650497175 | L6: 8365068607995 | M6: 10487787193431
A7: Doanh thu hoạt động tài chính | B7: 63318173965 | C7: 79415973001 | D7: 79985465695 | E7: 71688658080 | F7: 528453174917 | G7: 700560102056 | H7: 438057240540 | I7: 498183728007 | J7: 711903358963 | K7: 437280867832 | L7: 5938347436208 | M7: 616702440089
A8: Chi phí tài chính | B8: -171748751094 | C8: -159250258201 | D8: -234345232708 | E8: -206972919898 | F8: -832902574260 | G8: -1015139809937 | H8: -970569640998 | I8: -979462100729 | J8: -1073210620638 | K8: -1583968999127 | L8: -1868827249709 | M8: -1925757565918
A9: Chi phí lãi vay | B9: -118019669890 | C9: -135220094841 | D9: -141685345016 | E9: -144936133893 | F9: -525114798901 | G9: -562492663846 | H9: -627024360692 | I9: -439112631420 | J9: -812194101705 | K9: -1236524775157 | L9: -1333414699291 | M9: -1519613868123
A10: Chi phí bán hàng | B10: -143871695353 | C10: -154665928668 | D10: -188483553715 | E10: -191711141335 | F10: -720208188679 | G10: -230212058532 | H10: -737815718816 | I10: -825371907199 | J10: -798965987739 | K10: -271477098154 | L10: -1344969024100 | M10: -1717603199584
A11: Chi phí quản lý doanh nghiệp | B11: -114493721383 | C11: -66201080303 | D11: -51780664435 | E11: -209629621922 | F11: -321501544741 | G11: -517318083678 | H11: -347243794856 | I11: -322285873598 | J11: -355963309576 | K11: -411044379459 | L11: -385901879604 | M11: -307796866973
A12: Lãi/(lỗ) từ hoạt động kinh doanh | B12: 2598713187211 | C12: 2580573810686 | D12: 2868592105365 | E12: 2024206829538 | F12: 3385017591478 | G12: 3302799103110 | H12: 3806582011002 | I12: 4960786332190 | J12: 4571024716176 | K12: 4567440888267 | L12: 10704033503572 | M12: 7155004358406
A13: Thu nhập khác | B13: 151761821218 | C13: 114214391806 | D13: 79210487446 | E13: 143669887566 | F13: 220917018524 | G13: 225300683318 | H13: 153981783497 | I13: -41431471594 | J13: 78007207531 | K13: 115035838477 | L13: 99982776284 | M13: 82682443691
... A26: Lãi/(lỗ) từ công ty liên doanh (từ năm 2015) | B26: 0 | C26: 0 | D26: 0 | E26: 0 | F26: 0 | G26: 0 | H26: 0 | I26: 0 | J26: 0 | K26: 0 | L26: 315612782 | M26: 1672357361

Sheet cash_flow
A1: item | B1: 2018-Q1 | C1: 2018-Q2 | D1: 2018-Q3 | E1: 2018-Q4 | F1: 2024-Q3 | G1: 2024-Q4 | H1: 2025-Q1 | I1: 2025-Q2 | J1: 2025-Q3 | K1: 2025-Q4 | L1: 2026-Q1 | M1: 2026-Q2
A2: Lợi nhuận/(lỗ) trước thuế | B2: 2608439205997 | C2: 2577218001099 | D2: 2848086063843 | E2: 2037329601363 | F2: 3412385133844 | G2: 3286676100696 | H2: 3839765349020 | I2: 4972383493663 | J2: 4628313172434 | K2: 4600129962763 | L2: 10762183839545 | M2: 7184684207426
A3: Khấu hao TSCĐ và BĐSĐT | B3: 556108322687 | C3: 553037107154 | D3: 597087360757 | E3: 577870811942 | F3: 1771185761423 | G3: 1693028331093 | H3: 1801603135468 | I3: 1617247528510 | J3: 2169156032825 | K3: 2882676563353 | L3: 2854213903270 | M3: 2851263156834
A4: Chi phí dự phòng | B4: -7296315043 | C4: -426147437 | D4: -47094368475 | E4: -18173662868 | F4: -3156807492 | G4: -61035121811 | H4: 11289113084 | I4: -59927342891 | J4: 10882237428 | K4: -12074483403 | L4: -394463126 | M4: 29729264501
A5: Lãi/lỗ chênh lệch tỷ giá hối đoái do đánh giá lại các khoản mục tiền tệ có gốc ngoại tệ | B5: 38197623898 | C5: -33113633439 | D5: 21416556849 | E5: 4104939588 | F5: -206784225956 | G5: 227751228845 | H5: 132616469869 | I5: 309920317236 | J5: -56814712069 | K5: -36094914050 | L5: -93187660506 | M5: 36508026287
A6: Lãi/(lỗ) từ thanh lý tài sản cố định | B6: 0 | C6: 0 | D6: 0 | E6: 0 | F6: 0 | G6: 0 | H6: 0 | I6: 0 | J6: 0 | K6: 0 | L6: 0 | M6: 0
A7: (Lãi)/lỗ từ hoạt động đầu tư | B7: -46934532354 | C7: -41534210367 | D7: 2051444778 | E7: -66937818732 | F7: 103011663888 | G7: -765370789609 | H7: -244726801802 | I7: -305813548010 | J7: -454485515064 | K7: -293829106766 | L7: -5113315374186 | M7: -510268020185
A8: Chi phí lãi vay | B8: 118019669890 | C8: 135220094841 | D8: 141685345016 | E8: 144936133893 | F8: 525114798901 | G8: 562492663846 | H8: 627024360692 | I8: 439112631420 | J8: 812194101705 | K8: 1236524775157 | L8: 1333414699291 | M8: 1519613868123
A9: Thu lãi và cổ tức | B9: 0 | C9: 0 | D9: 0 | E9: 0 | F9: 0 | G9: 0 | H9: 0 | I9: 0 | J9: 0 | K9: 0 | L9: 0 | M9: 0
A10: Lợi nhuận/(lỗ) từ hoạt động kinh doanh trước những thay đổi vốn lưu động | B10: 3266533975075 | C10: 3202709431687 | D10: 3550924182932 | E10: 2679130005186 | F10: 5595706353956 | G10: 4955838305029 | H10: 6167571626331 | I10: 6972923079928 | J10: 7109245317259 | K10: 8377332797054 | L10: 9742914944288 | M10: 11111530502986
A11: (Tăng)/giảm các khoản phải thu | B11: 82342161661 | C11: -618456931257 | D11: 119547210473 | E11: -1712374696823 | F11: 377494427161 | G11: 971968926351 | H11: -4134982417163 | I11: -1835418390802 | J11: -167609437136 | K11: -2605118841180 | L11: -3247077198393 | M11: -2028681332858
A12: (Tăng)/giảm hàng tồn kho | B12: 543802130814 | C12: -1531001715888 | D12: -1501522889313 | E12: 891988751549 | F12: -3510769453171 | G12: -6209983876378 | H12: -384608710947 | I12: -2468299455608 | J12: 3191714046698 | K12: -7580580412836 | L12: 6689926170566 | M12: -12414552906660
A13: Tăng/(giảm) các khoản phải trả | B13: -243975167874 | C13: 924608516139 | D13: 44260251184 | E13: 734863589308 | F13: -1584866701776 | G13: 4023222874211 | H13: -1984736525485 | I13: 1394149750385 | J13: -812631275870 | K13: 12796369447003 | L13: -2632265270173 | M13: 11230394666327
... A42: (Tăng)/giảm chứng khoán kinh doanh | B42: 0 | C42: 0 | D42: 0 | E42: 0 | F42: 0 | G42: 0 | H42: 0 | I42: 0 | J42: 0 | K42: 0 | L42: 0 | M42: 0

Sheet chi_so_tai_chinh
A1: Chỉ tiêu | B1: =balance_sheet!B1 | C1: =balance_sheet!C1 | D1: =balance_sheet!D1 | E1: =balance_sheet!E1 | F1: =balance_sheet!F1 | G1: =balance_sheet!G1 | H1: =balance_sheet!H1 | I1: =balance_sheet!I1
A2: ROE (LNST CĐ Cty mẹ / VCSH bình quân) | B2: =IFERROR(B$53/((B$41+#REF!)/2),"n/a") | C2: =IFERROR(C$53/((C$41+B$41)/2),"n/a") | D2: =IFERROR(D$53/((D$41+C$41)/2),"n/a") | E2: =IFERROR(E$53/((E$41+D$41)/2),"n/a") | F2: =IFERROR(F$53/((F$41+E$41)/2),"n/a") | G2: =IFERROR(G$53/((G$41+F$41)/2),"n/a") | H2: =IFERROR(H$53/((H$41+G$41)/2),"n/a") | I2: =IFERROR(I$53/((I$41+H$41)/2),"n/a")
A3: ROA (LNST / Tổng tài sản bình quân) | B3: =IFERROR(B$52/((B$33+#REF!)/2),"n/a") | C3: =IFERROR(C$52/((C$33+B$33)/2),"n/a") | D3: =IFERROR(D$52/((D$33+C$33)/2),"n/a") | E3: =IFERROR(E$52/((E$33+D$33)/2),"n/a") | F3: =IFERROR(F$52/((F$33+E$33)/2),"n/a") | G3: =IFERROR(G$52/((G$33+F$33)/2),"n/a") | H3: =IFERROR(H$52/((H$33+G$33)/2),"n/a") | I3: =IFERROR(I$52/((I$33+H$33)/2),"n/a")
A4: Tăng trưởng LN Cổ đông Cty mẹ QQ | B4: =IFERROR((B$53-#REF!)/ABS(#REF!),"n/a") | C4: =IFERROR((C$53-B$53)/ABS(B$53),"n/a") | D4: =IFERROR((D$53-C$53)/ABS(C$53),"n/a") | E4: =IFERROR((E$53-D$53)/ABS(D$53),"n/a") | F4: =IFERROR((F$53-E$53)/ABS(E$53),"n/a") | G4: =IFERROR((G$53-F$53)/ABS(F$53),"n/a") | H4: =IFERROR((H$53-G$53)/ABS(G$53),"n/a") | I4: =IFERROR((I$53-H$53)/ABS(H$53),"n/a")
A5: Tăng trưởng LN Cổ đông Cty mẹ YY | F5: =IFERROR((F$53-B$53)/ABS(B$53),"n/a") | G5: =IFERROR((G$53-C$53)/ABS(C$53),"n/a") | H5: =IFERROR((H$53-D$53)/ABS(D$53),"n/a") | I5: =IFERROR((I$53-E$53)/ABS(E$53),"n/a")
A6: Tăng trưởng Doanh thu thuần QQ | B6: =IFERROR((B$45-#REF!)/ABS(#REF!),"n/a") | C6: =IFERROR((C$45-B$45)/ABS(B$45),"n/a") | D6: =IFERROR((D$45-C$45)/ABS(C$45),"n/a") | E6: =IFERROR((E$45-D$45)/ABS(D$45),"n/a") | F6: =IFERROR((F$45-E$45)/ABS(E$45),"n/a") | G6: =IFERROR((G$45-F$45)/ABS(F$45),"n/a") | H6: =IFERROR((H$45-G$45)/ABS(G$45),"n/a") | I6: =IFERROR((I$45-H$45)/ABS(H$45),"n/a")
A7: Tăng trưởng Doanh thu thuần YY | F7: =IFERROR((F$45-B$45)/ABS(B$45),"n/a") | G7: =IFERROR((G$45-C$45)/ABS(C$45),"n/a") | H7: =IFERROR((H$45-D$45)/ABS(D$45),"n/a") | I7: =IFERROR((I$45-E$45)/ABS(E$45),"n/a")
A8: Biên lợi nhuận gộp | B8: =IFERROR(B$47/B$45,"n/a") | C8: =IFERROR(C$47/C$45,"n/a") | D8: =IFERROR(D$47/D$45,"n/a") | E8: =IFERROR(E$47/E$45,"n/a") | F8: =IFERROR(F$47/F$45,"n/a") | G8: =IFERROR(G$47/G$45,"n/a") | H8: =IFERROR(H$47/H$45,"n/a") | I8: =IFERROR(I$47/I$45,"n/a")
A9: Biên lợi nhuận ròng | B9: =IFERROR(B$53/B$45,"n/a") | C9: =IFERROR(C$53/C$45,"n/a") | D9: =IFERROR(D$53/D$45,"n/a") | E9: =IFERROR(E$53/E$45,"n/a") | F9: =IFERROR(F$53/F$45,"n/a") | G9: =IFERROR(G$53/G$45,"n/a") | H9: =IFERROR(H$53/H$45,"n/a") | I9: =IFERROR(I$53/I$45,"n/a")
A10: D/E (Nợ vay / Vốn chủ sở hữu) | B10: =IFERROR((B$36+B$38)/B$41,"n/a") | C10: =IFERROR((C$36+C$38)/C$41,"n/a") | D10: =IFERROR((D$36+D$38)/D$41,"n/a") | E10: =IFERROR((E$36+E$38)/E$41,"n/a") | F10: =IFERROR((F$36+F$38)/F$41,"n/a") | G10: =IFERROR((G$36+G$38)/G$41,"n/a") | H10: =IFERROR((H$36+H$38)/H$41,"n/a") | I10: =IFERROR((I$36+I$38)/I$41,"n/a")
A11: - Nợ vay dài hạn/Vốn chủ sở hữu | B11: =IFERROR(B$38/B$41,"n/a") | C11: =IFERROR(C$38/C$41,"n/a") | D11: =IFERROR(D$38/D$41,"n/a") | E11: =IFERROR(E$38/E$41,"n/a") | F11: =IFERROR(F$38/F$41,"n/a") | G11: =IFERROR(G$38/G$41,"n/a") | H11: =IFERROR(H$38/H$41,"n/a") | I11: =IFERROR(I$38/I$41,"n/a")
A12: - Nợ vay ngắn hạn/Vốn chủ sở hữu | B12: =IFERROR(B$36/B$41,"n/a") | C12: =IFERROR(C$36/C$41,"n/a") | D12: =IFERROR(D$36/D$41,"n/a") | E12: =IFERROR(E$36/E$41,"n/a") | F12: =IFERROR(F$36/F$41,"n/a") | G12: =IFERROR(G$36/G$41,"n/a") | H12: =IFERROR(H$36/H$41,"n/a") | I12: =IFERROR(I$36/I$41,"n/a")
A13: Nợ phải trả/Vốn chủ sở hữu | B13: =IFERROR(B$40/B$41,"n/a") | C13: =IFERROR(C$40/C$41,"n/a") | D13: =IFERROR(D$40/D$41,"n/a") | E13: =IFERROR(E$40/E$41,"n/a") | F13: =IFERROR(F$40/F$41,"n/a") | G13: =IFERROR(G$40/G$41,"n/a") | H13: =IFERROR(H$40/H$41,"n/a") | I13: =IFERROR(I$40/I$41,"n/a")
A14: - Nợ dài hạn/Vốn chủ sở hữu | B14: =IFERROR(B$39/B$41,"n/a") | C14: =IFERROR(C$39/C$41,"n/a") | D14: =IFERROR(D$39/D$41,"n/a") | E14: =IFERROR(E$39/E$41,"n/a") | F14: =IFERROR(F$39/F$41,"n/a") | G14: =IFERROR(G$39/G$41,"n/a") | H14: =IFERROR(H$39/H$41,"n/a") | I14: =IFERROR(I$39/I$41,"n/a")
A15: - Nợ ngắn hạn/Vốn chủ sở hữu | B15: =IFERROR(B$37/B$41,"n/a") | C15: =IFERROR(C$37/C$41,"n/a") | D15: =IFERROR(D$37/D$41,"n/a") | E15: =IFERROR(E$37/E$41,"n/a") | F15: =IFERROR(F$37/F$41,"n/a") | G15: =IFERROR(G$37/G$41,"n/a") | H15: =IFERROR(H$37/H$41,"n/a") | I15: =IFERROR(I$37/I$41,"n/a")
A16: Chi phí bán hàng, quản lý/LN gộp | B16: =IFERROR((ABS(B$48)+ABS(B$49))/B$47,"n/a") | C16: =IFERROR((ABS(C$48)+ABS(C$49))/C$47,"n/a") | D16: =IFERROR((ABS(D$48)+ABS(D$49))/D$47,"n/a") | E16: =IFERROR((ABS(E$48)+ABS(E$49))/E$47,"n/a") | F16: =IFERROR((ABS(F$48)+ABS(F$49))/F$47,"n/a") | G16: =IFERROR((ABS(G$48)+ABS(G$49))/G$47,"n/a") | H16: =IFERROR((ABS(H$48)+ABS(H$49))/H$47,"n/a") | I16: =IFERROR((ABS(I$48)+ABS(I$49))/I$47,"n/a")
A17: Chi phí lãi vay/LN từ hoạt động kinh doanh | B17: =IFERROR(ABS(B$51)/B$50,"n/a") | C17: =IFERROR(ABS(C$51)/C$50,"n/a") | D17: =IFERROR(ABS(D$51)/D$50,"n/a") | E17: =IFERROR(ABS(E$51)/E$50,"n/a") | F17: =IFERROR(ABS(F$51)/F$50,"n/a") | G17: =IFERROR(ABS(G$51)/G$50,"n/a") | H17: =IFERROR(ABS(H$51)/H$50,"n/a") | I17: =IFERROR(ABS(I$51)/I$50,"n/a")
A18: Số ngày phải trả (DPO) | B18: =IFERROR(((B$35+#REF!)/2)/ABS(B$46)*365,"n/a") | C18: =IFERROR(((C$35+B$35)/2)/ABS(C$46)*365,"n/a") | D18: =IFERROR(((D$35+C$35)/2)/ABS(D$46)*365,"n/a") | E18: =IFERROR(((E$35+D$35)/2)/ABS(E$46)*365,"n/a") | F18: =IFERROR(((F$35+E$35)/2)/ABS(F$46)*365,"n/a") | G18: =IFERROR(((G$35+F$35)/2)/ABS(G$46)*365,"n/a") | H18: =IFERROR(((H$35+G$35)/2)/ABS(H$46)*365,"n/a") | I18: =IFERROR(((I$35+H$35)/2)/ABS(I$46)*365,"n/a")
A19: Số ngày phải thu (DSO) | B19: =IFERROR(((B$29+#REF!)/2)/B$45*365,"n/a") | C19: =IFERROR(((C$29+B$29)/2)/C$45*365,"n/a") | D19: =IFERROR(((D$29+C$29)/2)/D$45*365,"n/a") | E19: =IFERROR(((E$29+D$29)/2)/E$45*365,"n/a") | F19: =IFERROR(((F$29+E$29)/2)/F$45*365,"n/a") | G19: =IFERROR(((G$29+F$29)/2)/G$45*365,"n/a") | H19: =IFERROR(((H$29+G$29)/2)/H$45*365,"n/a") | I19: =IFERROR(((I$29+H$29)/2)/I$45*365,"n/a")
A20: Số ngày tồn kho (DIO) | B20: =IFERROR(((B$30+#REF!)/2)/ABS(B$46)*365,"n/a") | C20: =IFERROR(((C$30+B$30)/2)/ABS(C$46)*365,"n/a") | D20: =IFERROR(((D$30+C$30)/2)/ABS(D$46)*365,"n/a") | E20: =IFERROR(((E$30+D$30)/2)/ABS(E$46)*365,"n/a") | F20: =IFERROR(((F$30+E$30)/2)/ABS(F$46)*365,"n/a") | G20: =IFERROR(((G$30+F$30)/2)/ABS(G$46)*365,"n/a") | H20: =IFERROR(((H$30+G$30)/2)/ABS(H$46)*365,"n/a") | I20: =IFERROR(((I$30+H$30)/2)/ABS(I$46)*365,"n/a")
A21: Tiền và tương đương tiền/Tài sản | B21: =IFERROR(B$28/B$33,"n/a") | C21: =IFERROR(C$28/C$33,"n/a") | D21: =IFERROR(D$28/D$33,"n/a") | E21: =IFERROR(E$28/E$33,"n/a") | F21: =IFERROR(F$28/F$33,"n/a") | G21: =IFERROR(G$28/G$33,"n/a") | H21: =IFERROR(H$28/H$33,"n/a") | I21: =IFERROR(I$28/I$33,"n/a")
A22: Hàng tồn kho/Tài sản | B22: =IFERROR(B$30/B$33,"n/a") | C22: =IFERROR(C$30/C$33,"n/a") | D22: =IFERROR(D$30/D$33,"n/a") | E22: =IFERROR(E$30/E$33,"n/a") | F22: =IFERROR(F$30/F$33,"n/a") | G22: =IFERROR(G$30/G$33,"n/a") | H22: =IFERROR(H$30/H$33,"n/a") | I22: =IFERROR(I$30/I$33,"n/a")
A24: II. DỮ LIỆU TRÍCH XUẤT (tự động dò theo tên khoản mục)
A25: Khoản mục | B25: =balance_sheet!B1 | C25: =balance_sheet!C1 | D25: =balance_sheet!D1 | E25: =balance_sheet!E1 | F25: =balance_sheet!F1 | G25: =balance_sheet!G1 | H25: =balance_sheet!H1 | I25: =balance_sheet!I1
A26: CĐKT
A27: Tài sản
A28: Tiền và tương đương tiền | B28: =IFERROR(INDEX(balance_sheet!$B:$XFD,MATCH("Tiền và tương đương tiền",balance_sheet!$A:$A,0),MATCH(B$25,balance_sheet!$B$1:$XFD$1,0)),"") | C28: =IFERROR(INDEX(balance_sheet!$B:$XFD,MATCH("Tiền và tương đương tiền",balance_sheet!$A:$A,0),MATCH(C$25,balance_sheet!$B$1:$XFD$1,0)),"") | D28: =IFERROR(INDEX(balance_sheet!$B:$XFD,MATCH("Tiền và tương đương tiền",balance_sheet!$A:$A,0),MATCH(D$25,balance_sheet!$B$1:$XFD$1,0)),"") | E28: =IFERROR(INDEX(balance_sheet!$B:$XFD,MATCH("Tiền và tương đương tiền",balance_sheet!$A:$A,0),MATCH(E$25,balance_sheet!$B$1:$XFD$1,0)),"") | F28: =IFERROR(INDEX(balance_sheet!$B:$XFD,MATCH("Tiền và tương đương tiền",balance_sheet!$A:$A,0),MATCH(F$25,balance_sheet!$B$1:$XFD$1,0)),"") | G28: =IFERROR(INDEX(balance_sheet!$B:$XFD,MATCH("Tiền và tương đương tiền",balance_sheet!$A:$A,0),MATCH(G$25,balance_sheet!$B$1:$XFD$1,0)),"") | H28: =IFERROR(INDEX(balance_sheet!$B:$XFD,MATCH("Tiền và tương đương tiền",balance_sheet!$A:$A,0),MATCH(H$25,balance_sheet!$B$1:$XFD$1,0)),"") | I28: =IFERROR(INDEX(balance_sheet!$B:$XFD,MATCH("Tiền và tương đương tiền",balance_sheet!$A:$A,0),MATCH(I$25,balance_sheet!$B$1:$XFD$1,0)),"")
A29: Phải thu khách hàng | B29: =IFERROR(INDEX(balance_sheet!$B:$XFD,MATCH("Phải thu khách hàng",balance_sheet!$A:$A,0),MATCH(B$25,balance_sheet!$B$1:$XFD$1,0)),"") | C29: =IFERROR(INDEX(balance_sheet!$B:$XFD,MATCH("Phải thu khách hàng",balance_sheet!$A:$A,0),MATCH(C$25,balance_sheet!$B$1:$XFD$1,0)),"") | D29: =IFERROR(INDEX(balance_sheet!$B:$XFD,MATCH("Phải thu khách hàng",balance_sheet!$A:$A,0),MATCH(D$25,balance_sheet!$B$1:$XFD$1,0)),"") | E29: =IFERROR(INDEX(balance_sheet!$B:$XFD,MATCH("Phải thu khách hàng",balance_sheet!$A:$A,0),MATCH(E$25,balance_sheet!$B$1:$XFD$1,0)),"") | F29: =IFERROR(INDEX(balance_sheet!$B:$XFD,MATCH("Phải thu khách hàng",balance_sheet!$A:$A,0),MATCH(F$25,balance_sheet!$B$1:$XFD$1,0)),"") | G29: =IFERROR(INDEX(balance_sheet!$B:$XFD,MATCH("Phải thu khách hàng",balance_sheet!$A:$A,0),MATCH(G$25,balance_sheet!$B$1:$XFD$1,0)),"") | H29: =IFERROR(INDEX(balance_sheet!$B:$XFD,MATCH("Phải thu khách hàng",balance_sheet!$A:$A,0),MATCH(H$25,balance_sheet!$B$1:$XFD$1,0)),"") | I29: =IFERROR(INDEX(balance_sheet!$B:$XFD,MATCH("Phải thu khách hàng",balance_sheet!$A:$A,0),MATCH(I$25,balance_sheet!$B$1:$XFD$1,0)),"")
A30: Hàng tồn kho, ròng | B30: =IFERROR(INDEX(balance_sheet!$B:$XFD,MATCH("Hàng tồn kho, ròng",balance_sheet!$A:$A,0),MATCH(B$25,balance_sheet!$B$1:$XFD$1,0)),"") | C30: =IFERROR(INDEX(balance_sheet!$B:$XFD,MATCH("Hàng tồn kho, ròng",balance_sheet!$A:$A,0),MATCH(C$25,balance_sheet!$B$1:$XFD$1,0)),"") | D30: =IFERROR(INDEX(balance_sheet!$B:$XFD,MATCH("Hàng tồn kho, ròng",balance_sheet!$A:$A,0),MATCH(D$25,balance_sheet!$B$1:$XFD$1,0)),"") | E30: =IFERROR(INDEX(balance_sheet!$B:$XFD,MATCH("Hàng tồn kho, ròng",balance_sheet!$A:$A,0),MATCH(E$25,balance_sheet!$B$1:$XFD$1,0)),"") | F30: =IFERROR(INDEX(balance_sheet!$B:$XFD,MATCH("Hàng tồn kho, ròng",balance_sheet!$A:$A,0),MATCH(F$25,balance_sheet!$B$1:$XFD$1,0)),"") | G30: =IFERROR(INDEX(balance_sheet!$B:$XFD,MATCH("Hàng tồn kho, ròng",balance_sheet!$A:$A,0),MATCH(G$25,balance_sheet!$B$1:$XFD$1,0)),"") | H30: =IFERROR(INDEX(balance_sheet!$B:$XFD,MATCH("Hàng tồn kho, ròng",balance_sheet!$A:$A,0),MATCH(H$25,balance_sheet!$B$1:$XFD$1,0)),"") | I30: =IFERROR(INDEX(balance_sheet!$B:$XFD,MATCH("Hàng tồn kho, ròng",balance_sheet!$A:$A,0),MATCH(I$25,balance_sheet!$B$1:$XFD$1,0)),"")
A31: TÀI SẢN NGẮN HẠN | B31: =IFERROR(INDEX(balance_sheet!$B:$XFD,MATCH("TÀI SẢN NGẮN HẠN",balance_sheet!$A:$A,0),MATCH(B$25,balance_sheet!$B$1:$XFD$1,0)),"") | C31: =IFERROR(INDEX(balance_sheet!$B:$XFD,MATCH("TÀI SẢN NGẮN HẠN",balance_sheet!$A:$A,0),MATCH(C$25,balance_sheet!$B$1:$XFD$1,0)),"") | D31: =IFERROR(INDEX(balance_sheet!$B:$XFD,MATCH("TÀI SẢN NGẮN HẠN",balance_sheet!$A:$A,0),MATCH(D$25,balance_sheet!$B$1:$XFD$1,0)),"") | E31: =IFERROR(INDEX(balance_sheet!$B:$XFD,MATCH("TÀI SẢN NGẮN HẠN",balance_sheet!$A:$A,0),MATCH(E$25,balance_sheet!$B$1:$XFD$1,0)),"") | F31: =IFERROR(INDEX(balance_sheet!$B:$XFD,MATCH("TÀI SẢN NGẮN HẠN",balance_sheet!$A:$A,0),MATCH(F$25,balance_sheet!$B$1:$XFD$1,0)),"") | G31: =IFERROR(INDEX(balance_sheet!$B:$XFD,MATCH("TÀI SẢN NGẮN HẠN",balance_sheet!$A:$A,0),MATCH(G$25,balance_sheet!$B$1:$XFD$1,0)),"") | H31: =IFERROR(INDEX(balance_sheet!$B:$XFD,MATCH("TÀI SẢN NGẮN HẠN",balance_sheet!$A:$A,0),MATCH(H$25,balance_sheet!$B$1:$XFD$1,0)),"") | I31: =IFERROR(INDEX(balance_sheet!$B:$XFD,MATCH("TÀI SẢN NGẮN HẠN",balance_sheet!$A:$A,0),MATCH(I$25,balance_sheet!$B$1:$XFD$1,0)),"")
A32: GTCL tài sản cố định vô hình | B32: =IFERROR(INDEX(balance_sheet!$B:$XFD,MATCH("GTCL tài sản cố định vô hình",balance_sheet!$A:$A,0),MATCH(B$25,balance_sheet!$B$1:$XFD$1,0)),"") | C32: =IFERROR(INDEX(balance_sheet!$B:$XFD,MATCH("GTCL tài sản cố định vô hình",balance_sheet!$A:$A,0),MATCH(C$25,balance_sheet!$B$1:$XFD$1,0)),"") | D32: =IFERROR(INDEX(balance_sheet!$B:$XFD,MATCH("GTCL tài sản cố định vô hình",balance_sheet!$A:$A,0),MATCH(D$25,balance_sheet!$B$1:$XFD$1,0)),"") | E32: =IFERROR(INDEX(balance_sheet!$B:$XFD,MATCH("GTCL tài sản cố định vô hình",balance_sheet!$A:$A,0),MATCH(E$25,balance_sheet!$B$1:$XFD$1,0)),"") | F32: =IFERROR(INDEX(balance_sheet!$B:$XFD,MATCH("GTCL tài sản cố định vô hình",balance_sheet!$A:$A,0),MATCH(F$25,balance_sheet!$B$1:$XFD$1,0)),"") | G32: =IFERROR(INDEX(balance_sheet!$B:$XFD,MATCH("GTCL tài sản cố định vô hình",balance_sheet!$A:$A,0),MATCH(G$25,balance_sheet!$B$1:$XFD$1,0)),"") | H32: =IFERROR(INDEX(balance_sheet!$B:$XFD,MATCH("GTCL tài sản cố định vô hình",balance_sheet!$A:$A,0),MATCH(H$25,balance_sheet!$B$1:$XFD$1,0)),"") | I32: =IFERROR(INDEX(balance_sheet!$B:$XFD,MATCH("GTCL tài sản cố định vô hình",balance_sheet!$A:$A,0),MATCH(I$25,balance_sheet!$B$1:$XFD$1,0)),"")
A33: TỔNG CỘNG TÀI SẢN | B33: =IFERROR(INDEX(balance_sheet!$B:$XFD,MATCH("TỔNG CỘNG TÀI SẢN",balance_sheet!$A:$A,0),MATCH(B$25,balance_sheet!$B$1:$XFD$1,0)),"") | C33: =IFERROR(INDEX(balance_sheet!$B:$XFD,MATCH("TỔNG CỘNG TÀI SẢN",balance_sheet!$A:$A,0),MATCH(C$25,balance_sheet!$B$1:$XFD$1,0)),"") | D33: =IFERROR(INDEX(balance_sheet!$B:$XFD,MATCH("TỔNG CỘNG TÀI SẢN",balance_sheet!$A:$A,0),MATCH(D$25,balance_sheet!$B$1:$XFD$1,0)),"") | E33: =IFERROR(INDEX(balance_sheet!$B:$XFD,MATCH("TỔNG CỘNG TÀI SẢN",balance_sheet!$A:$A,0),MATCH(E$25,balance_sheet!$B$1:$XFD$1,0)),"") | F33: =IFERROR(INDEX(balance_sheet!$B:$XFD,MATCH("TỔNG CỘNG TÀI SẢN",balance_sheet!$A:$A,0),MATCH(F$25,balance_sheet!$B$1:$XFD$1,0)),"") | G33: =IFERROR(INDEX(balance_sheet!$B:$XFD,MATCH("TỔNG CỘNG TÀI SẢN",balance_sheet!$A:$A,0),MATCH(G$25,balance_sheet!$B$1:$XFD$1,0)),"") | H33: =IFERROR(INDEX(balance_sheet!$B:$XFD,MATCH("TỔNG CỘNG TÀI SẢN",balance_sheet!$A:$A,0),MATCH(H$25,balance_sheet!$B$1:$XFD$1,0)),"") | I33: =IFERROR(INDEX(balance_sheet!$B:$XFD,MATCH("TỔNG CỘNG TÀI SẢN",balance_sheet!$A:$A,0),MATCH(I$25,balance_sheet!$B$1:$XFD$1,0)),"")
A34: Nguồn vốn
A35: Phải trả người bán | B35: =IFERROR(INDEX(balance_sheet!$B:$XFD,MATCH("Phải trả người bán",balance_sheet!$A:$A,0),MATCH(B$25,balance_sheet!$B$1:$XFD$1,0)),"") | C35: =IFERROR(INDEX(balance_sheet!$B:$XFD,MATCH("Phải trả người bán",balance_sheet!$A:$A,0),MATCH(C$25,balance_sheet!$B$1:$XFD$1,0)),"") | D35: =IFERROR(INDEX(balance_sheet!$B:$XFD,MATCH("Phải trả người bán",balance_sheet!$A:$A,0),MATCH(D$25,balance_sheet!$B$1:$XFD$1,0)),"") | E35: =IFERROR(INDEX(balance_sheet!$B:$XFD,MATCH("Phải trả người bán",balance_sheet!$A:$A,0),MATCH(E$25,balance_sheet!$B$1:$XFD$1,0)),"") | F35: =IFERROR(INDEX(balance_sheet!$B:$XFD,MATCH("Phải trả người bán",balance_sheet!$A:$A,0),MATCH(F$25,balance_sheet!$B$1:$XFD$1,0)),"") | G35: =IFERROR(INDEX(balance_sheet!$B:$XFD,MATCH("Phải trả người bán",balance_sheet!$A:$A,0),MATCH(G$25,balance_sheet!$B$1:$XFD$1,0)),"") | H35: =IFERROR(INDEX(balance_sheet!$B:$XFD,MATCH("Phải trả người bán",balance_sheet!$A:$A,0),MATCH(H$25,balance_sheet!$B$1:$XFD$1,0)),"") | I35: =IFERROR(INDEX(balance_sheet!$B:$XFD,MATCH("Phải trả người bán",balance_sheet!$A:$A,0),MATCH(I$25,balance_sheet!$B$1:$XFD$1,0)),"")
A36: Vay ngắn hạn | B36: =IFERROR(INDEX(balance_sheet!$B:$XFD,MATCH("Vay ngắn hạn",balance_sheet!$A:$A,0),MATCH(B$25,balance_sheet!$B$1:$XFD$1,0)),"") | C36: =IFERROR(INDEX(balance_sheet!$B:$XFD,MATCH("Vay ngắn hạn",balance_sheet!$A:$A,0),MATCH(C$25,balance_sheet!$B$1:$XFD$1,0)),"") | D36: =IFERROR(INDEX(balance_sheet!$B:$XFD,MATCH("Vay ngắn hạn",balance_sheet!$A:$A,0),MATCH(D$25,balance_sheet!$B$1:$XFD$1,0)),"") | E36: =IFERROR(INDEX(balance_sheet!$B:$XFD,MATCH("Vay ngắn hạn",balance_sheet!$A:$A,0),MATCH(E$25,balance_sheet!$B$1:$XFD$1,0)),"") | F36: =IFERROR(INDEX(balance_sheet!$B:$XFD,MATCH("Vay ngắn hạn",balance_sheet!$A:$A,0),MATCH(F$25,balance_sheet!$B$1:$XFD$1,0)),"") | G36: =IFERROR(INDEX(balance_sheet!$B:$XFD,MATCH("Vay ngắn hạn",balance_sheet!$A:$A,0),MATCH(G$25,balance_sheet!$B$1:$XFD$1,0)),"") | H36: =IFERROR(INDEX(balance_sheet!$B:$XFD,MATCH("Vay ngắn hạn",balance_sheet!$A:$A,0),MATCH(H$25,balance_sheet!$B$1:$XFD$1,0)),"") | I36: =IFERROR(INDEX(balance_sheet!$B:$XFD,MATCH("Vay ngắn hạn",balance_sheet!$A:$A,0),MATCH(I$25,balance_sheet!$B$1:$XFD$1,0)),"")
A37: Nợ ngắn hạn | B37: =IFERROR(INDEX(balance_sheet!$B:$XFD,MATCH("Nợ ngắn hạn",balance_sheet!$A:$A,0),MATCH(B$25,balance_sheet!$B$1:$XFD$1,0)),"") | C37: =IFERROR(INDEX(balance_sheet!$B:$XFD,MATCH("Nợ ngắn hạn",balance_sheet!$A:$A,0),MATCH(C$25,balance_sheet!$B$1:$XFD$1,0)),"") | D37: =IFERROR(INDEX(balance_sheet!$B:$XFD,MATCH("Nợ ngắn hạn",balance_sheet!$A:$A,0),MATCH(D$25,balance_sheet!$B$1:$XFD$1,0)),"") | E37: =IFERROR(INDEX(balance_sheet!$B:$XFD,MATCH("Nợ ngắn hạn",balance_sheet!$A:$A,0),MATCH(E$25,balance_sheet!$B$1:$XFD$1,0)),"") | F37: =IFERROR(INDEX(balance_sheet!$B:$XFD,MATCH("Nợ ngắn hạn",balance_sheet!$A:$A,0),MATCH(F$25,balance_sheet!$B$1:$XFD$1,0)),"") | G37: =IFERROR(INDEX(balance_sheet!$B:$XFD,MATCH("Nợ ngắn hạn",balance_sheet!$A:$A,0),MATCH(G$25,balance_sheet!$B$1:$XFD$1,0)),"") | H37: =IFERROR(INDEX(balance_sheet!$B:$XFD,MATCH("Nợ ngắn hạn",balance_sheet!$A:$A,0),MATCH(H$25,balance_sheet!$B$1:$XFD$1,0)),"") | I37: =IFERROR(INDEX(balance_sheet!$B:$XFD,MATCH("Nợ ngắn hạn",balance_sheet!$A:$A,0),MATCH(I$25,balance_sheet!$B$1:$XFD$1,0)),"")
A38: Vay dài hạn | B38: =IFERROR(INDEX(balance_sheet!$B:$XFD,MATCH("Vay dài hạn",balance_sheet!$A:$A,0),MATCH(B$25,balance_sheet!$B$1:$XFD$1,0)),"") | C38: =IFERROR(INDEX(balance_sheet!$B:$XFD,MATCH("Vay dài hạn",balance_sheet!$A:$A,0),MATCH(C$25,balance_sheet!$B$1:$XFD$1,0)),"") | D38: =IFERROR(INDEX(balance_sheet!$B:$XFD,MATCH("Vay dài hạn",balance_sheet!$A:$A,0),MATCH(D$25,balance_sheet!$B$1:$XFD$1,0)),"") | E38: =IFERROR(INDEX(balance_sheet!$B:$XFD,MATCH("Vay dài hạn",balance_sheet!$A:$A,0),MATCH(E$25,balance_sheet!$B$1:$XFD$1,0)),"") | F38: =IFERROR(INDEX(balance_sheet!$B:$XFD,MATCH("Vay dài hạn",balance_sheet!$A:$A,0),MATCH(F$25,balance_sheet!$B$1:$XFD$1,0)),"") | G38: =IFERROR(INDEX(balance_sheet!$B:$XFD,MATCH("Vay dài hạn",balance_sheet!$A:$A,0),MATCH(G$25,balance_sheet!$B$1:$XFD$1,0)),"") | H38: =IFERROR(INDEX(balance_sheet!$B:$XFD,MATCH("Vay dài hạn",balance_sheet!$A:$A,0),MATCH(H$25,balance_sheet!$B$1:$XFD$1,0)),"") | I38: =IFERROR(INDEX(balance_sheet!$B:$XFD,MATCH("Vay dài hạn",balance_sheet!$A:$A,0),MATCH(I$25,balance_sheet!$B$1:$XFD$1,0)),"")
A39: Nợ dài hạn | B39: =IFERROR(INDEX(balance_sheet!$B:$XFD,MATCH("Nợ dài hạn",balance_sheet!$A:$A,0),MATCH(B$25,balance_sheet!$B$1:$XFD$1,0)),"") | C39: =IFERROR(INDEX(balance_sheet!$B:$XFD,MATCH("Nợ dài hạn",balance_sheet!$A:$A,0),MATCH(C$25,balance_sheet!$B$1:$XFD$1,0)),"") | D39: =IFERROR(INDEX(balance_sheet!$B:$XFD,MATCH("Nợ dài hạn",balance_sheet!$A:$A,0),MATCH(D$25,balance_sheet!$B$1:$XFD$1,0)),"") | E39: =IFERROR(INDEX(balance_sheet!$B:$XFD,MATCH("Nợ dài hạn",balance_sheet!$A:$A,0),MATCH(E$25,balance_sheet!$B$1:$XFD$1,0)),"") | F39: =IFERROR(INDEX(balance_sheet!$B:$XFD,MATCH("Nợ dài hạn",balance_sheet!$A:$A,0),MATCH(F$25,balance_sheet!$B$1:$XFD$1,0)),"") | G39: =IFERROR(INDEX(balance_sheet!$B:$XFD,MATCH("Nợ dài hạn",balance_sheet!$A:$A,0),MATCH(G$25,balance_sheet!$B$1:$XFD$1,0)),"") | H39: =IFERROR(INDEX(balance_sheet!$B:$XFD,MATCH("Nợ dài hạn",balance_sheet!$A:$A,0),MATCH(H$25,balance_sheet!$B$1:$XFD$1,0)),"") | I39: =IFERROR(INDEX(balance_sheet!$B:$XFD,MATCH("Nợ dài hạn",balance_sheet!$A:$A,0),MATCH(I$25,balance_sheet!$B$1:$XFD$1,0)),"")
A40: NỢ PHẢI TRẢ | B40: =IFERROR(INDEX(balance_sheet!$B:$XFD,MATCH("NỢ PHẢI TRẢ",balance_sheet!$A:$A,0),MATCH(B$25,balance_sheet!$B$1:$XFD$1,0)),"") | C40: =IFERROR(INDEX(balance_sheet!$B:$XFD,MATCH("NỢ PHẢI TRẢ",balance_sheet!$A:$A,0),MATCH(C$25,balance_sheet!$B$1:$XFD$1,0)),"") | D40: =IFERROR(INDEX(balance_sheet!$B:$XFD,MATCH("NỢ PHẢI TRẢ",balance_sheet!$A:$A,0),MATCH(D$25,balance_sheet!$B$1:$XFD$1,0)),"") | E40: =IFERROR(INDEX(balance_sheet!$B:$XFD,MATCH("NỢ PHẢI TRẢ",balance_sheet!$A:$A,0),MATCH(E$25,balance_sheet!$B$1:$XFD$1,0)),"") | F40: =IFERROR(INDEX(balance_sheet!$B:$XFD,MATCH("NỢ PHẢI TRẢ",balance_sheet!$A:$A,0),MATCH(F$25,balance_sheet!$B$1:$XFD$1,0)),"") | G40: =IFERROR(INDEX(balance_sheet!$B:$XFD,MATCH("NỢ PHẢI TRẢ",balance_sheet!$A:$A,0),MATCH(G$25,balance_sheet!$B$1:$XFD$1,0)),"") | H40: =IFERROR(INDEX(balance_sheet!$B:$XFD,MATCH("NỢ PHẢI TRẢ",balance_sheet!$A:$A,0),MATCH(H$25,balance_sheet!$B$1:$XFD$1,0)),"") | I40: =IFERROR(INDEX(balance_sheet!$B:$XFD,MATCH("NỢ PHẢI TRẢ",balance_sheet!$A:$A,0),MATCH(I$25,balance_sheet!$B$1:$XFD$1,0)),"")
A41: Vốn chủ sở hữu | B41: =IFERROR(INDEX(balance_sheet!$B:$XFD,MATCH("Vốn chủ sở hữu",balance_sheet!$A:$A,0),MATCH(B$25,balance_sheet!$B$1:$XFD$1,0)),"") | C41: =IFERROR(INDEX(balance_sheet!$B:$XFD,MATCH("Vốn chủ sở hữu",balance_sheet!$A:$A,0),MATCH(C$25,balance_sheet!$B$1:$XFD$1,0)),"") | D41: =IFERROR(INDEX(balance_sheet!$B:$XFD,MATCH("Vốn chủ sở hữu",balance_sheet!$A:$A,0),MATCH(D$25,balance_sheet!$B$1:$XFD$1,0)),"") | E41: =IFERROR(INDEX(balance_sheet!$B:$XFD,MATCH("Vốn chủ sở hữu",balance_sheet!$A:$A,0),MATCH(E$25,balance_sheet!$B$1:$XFD$1,0)),"") | F41: =IFERROR(INDEX(balance_sheet!$B:$XFD,MATCH("Vốn chủ sở hữu",balance_sheet!$A:$A,0),MATCH(F$25,balance_sheet!$B$1:$XFD$1,0)),"") | G41: =IFERROR(INDEX(balance_sheet!$B:$XFD,MATCH("Vốn chủ sở hữu",balance_sheet!$A:$A,0),MATCH(G$25,balance_sheet!$B$1:$XFD$1,0)),"") | H41: =IFERROR(INDEX(balance_sheet!$B:$XFD,MATCH("Vốn chủ sở hữu",balance_sheet!$A:$A,0),MATCH(H$25,balance_sheet!$B$1:$XFD$1,0)),"") | I41: =IFERROR(INDEX(balance_sheet!$B:$XFD,MATCH("Vốn chủ sở hữu",balance_sheet!$A:$A,0),MATCH(I$25,balance_sheet!$B$1:$XFD$1,0)),"")
A42: Tăng VCSH/LN cổ đông cty mẹ | B42: =(B41-#REF!)/B53 | C42: =(C41-B41)/C53 | D42: =(D41-C41)/D53 | E42: =(E41-D41)/E53 | F42: =(F41-E41)/F53 | G42: =(G41-F41)/G53 | H42: =(H41-G41)/H53 | I42: =(I41-H41)/I53
A43: Lợi ích cổ đông không kiểm soát | B43: =IFERROR(INDEX(balance_sheet!$B:$XFD,MATCH("Lợi ích cổ đông không kiểm soát",balance_sheet!$A:$A,0),MATCH(B$25,balance_sheet!$B$1:$XFD$1,0)),"") | C43: =IFERROR(INDEX(balance_sheet!$B:$XFD,MATCH("Lợi ích cổ đông không kiểm soát",balance_sheet!$A:$A,0),MATCH(C$25,balance_sheet!$B$1:$XFD$1,0)),"") | D43: =IFERROR(INDEX(balance_sheet!$B:$XFD,MATCH("Lợi ích cổ đông không kiểm soát",balance_sheet!$A:$A,0),MATCH(D$25,balance_sheet!$B$1:$XFD$1,0)),"") | E43: =IFERROR(INDEX(balance_sheet!$B:$XFD,MATCH("Lợi ích cổ đông không kiểm soát",balance_sheet!$A:$A,0),MATCH(E$25,balance_sheet!$B$1:$XFD$1,0)),"") | F43: =IFERROR(INDEX(balance_sheet!$B:$XFD,MATCH("Lợi ích cổ đông không kiểm soát",balance_sheet!$A:$A,0),MATCH(F$25,balance_sheet!$B$1:$XFD$1,0)),"") | G43: =IFERROR(INDEX(balance_sheet!$B:$XFD,MATCH("Lợi ích cổ đông không kiểm soát",balance_sheet!$A:$A,0),MATCH(G$25,balance_sheet!$B$1:$XFD$1,0)),"") | H43: =IFERROR(INDEX(balance_sheet!$B:$XFD,MATCH("Lợi ích cổ đông không kiểm soát",balance_sheet!$A:$A,0),MATCH(H$25,balance_sheet!$B$1:$XFD$1,0)),"") | I43: =IFERROR(INDEX(balance_sheet!$B:$XFD,MATCH("Lợi ích cổ đông không kiểm soát",balance_sheet!$A:$A,0),MATCH(I$25,balance_sheet!$B$1:$XFD$1,0)),"")
A44: Kết quả hoạt động kinh doanh
A45: Doanh thu thuần | B45: =IFERROR(INDEX(income_statement!$B:$XFD,MATCH("Doanh thu thuần",income_statement!$A:$A,0),MATCH(B$25,income_statement!$B$1:$XFD$1,0)),"") | C45: =IFERROR(INDEX(income_statement!$B:$XFD,MATCH("Doanh thu thuần",income_statement!$A:$A,0),MATCH(C$25,income_statement!$B$1:$XFD$1,0)),"") | D45: =IFERROR(INDEX(income_statement!$B:$XFD,MATCH("Doanh thu thuần",income_statement!$A:$A,0),MATCH(D$25,income_statement!$B$1:$XFD$1,0)),"") | E45: =IFERROR(INDEX(income_statement!$B:$XFD,MATCH("Doanh thu thuần",income_statement!$A:$A,0),MATCH(E$25,income_statement!$B$1:$XFD$1,0)),"") | F45: =IFERROR(INDEX(income_statement!$B:$XFD,MATCH("Doanh thu thuần",income_statement!$A:$A,0),MATCH(F$25,income_statement!$B$1:$XFD$1,0)),"") | G45: =IFERROR(INDEX(income_statement!$B:$XFD,MATCH("Doanh thu thuần",income_statement!$A:$A,0),MATCH(G$25,income_statement!$B$1:$XFD$1,0)),"") | H45: =IFERROR(INDEX(income_statement!$B:$XFD,MATCH("Doanh thu thuần",income_statement!$A:$A,0),MATCH(H$25,income_statement!$B$1:$XFD$1,0)),"") | I45: =IFERROR(INDEX(income_statement!$B:$XFD,MATCH("Doanh thu thuần",income_statement!$A:$A,0),MATCH(I$25,income_statement!$B$1:$XFD$1,0)),"")
A46: Giá vốn hàng bán | B46: =IFERROR(INDEX(income_statement!$B:$XFD,MATCH("Giá vốn hàng bán",income_statement!$A:$A,0),MATCH(B$25,income_statement!$B$1:$XFD$1,0)),"") | C46: =IFERROR(INDEX(income_statement!$B:$XFD,MATCH("Giá vốn hàng bán",income_statement!$A:$A,0),MATCH(C$25,income_statement!$B$1:$XFD$1,0)),"") | D46: =IFERROR(INDEX(income_statement!$B:$XFD,MATCH("Giá vốn hàng bán",income_statement!$A:$A,0),MATCH(D$25,income_statement!$B$1:$XFD$1,0)),"") | E46: =IFERROR(INDEX(income_statement!$B:$XFD,MATCH("Giá vốn hàng bán",income_statement!$A:$A,0),MATCH(E$25,income_statement!$B$1:$XFD$1,0)),"") | F46: =IFERROR(INDEX(income_statement!$B:$XFD,MATCH("Giá vốn hàng bán",income_statement!$A:$A,0),MATCH(F$25,income_statement!$B$1:$XFD$1,0)),"") | G46: =IFERROR(INDEX(income_statement!$B:$XFD,MATCH("Giá vốn hàng bán",income_statement!$A:$A,0),MATCH(G$25,income_statement!$B$1:$XFD$1,0)),"") | H46: =IFERROR(INDEX(income_statement!$B:$XFD,MATCH("Giá vốn hàng bán",income_statement!$A:$A,0),MATCH(H$25,income_statement!$B$1:$XFD$1,0)),"") | I46: =IFERROR(INDEX(income_statement!$B:$XFD,MATCH("Giá vốn hàng bán",income_statement!$A:$A,0),MATCH(I$25,income_statement!$B$1:$XFD$1,0)),"")
A47: Lợi nhuận gộp | B47: =IFERROR(INDEX(income_statement!$B:$XFD,MATCH("Lợi nhuận gộp",income_statement!$A:$A,0),MATCH(B$25,income_statement!$B$1:$XFD$1,0)),"") | C47: =IFERROR(INDEX(income_statement!$B:$XFD,MATCH("Lợi nhuận gộp",income_statement!$A:$A,0),MATCH(C$25,income_statement!$B$1:$XFD$1,0)),"") | D47: =IFERROR(INDEX(income_statement!$B:$XFD,MATCH("Lợi nhuận gộp",income_statement!$A:$A,0),MATCH(D$25,income_statement!$B$1:$XFD$1,0)),"") | E47: =IFERROR(INDEX(income_statement!$B:$XFD,MATCH("Lợi nhuận gộp",income_statement!$A:$A,0),MATCH(E$25,income_statement!$B$1:$XFD$1,0)),"") | F47: =IFERROR(INDEX(income_statement!$B:$XFD,MATCH("Lợi nhuận gộp",income_statement!$A:$A,0),MATCH(F$25,income_statement!$B$1:$XFD$1,0)),"") | G47: =IFERROR(INDEX(income_statement!$B:$XFD,MATCH("Lợi nhuận gộp",income_statement!$A:$A,0),MATCH(G$25,income_statement!$B$1:$XFD$1,0)),"") | H47: =IFERROR(INDEX(income_statement!$B:$XFD,MATCH("Lợi nhuận gộp",income_statement!$A:$A,0),MATCH(H$25,income_statement!$B$1:$XFD$1,0)),"") | I47: =IFERROR(INDEX(income_statement!$B:$XFD,MATCH("Lợi nhuận gộp",income_statement!$A:$A,0),MATCH(I$25,income_statement!$B$1:$XFD$1,0)),"")
A48: Chi phí bán hàng | B48: =IFERROR(INDEX(income_statement!$B:$XFD,MATCH("Chi phí bán hàng",income_statement!$A:$A,0),MATCH(B$25,income_statement!$B$1:$XFD$1,0)),"") | C48: =IFERROR(INDEX(income_statement!$B:$XFD,MATCH("Chi phí bán hàng",income_statement!$A:$A,0),MATCH(C$25,income_statement!$B$1:$XFD$1,0)),"") | D48: =IFERROR(INDEX(income_statement!$B:$XFD,MATCH("Chi phí bán hàng",income_statement!$A:$A,0),MATCH(D$25,income_statement!$B$1:$XFD$1,0)),"") | E48: =IFERROR(INDEX(income_statement!$B:$XFD,MATCH("Chi phí bán hàng",income_statement!$A:$A,0),MATCH(E$25,income_statement!$B$1:$XFD$1,0)),"") | F48: =IFERROR(INDEX(income_statement!$B:$XFD,MATCH("Chi phí bán hàng",income_statement!$A:$A,0),MATCH(F$25,income_statement!$B$1:$XFD$1,0)),"") | G48: =IFERROR(INDEX(income_statement!$B:$XFD,MATCH("Chi phí bán hàng",income_statement!$A:$A,0),MATCH(G$25,income_statement!$B$1:$XFD$1,0)),"") | H48: =IFERROR(INDEX(income_statement!$B:$XFD,MATCH("Chi phí bán hàng",income_statement!$A:$A,0),MATCH(H$25,income_statement!$B$1:$XFD$1,0)),"") | I48: =IFERROR(INDEX(income_statement!$B:$XFD,MATCH("Chi phí bán hàng",income_statement!$A:$A,0),MATCH(I$25,income_statement!$B$1:$XFD$1,0)),"")
A49: Chi phí quản lý doanh nghiệp | B49: =IFERROR(INDEX(income_statement!$B:$XFD,MATCH("Chi phí quản lý doanh nghiệp",income_statement!$A:$A,0),MATCH(B$25,income_statement!$B$1:$XFD$1,0)),"") | C49: =IFERROR(INDEX(income_statement!$B:$XFD,MATCH("Chi phí quản lý doanh nghiệp",income_statement!$A:$A,0),MATCH(C$25,income_statement!$B$1:$XFD$1,0)),"") | D49: =IFERROR(INDEX(income_statement!$B:$XFD,MATCH("Chi phí quản lý doanh nghiệp",income_statement!$A:$A,0),MATCH(D$25,income_statement!$B$1:$XFD$1,0)),"") | E49: =IFERROR(INDEX(income_statement!$B:$XFD,MATCH("Chi phí quản lý doanh nghiệp",income_statement!$A:$A,0),MATCH(E$25,income_statement!$B$1:$XFD$1,0)),"") | F49: =IFERROR(INDEX(income_statement!$B:$XFD,MATCH("Chi phí quản lý doanh nghiệp",income_statement!$A:$A,0),MATCH(F$25,income_statement!$B$1:$XFD$1,0)),"") | G49: =IFERROR(INDEX(income_statement!$B:$XFD,MATCH("Chi phí quản lý doanh nghiệp",income_statement!$A:$A,0),MATCH(G$25,income_statement!$B$1:$XFD$1,0)),"") | H49: =IFERROR(INDEX(income_statement!$B:$XFD,MATCH("Chi phí quản lý doanh nghiệp",income_statement!$A:$A,0),MATCH(H$25,income_statement!$B$1:$XFD$1,0)),"") | I49: =IFERROR(INDEX(income_statement!$B:$XFD,MATCH("Chi phí quản lý doanh nghiệp",income_statement!$A:$A,0),MATCH(I$25,income_statement!$B$1:$XFD$1,0)),"")
A50: Lãi/(lỗ) từ hoạt động kinh doanh | B50: =IFERROR(INDEX(income_statement!$B:$XFD,MATCH("Lãi/(lỗ) từ hoạt động kinh doanh",income_statement!$A:$A,0),MATCH(B$25,income_statement!$B$1:$XFD$1,0)),"") | C50: =IFERROR(INDEX(income_statement!$B:$XFD,MATCH("Lãi/(lỗ) từ hoạt động kinh doanh",income_statement!$A:$A,0),MATCH(C$25,income_statement!$B$1:$XFD$1,0)),"") | D50: =IFERROR(INDEX(income_statement!$B:$XFD,MATCH("Lãi/(lỗ) từ hoạt động kinh doanh",income_statement!$A:$A,0),MATCH(D$25,income_statement!$B$1:$XFD$1,0)),"") | E50: =IFERROR(INDEX(income_statement!$B:$XFD,MATCH("Lãi/(lỗ) từ hoạt động kinh doanh",income_statement!$A:$A,0),MATCH(E$25,income_statement!$B$1:$XFD$1,0)),"") | F50: =IFERROR(INDEX(income_statement!$B:$XFD,MATCH("Lãi/(lỗ) từ hoạt động kinh doanh",income_statement!$A:$A,0),MATCH(F$25,income_statement!$B$1:$XFD$1,0)),"") | G50: =IFERROR(INDEX(income_statement!$B:$XFD,MATCH("Lãi/(lỗ) từ hoạt động kinh doanh",income_statement!$A:$A,0),MATCH(G$25,income_statement!$B$1:$XFD$1,0)),"") | H50: =IFERROR(INDEX(income_statement!$B:$XFD,MATCH("Lãi/(lỗ) từ hoạt động kinh doanh",income_statement!$A:$A,0),MATCH(H$25,income_statement!$B$1:$XFD$1,0)),"") | I50: =IFERROR(INDEX(income_statement!$B:$XFD,MATCH("Lãi/(lỗ) từ hoạt động kinh doanh",income_statement!$A:$A,0),MATCH(I$25,income_statement!$B$1:$XFD$1,0)),"")
A51: Chi phí lãi vay | B51: =IFERROR(INDEX(income_statement!$B:$XFD,MATCH("Chi phí lãi vay",income_statement!$A:$A,0),MATCH(B$25,income_statement!$B$1:$XFD$1,0)),"") | C51: =IFERROR(INDEX(income_statement!$B:$XFD,MATCH("Chi phí lãi vay",income_statement!$A:$A,0),MATCH(C$25,income_statement!$B$1:$XFD$1,0)),"") | D51: =IFERROR(INDEX(income_statement!$B:$XFD,MATCH("Chi phí lãi vay",income_statement!$A:$A,0),MATCH(D$25,income_statement!$B$1:$XFD$1,0)),"") | E51: =IFERROR(INDEX(income_statement!$B:$XFD,MATCH("Chi phí lãi vay",income_statement!$A:$A,0),MATCH(E$25,income_statement!$B$1:$XFD$1,0)),"") | F51: =IFERROR(INDEX(income_statement!$B:$XFD,MATCH("Chi phí lãi vay",income_statement!$A:$A,0),MATCH(F$25,income_statement!$B$1:$XFD$1,0)),"") | G51: =IFERROR(INDEX(income_statement!$B:$XFD,MATCH("Chi phí lãi vay",income_statement!$A:$A,0),MATCH(G$25,income_statement!$B$1:$XFD$1,0)),"") | H51: =IFERROR(INDEX(income_statement!$B:$XFD,MATCH("Chi phí lãi vay",income_statement!$A:$A,0),MATCH(H$25,income_statement!$B$1:$XFD$1,0)),"") | I51: =IFERROR(INDEX(income_statement!$B:$XFD,MATCH("Chi phí lãi vay",income_statement!$A:$A,0),MATCH(I$25,income_statement!$B$1:$XFD$1,0)),"")
A52: Lãi/(lỗ) thuần sau thuế | B52: =IFERROR(INDEX(income_statement!$B:$XFD,MATCH("Lãi/(lỗ) thuần sau thuế",income_statement!$A:$A,0),MATCH(B$25,income_statement!$B$1:$XFD$1,0)),"") | C52: =IFERROR(INDEX(income_statement!$B:$XFD,MATCH("Lãi/(lỗ) thuần sau thuế",income_statement!$A:$A,0),MATCH(C$25,income_statement!$B$1:$XFD$1,0)),"") | D52: =IFERROR(INDEX(income_statement!$B:$XFD,MATCH("Lãi/(lỗ) thuần sau thuế",income_statement!$A:$A,0),MATCH(D$25,income_statement!$B$1:$XFD$1,0)),"") | E52: =IFERROR(INDEX(income_statement!$B:$XFD,MATCH("Lãi/(lỗ) thuần sau thuế",income_statement!$A:$A,0),MATCH(E$25,income_statement!$B$1:$XFD$1,0)),"") | F52: =IFERROR(INDEX(income_statement!$B:$XFD,MATCH("Lãi/(lỗ) thuần sau thuế",income_statement!$A:$A,0),MATCH(F$25,income_statement!$B$1:$XFD$1,0)),"") | G52: =IFERROR(INDEX(income_statement!$B:$XFD,MATCH("Lãi/(lỗ) thuần sau thuế",income_statement!$A:$A,0),MATCH(G$25,income_statement!$B$1:$XFD$1,0)),"") | H52: =IFERROR(INDEX(income_statement!$B:$XFD,MATCH("Lãi/(lỗ) thuần sau thuế",income_statement!$A:$A,0),MATCH(H$25,income_statement!$B$1:$XFD$1,0)),"") | I52: =IFERROR(INDEX(income_statement!$B:$XFD,MATCH("Lãi/(lỗ) thuần sau thuế",income_statement!$A:$A,0),MATCH(I$25,income_statement!$B$1:$XFD$1,0)),"")
A53: Lợi nhuận của Cổ đông của Công ty mẹ | B53: =IFERROR(INDEX(income_statement!$B:$XFD,MATCH("Lợi nhuận của Cổ đông của Công ty mẹ",income_statement!$A:$A,0),MATCH(B$25,income_statement!$B$1:$XFD$1,0)),"") | C53: =IFERROR(INDEX(income_statement!$B:$XFD,MATCH("Lợi nhuận của Cổ đông của Công ty mẹ",income_statement!$A:$A,0),MATCH(C$25,income_statement!$B$1:$XFD$1,0)),"") | D53: =IFERROR(INDEX(income_statement!$B:$XFD,MATCH("Lợi nhuận của Cổ đông của Công ty mẹ",income_statement!$A:$A,0),MATCH(D$25,income_statement!$B$1:$XFD$1,0)),"") | E53: =IFERROR(INDEX(income_statement!$B:$XFD,MATCH("Lợi nhuận của Cổ đông của Công ty mẹ",income_statement!$A:$A,0),MATCH(E$25,income_statement!$B$1:$XFD$1,0)),"") | F53: =IFERROR(INDEX(income_statement!$B:$XFD,MATCH("Lợi nhuận của Cổ đông của Công ty mẹ",income_statement!$A:$A,0),MATCH(F$25,income_statement!$B$1:$XFD$1,0)),"") | G53: =IFERROR(INDEX(income_statement!$B:$XFD,MATCH("Lợi nhuận của Cổ đông của Công ty mẹ",income_statement!$A:$A,0),MATCH(G$25,income_statement!$B$1:$XFD$1,0)),"") | H53: =IFERROR(INDEX(income_statement!$B:$XFD,MATCH("Lợi nhuận của Cổ đông của Công ty mẹ",income_statement!$A:$A,0),MATCH(H$25,income_statement!$B$1:$XFD$1,0)),"") | I53: =IFERROR(INDEX(income_statement!$B:$XFD,MATCH("Lợi nhuận của Cổ đông của Công ty mẹ",income_statement!$A:$A,0),MATCH(I$25,income_statement!$B$1:$XFD$1,0)),"")
A54: Lưu chuyển tiền tệ
A55: Khấu hao TSCĐ và BĐSĐT | B55: =IFERROR(INDEX(cash_flow!$B:$XFD,MATCH("Khấu hao TSCĐ và BĐSĐT",cash_flow!$A:$A,0),MATCH(B$25,cash_flow!$B$1:$XFD$1,0)),"") | C55: =IFERROR(INDEX(cash_flow!$B:$XFD,MATCH("Khấu hao TSCĐ và BĐSĐT",cash_flow!$A:$A,0),MATCH(C$25,cash_flow!$B$1:$XFD$1,0)),"") | D55: =IFERROR(INDEX(cash_flow!$B:$XFD,MATCH("Khấu hao TSCĐ và BĐSĐT",cash_flow!$A:$A,0),MATCH(D$25,cash_flow!$B$1:$XFD$1,0)),"") | E55: =IFERROR(INDEX(cash_flow!$B:$XFD,MATCH("Khấu hao TSCĐ và BĐSĐT",cash_flow!$A:$A,0),MATCH(E$25,cash_flow!$B$1:$XFD$1,0)),"") | F55: =IFERROR(INDEX(cash_flow!$B:$XFD,MATCH("Khấu hao TSCĐ và BĐSĐT",cash_flow!$A:$A,0),MATCH(F$25,cash_flow!$B$1:$XFD$1,0)),"") | G55: =IFERROR(INDEX(cash_flow!$B:$XFD,MATCH("Khấu hao TSCĐ và BĐSĐT",cash_flow!$A:$A,0),MATCH(G$25,cash_flow!$B$1:$XFD$1,0)),"") | H55: =IFERROR(INDEX(cash_flow!$B:$XFD,MATCH("Khấu hao TSCĐ và BĐSĐT",cash_flow!$A:$A,0),MATCH(H$25,cash_flow!$B$1:$XFD$1,0)),"") | I55: =IFERROR(INDEX(cash_flow!$B:$XFD,MATCH("Khấu hao TSCĐ và BĐSĐT",cash_flow!$A:$A,0),MATCH(I$25,cash_flow!$B$1:$XFD$1,0)),"")
A56: Tiền chi để mua sắm, xây dựng TSCĐ và các tài sản dài hạn khác | B56: =IFERROR(INDEX(cash_flow!$B:$XFD,MATCH("Tiền chi để mua sắm, xây dựng TSCĐ và các tài sản dài hạn khác",cash_flow!$A:$A,0),MATCH(B$25,cash_flow!$B$1:$XFD$1,0)),"") | C56: =IFERROR(INDEX(cash_flow!$B:$XFD,MATCH("Tiền chi để mua sắm, xây dựng TSCĐ và các tài sản dài hạn khác",cash_flow!$A:$A,0),MATCH(C$25,cash_flow!$B$1:$XFD$1,0)),"") | D56: =IFERROR(INDEX(cash_flow!$B:$XFD,MATCH("Tiền chi để mua sắm, xây dựng TSCĐ và các tài sản dài hạn khác",cash_flow!$A:$A,0),MATCH(D$25,cash_flow!$B$1:$XFD$1,0)),"") | E56: =IFERROR(INDEX(cash_flow!$B:$XFD,MATCH("Tiền chi để mua sắm, xây dựng TSCĐ và các tài sản dài hạn khác",cash_flow!$A:$A,0),MATCH(E$25,cash_flow!$B$1:$XFD$1,0)),"") | F56: =IFERROR(INDEX(cash_flow!$B:$XFD,MATCH("Tiền chi để mua sắm, xây dựng TSCĐ và các tài sản dài hạn khác",cash_flow!$A:$A,0),MATCH(F$25,cash_flow!$B$1:$XFD$1,0)),"") | G56: =IFERROR(INDEX(cash_flow!$B:$XFD,MATCH("Tiền chi để mua sắm, xây dựng TSCĐ và các tài sản dài hạn khác",cash_flow!$A:$A,0),MATCH(G$25,cash_flow!$B$1:$XFD$1,0)),"") | H56: =IFERROR(INDEX(cash_flow!$B:$XFD,MATCH("Tiền chi để mua sắm, xây dựng TSCĐ và các tài sản dài hạn khác",cash_flow!$A:$A,0),MATCH(H$25,cash_flow!$B$1:$XFD$1,0)),"") | I56: =IFERROR(INDEX(cash_flow!$B:$XFD,MATCH("Tiền chi để mua sắm, xây dựng TSCĐ và các tài sản dài hạn khác",cash_flow!$A:$A,0),MATCH(I$25,cash_flow!$B$1:$XFD$1,0)),"")
A57: Lưu chuyển tiền tệ ròng từ các hoạt động sản xuất kinh doanh | B57: =IFERROR(INDEX(cash_flow!$B:$XFD,MATCH("Lưu chuyển tiền tệ ròng từ các hoạt động sản xuất kinh doanh",cash_flow!$A:$A,0),MATCH(B$25,cash_flow!$B$1:$XFD$1,0)),"") | C57: =IFERROR(INDEX(cash_flow!$B:$XFD,MATCH("Lưu chuyển tiền tệ ròng từ các hoạt động sản xuất kinh doanh",cash_flow!$A:$A,0),MATCH(C$25,cash_flow!$B$1:$XFD$1,0)),"") | D57: =IFERROR(INDEX(cash_flow!$B:$XFD,MATCH("Lưu chuyển tiền tệ ròng từ các hoạt động sản xuất kinh doanh",cash_flow!$A:$A,0),MATCH(D$25,cash_flow!$B$1:$XFD$1,0)),"") | E57: =IFERROR(INDEX(cash_flow!$B:$XFD,MATCH("Lưu chuyển tiền tệ ròng từ các hoạt động sản xuất kinh doanh",cash_flow!$A:$A,0),MATCH(E$25,cash_flow!$B$1:$XFD$1,0)),"") | F57: =IFERROR(INDEX(cash_flow!$B:$XFD,MATCH("Lưu chuyển tiền tệ ròng từ các hoạt động sản xuất kinh doanh",cash_flow!$A:$A,0),MATCH(F$25,cash_flow!$B$1:$XFD$1,0)),"") | G57: =IFERROR(INDEX(cash_flow!$B:$XFD,MATCH("Lưu chuyển tiền tệ ròng từ các hoạt động sản xuất kinh doanh",cash_flow!$A:$A,0),MATCH(G$25,cash_flow!$B$1:$XFD$1,0)),"") | H57: =IFERROR(INDEX(cash_flow!$B:$XFD,MATCH("Lưu chuyển tiền tệ ròng từ các hoạt động sản xuất kinh doanh",cash_flow!$A:$A,0),MATCH(H$25,cash_flow!$B$1:$XFD$1,0)),"") | I57: =IFERROR(INDEX(cash_flow!$B:$XFD,MATCH("Lưu chuyển tiền tệ ròng từ các hoạt động sản xuất kinh doanh",cash_flow!$A:$A,0),MATCH(I$25,cash_flow!$B$1:$XFD$1,0)),"")
A61: CHỈ SỐ THÊM | B61: 2026 | C61: 2027 | D61: 2028 | E61: 2029 | F61: 2030 | G61: 2031 | H61: 2032 | I61: 2033
A62: Khả năng sinh lời & hiệu quả sử dụng vốn
A63: ROCE | B63: =IFERROR(B$65/(B$33-B$37),"n/a") | C63: =IFERROR(C$65/(C$33-C$37),"n/a") | D63: =IFERROR(D$65/(D$33-D$37),"n/a") | E63: =IFERROR(E$65/(E$33-E$37),"n/a") | F63: =IFERROR(F$65/(F$33-F$37),"n/a") | G63: =IFERROR(G$65/(G$33-G$37),"n/a") | H63: =IFERROR(H$65/(H$33-H$37),"n/a") | I63: =IFERROR(I$65/(I$33-I$37),"n/a")
A64: CROIC | B64: =IFERROR(B$69/(B$33-B$37),"n/a") | C64: =IFERROR(C$69/(C$33-C$37),"n/a") | D64: =IFERROR(D$69/(D$33-D$37),"n/a") | E64: =IFERROR(E$69/(E$33-E$37),"n/a") | F64: =IFERROR(F$69/(F$33-F$37),"n/a") | G64: =IFERROR(G$69/(G$33-G$37),"n/a") | H64: =IFERROR(H$69/(H$33-H$37),"n/a") | I64: =IFERROR(I$69/(I$33-I$37),"n/a")
A65: EBIT | B65: =IFERROR(B$50+ABS(B$51),"n/a") | C65: =IFERROR(C$50+ABS(C$51),"n/a") | D65: =IFERROR(D$50+ABS(D$51),"n/a") | E65: =IFERROR(E$50+ABS(E$51),"n/a") | F65: =IFERROR(F$50+ABS(F$51),"n/a") | G65: =IFERROR(G$50+ABS(G$51),"n/a") | H65: =IFERROR(H$50+ABS(H$51),"n/a") | I65: =IFERROR(I$50+ABS(I$51),"n/a")
A66: EBIT/DT | B66: =IFERROR(B$65/B$45,"n/a") | C66: =IFERROR(C$65/C$45,"n/a") | D66: =IFERROR(D$65/D$45,"n/a") | E66: =IFERROR(E$65/E$45,"n/a") | F66: =IFERROR(F$65/F$45,"n/a") | G66: =IFERROR(G$65/G$45,"n/a") | H66: =IFERROR(H$65/H$45,"n/a") | I66: =IFERROR(I$65/I$45,"n/a")
A67: DT/TS | B67: =IFERROR(B$45/B$33,"n/a") | C67: =IFERROR(C$45/C$33,"n/a") | D67: =IFERROR(D$45/D$33,"n/a") | E67: =IFERROR(E$45/E$33,"n/a") | F67: =IFERROR(F$45/F$33,"n/a") | G67: =IFERROR(G$45/G$33,"n/a") | H67: =IFERROR(H$45/H$33,"n/a") | I67: =IFERROR(I$45/I$33,"n/a")
A68: Dòng tiền & tái đầu tư
A69: FCF | B69: =IFERROR(B$57-ABS(B$56),"n/a") | C69: =IFERROR(C$57-ABS(C$56),"n/a") | D69: =IFERROR(D$57-ABS(D$56),"n/a") | E69: =IFERROR(E$57-ABS(E$56),"n/a") | F69: =IFERROR(F$57-ABS(F$56),"n/a") | G69: =IFERROR(G$57-ABS(G$56),"n/a") | H69: =IFERROR(H$57-ABS(H$56),"n/a") | I69: =IFERROR(I$57-ABS(I$56),"n/a")
A70: FCF/DT | B70: =IFERROR(B$69/B$45,"n/a") | C70: =IFERROR(C$69/C$45,"n/a") | D70: =IFERROR(D$69/D$45,"n/a") | E70: =IFERROR(E$69/E$45,"n/a") | F70: =IFERROR(F$69/F$45,"n/a") | G70: =IFERROR(G$69/G$45,"n/a") | H70: =IFERROR(H$69/H$45,"n/a") | I70: =IFERROR(I$69/I$45,"n/a")
A71: FCF/Nợ ngắn hạn | B71: =IFERROR(B$69/B$37,"n/a") | C71: =IFERROR(C$69/C$37,"n/a") | D71: =IFERROR(D$69/D$37,"n/a") | E71: =IFERROR(E$69/E$37,"n/a") | F71: =IFERROR(F$69/F$37,"n/a") | G71: =IFERROR(G$69/G$37,"n/a") | H71: =IFERROR(H$69/H$37,"n/a") | I71: =IFERROR(I$69/I$37,"n/a")
A72: Capex | B72: =IFERROR(ABS(B$56),"n/a") | C72: =IFERROR(ABS(C$56),"n/a") | D72: =IFERROR(ABS(D$56),"n/a") | E72: =IFERROR(ABS(E$56),"n/a") | F72: =IFERROR(ABS(F$56),"n/a") | G72: =IFERROR(ABS(G$56),"n/a") | H72: =IFERROR(ABS(H$56),"n/a") | I72: =IFERROR(ABS(I$56),"n/a")
A73: Capex/TS | B73: =IFERROR(B$72/B$33,"n/a") | C73: =IFERROR(C$72/C$33,"n/a") | D73: =IFERROR(D$72/D$33,"n/a") | E73: =IFERROR(E$72/E$33,"n/a") | F73: =IFERROR(F$72/F$33,"n/a") | G73: =IFERROR(G$72/G$33,"n/a") | H73: =IFERROR(H$72/H$33,"n/a") | I73: =IFERROR(I$72/I$33,"n/a")
A74: Capex/LNST | B74: =IFERROR(B$72/ABS(B$52),"n/a") | C74: =IFERROR(C$72/ABS(C$52),"n/a") | D74: =IFERROR(D$72/ABS(D$52),"n/a") | E74: =IFERROR(E$72/ABS(E$52),"n/a") | F74: =IFERROR(F$72/ABS(F$52),"n/a") | G74: =IFERROR(G$72/ABS(G$52),"n/a") | H74: =IFERROR(H$72/ABS(H$52),"n/a") | I74: =IFERROR(I$72/ABS(I$52),"n/a")
A75: Chi phí khấu hao/Lợi nhuận gộp | B75: =IFERROR(ABS(B$55)/B$47,"n/a") | C75: =IFERROR(ABS(C$55)/C$47,"n/a") | D75: =IFERROR(ABS(D$55)/D$47,"n/a") | E75: =IFERROR(ABS(E$55)/E$47,"n/a") | F75: =IFERROR(ABS(F$55)/F$47,"n/a") | G75: =IFERROR(ABS(G$55)/G$47,"n/a") | H75: =IFERROR(ABS(H$55)/H$47,"n/a") | I75: =IFERROR(ABS(I$55)/I$47,"n/a")
A76: EBIT/Chi phí lãi vay | B76: =IFERROR(B$65/ABS(B$51),"n/a") | C76: =IFERROR(C$65/ABS(C$51),"n/a") | D76: =IFERROR(D$65/ABS(D$51),"n/a") | E76: =IFERROR(E$65/ABS(E$51),"n/a") | F76: =IFERROR(F$65/ABS(F$51),"n/a") | G76: =IFERROR(G$65/ABS(G$51),"n/a") | H76: =IFERROR(H$65/ABS(H$51),"n/a") | I76: =IFERROR(I$65/ABS(I$51),"n/a")
A77: Vốn lưu động & hiệu quả hoạt động
A78: Vòng quay tiền mặt | B78: =IFERROR(B$19+B$20-B$18,"n/a") | C78: =IFERROR(C$19+C$20-C$18,"n/a") | D78: =IFERROR(D$19+D$20-D$18,"n/a") | E78: =IFERROR(E$19+E$20-E$18,"n/a") | F78: =IFERROR(F$19+F$20-F$18,"n/a") | G78: =IFERROR(G$19+G$20-G$18,"n/a") | H78: =IFERROR(H$19+H$20-H$18,"n/a") | I78: =IFERROR(I$19+I$20-I$18,"n/a")
A79: HTK/DT | B79: =IFERROR(B$30/B$45,"n/a") | C79: =IFERROR(C$30/C$45,"n/a") | D79: =IFERROR(D$30/D$45,"n/a") | E79: =IFERROR(E$30/E$45,"n/a") | F79: =IFERROR(F$30/F$45,"n/a") | G79: =IFERROR(G$30/G$45,"n/a") | H79: =IFERROR(H$30/H$45,"n/a") | I79: =IFERROR(I$30/I$45,"n/a")
A80: HTK/TS | B80: =IFERROR(B$30/B$33,"n/a") | C80: =IFERROR(C$30/C$33,"n/a") | D80: =IFERROR(D$30/D$33,"n/a") | E80: =IFERROR(E$30/E$33,"n/a") | F80: =IFERROR(F$30/F$33,"n/a") | G80: =IFERROR(G$30/G$33,"n/a") | H80: =IFERROR(H$30/H$33,"n/a") | I80: =IFERROR(I$30/I$33,"n/a")
A81: DT/TS | B81: =IFERROR(B$45/B$33,"n/a") | C81: =IFERROR(C$45/C$33,"n/a") | D81: =IFERROR(D$45/D$33,"n/a") | E81: =IFERROR(E$45/E$33,"n/a") | F81: =IFERROR(F$45/F$33,"n/a") | G81: =IFERROR(G$45/G$33,"n/a") | H81: =IFERROR(H$45/H$33,"n/a") | I81: =IFERROR(I$45/I$33,"n/a")
A82: Khả năng thanh toán
A83: (TS ngắn hạn − HTK)/Nợ ngắn hạn | B83: =IFERROR((B$31-B$30)/B$37,"n/a") | C83: =IFERROR((C$31-C$30)/C$37,"n/a") | D83: =IFERROR((D$31-D$30)/D$37,"n/a") | E83: =IFERROR((E$31-E$30)/E$37,"n/a") | F83: =IFERROR((F$31-F$30)/F$37,"n/a") | G83: =IFERROR((G$31-G$30)/G$37,"n/a") | H83: =IFERROR((H$31-H$30)/H$37,"n/a") | I83: =IFERROR((I$31-I$30)/I$37,"n/a")
A84: TS ngắn hạn/Nợ ngắn hạn | B84: =IFERROR(B$31/B$37,"n/a") | C84: =IFERROR(C$31/C$37,"n/a") | D84: =IFERROR(D$31/D$37,"n/a") | E84: =IFERROR(E$31/E$37,"n/a") | F84: =IFERROR(F$31/F$37,"n/a") | G84: =IFERROR(G$31/G$37,"n/a") | H84: =IFERROR(H$31/H$37,"n/a") | I84: =IFERROR(I$31/I$37,"n/a")
A85: Tài sản & cơ cấu tài sản
A86: TSCĐ vô hình | B86: =IFERROR(B$32,"n/a") | C86: =IFERROR(C$32,"n/a") | D86: =IFERROR(D$32,"n/a") | E86: =IFERROR(E$32,"n/a") | F86: =IFERROR(F$32,"n/a") | G86: =IFERROR(G$32,"n/a") | H86: =IFERROR(H$32,"n/a") | I86: =IFERROR(I$32,"n/a")
A87: Tài sản vô hình/Giá trị sổ sách | B87: =IFERROR(B$32/B$41,"n/a") | C87: =IFERROR(C$32/C$41,"n/a") | D87: =IFERROR(D$32/D$41,"n/a") | E87: =IFERROR(E$32/E$41,"n/a") | F87: =IFERROR(F$32/F$41,"n/a") | G87: =IFERROR(G$32/G$41,"n/a") | H87: =IFERROR(H$32/H$41,"n/a") | I87: =IFERROR(I$32/I$41,"n/a")

Sheet Dự báo tăng trưởng
B1: Q1/2026 | C1: Q2/2026 | D1: Q3/2026 | E1: Q4/2026
A2: Số CP | B2: 8442964520 | C2: 8442964520 | D2: 8442964520 | E2: 8442964520
A3: Thị giá | B3: 22250 | C3: 22250 | D3: 22250 | E3: 22250
A4: Vốn hoá | B4: =B2*B3 | C4: =C2*C3 | D4: =D2*D3 | E4: =E2*E3
A6: VCSH | B6: 139782000000000 | C6: 141516000000000 | D6: =B6*(($E$6/$B$6)^(2/3)) | E6: =chi_so_tai_chinh!B41
A7: LICĐKKS | B7: =B6*0.35/100 | C7: =C6*0.35/100 | D7: =D6*0.35/100 | E7: =E6*0.35/100
A8: BV | B8: =B6-B7 | C8: =C6-C7 | D8: =D6-D7 | E8: =E6-E7
A9: BVPS | B9: =B8/B2 | C9: =C8/C2 | D9: =D8/D2 | E9: =E8/E2
A10: PB | B10: =$E$3/B9 | C10: =$E$3/C9 | D10: =$E$3/D9 | E10: =$E$3/E9
