Workbook

Sheet balance_sheet
A1: item | B1: 2018 | C1: 2019 | D1: 2020 | E1: 2021 | F1: 2022 | G1: 2023 | H1: 2024 | I1: 2025
A2: TÀI SẢN NGẮN HẠN | B2: 23371994756394 | C2: 35011896908246 | D2: 37317233970267 | E2: 51955257770657 | F2: 44577607228189 | G2: 51950337976047 | H2: 65836422620040 | I2: 77201650782966
A3: Tiền và tương đương tiền | B3: 3749550258212 | C3: 3115236816468 | D3: 7347857397925 | E3: 4142015762555 | F3: 5061020547422 | G3: 5365704857172 | H3: 4897331540730 | I3: 4999925717187
A4: Tiền | B4: 3363717276954 | C4: 2024347938868 | D4: 2243274466174 | E4: 2606672264502 | F4: 3846020547422 | G4: 4795636583222 | H4: 4697331540730 | I4: 4960375717187
A5: Các khoản tương đương tiền | B5: 385832981258 | C5: 1090888877600 | D5: 5104582931751 | E5: 1535343498053 | F5: 1215000000000 | G5: 570068273950 | H5: 200000000000 | I5: 39550000000
A6: Đầu tư ngắn hạn | B6: 0 | C6: 0 | D6: 0 | E6: 0 | F6: 0 | G6: 0 | H6: 0 | I6: 0
A7: Đầu tư ngắn hạn | F7: 0 | G7: 0 | H7: 0 | I7: 0
A8: Dự phòng giảm giá | B8: 0 | C8: 0 | D8: 0 | E8: 0 | F8: 0 | G8: 0 | H8: 0 | I8: 0
A9: Các khoản phải thu | B9: 1542529736073 | C9: 1815085561979 | D9: 1595251018496 | E9: 3162121971586 | F9: 3000817466182 | G9: 5158853337785 | H9: 8825896224771 | I9: 10182835978469
A10: Phải thu khách hàng | B10: 369573657457 | C10: 262268362817 | D10: 196394545434 | E10: 384236578232 | F10: 178061365251 | G10: 308474343927 | H10: 241405396887 | I10: 253358838280
A11: Trả trước người bán | B11: 21007291749 | C11: 195016846986 | D11: 287913331552 | E11: 390738782756 | F11: 403669438496 | G11: 95981093251 | H11: 115888383111 | I11: 141627187798
A12: Phải thu nội bộ | B12: 0 | C12: 0 | D12: 0 | E12: 0 | F12: 0 | G12: 0 | H12: 0 | I12: 0
A13: Phải thu hợp đồng xây dựng đang thực hiện | B13: 0 | C13: 0 | D13: 0 | E13: 0 | F13: 0 | G13: 0 | H13: 0 | I13: 0
A14: Phải thu khác | B14: 1151948786867 | C14: 1357800352176 | D14: 1030943141510 | E14: 1425228912960 | F14: 2402168964797 | G14: 2668480202969 | H14: 2430887848672 | I14: 2877349952391
A15: Dự phòng nợ khó đòi | B15: 0 | C15: 0 | D15: 0 | E15: 0 | F15: 0 | G15: 0 | H15: 0 | I15: 0
A16: Hàng tồn kho, ròng | B16: 17446005298981 | C16: 25745428436580 | D16: 19422177452674 | E16: 29167232293922 | F16: 25696077735282 | G16: 21824235626176 | H16: 22244676326705 | I16: 27266851974258
A17: Hàng tồn kho | B17: 17821137643753 | C17: 26195934673884 | D17: 19926363502365 | E17: 29850068817719 | F17: 26058131396686 | G17: 22028684523096 | H17: 22667774012643 | I17: 27876446129267
A18: Dự phòng giảm giá hàng tồn kho | B18: -375132344772 | C18: -450506237304 | D18: -504186049691 | E18: -682836523797 | F18: -362053661404 | G18: -204448896920 | H18: -423097685938 | I18: -609594155009
A19: Tài sản lưu động khác | B19: 0 | C19: 0 | D19: 0 | E19: 0 | F19: 0 | G19: 0 | H19: 0 | I19: 0
... A22: Phải thu thuế khác | B22: 1842948927 | C22: 2890365291 | D22: 4751687467 | E22: 41984411029 | F22: 28637906590 | G22: 23473930964 | H22: 32630294575 | I22: 44293494912
A23: Tài sản lưu động khác | F23: 0 | G23: 0 | H23: 0 | I23: 0
A24: TÀI SẢN DÀI HẠN | B24: 4750536730462 | C24: 6696198636637 | D24: 8713645982187 | E24: 11016147044285 | F24: 11256488385860 | G24: 8160899236677 | H24: 4601353101564 | I24: 6743968829068
A25: Phải thu dài hạn | B25: 313775645332 | C25: 374563598474 | D25: 439493257757 | E25: 482389179464 | F25: 503486573563 | G25: 457569986630 | H25: 389707802472 | I25: 403823784845
A26: Phải thu khách hàng dài hạn | B26: 0 | C26: 0 | D26: 0 | E26: 0 | F26: 0 | G26: 0 | H26: 0 | I26: 0
A27: Phải thu nội bộ dài hạn | B27: 0 | C27: 0 | D27: 0 | E27: 0 | F27: 0 | G27: 0 | H27: 0 | I27: 0
A28: Phải thu dài hạn khác | B28: 313775645332 | C28: 374563598474 | D28: 439493257757 | E28: 482389179464 | F28: 493741850234 | G28: 448325013301 | H28: 389707802472 | I28: 403823784845
A29: Dự phòng phải thu dài hạn | B29: 0 | C29: 0 | D29: 0 | E29: 0 | F29: 0 | G29: 0 | H29: 0 | I29: 0
A30: Tài sản cố định | B30: 3333147659602 | C30: 5403776988921 | D30: 7294961666136 | E30: 9647168873232 | F30: 9727502911440 | G30: 6500135608914 | H30: 3586628664045 | I30: 2598189217583
A31: GTCL TSCĐ hữu hình | B31: 3304923529470 | C31: 5375279172974 | D31: 7267319287908 | E31: 9566954933220 | F31: 9653330005976 | G31: 6431315373113 | H31: 3523161097906 | I31: 2540074321107
A32: Nguyên giá TSCĐ hữu hình | B32: 5788326331676 | C32: 9148455989525 | D32: 12963311412901 | E32: 17987087849355 | F32: 20841513609195 | G32: 20139282722977 | H32: 19174626383752 | I32: 19478200234864
A33: Khấu hao lũy kế TSCĐ hữu hình | B33: -2483402802206 | C33: -3773176816551 | D33: -5695992124993 | E33: -8420132916135 | F33: -11188183603219 | G33: -13707967349864 | H33: -15651465285846 | I33: -16938125913757
A34: GTCL tài sản thuê tài chính | B34: 0 | C34: 0 | D34: 0 | E34: 0 | F34: 0 | G34: 0 | H34: 0 | I34: 0
A35: Nguyên giá tài sản thuê tài chính | B35: 0 | C35: 0 | D35: 0 | E35: 0 | F35: 0 | G35: 0 | H35: 0 | I35: 0
... A72: Vay dài hạn | B72: 1208167140389 | C72: 1122136666657 | D72: 1126676666653 | E72: 0 | F72: 5901250000000 | G72: 5985250000000 | H72: 0 | I72: 0
A73: Thuế thu nhập hoãn lại | F73: 0 | G73: 1168691414 | H73: 0 | I73: 0
A74: Dự phòng trợ cấp thôi việc | B74: 0 | C74: 0 | D74: 0 | E74: 0 | F74: 0 | G74: 0 | H74: 0 | I74: 0
A75: Dự phòng các khoản nợ dài hạn | B75: 0 | C75: 0 | D75: 0 | E75: 0 | F75: 0 | G75: 0 | H75: 0 | I75: 0
A76: Doanh thu chưa thực hiện | B76: 0 | C76: 0 | D76: 0 | E76: 0 | F76: 0 | G76: 0 | H76: 0 | I76: 0
A77: Quỹ phát triển khoa học công nghệ | B77: 0 | C77: 0 | D77: 0 | E77: 0 | F77: 0 | G77: 0 | H77: 0 | I77: 0
A78: Vốn chủ sở hữu | B78: 8983035331342 | C78: 12143592194353 | D78: 15481689846432 | E78: 20378245999846 | F78: 23932581517576 | G78: 23359557967338 | H78: 28121576823855 | I78: 33176117374577
A79: Vốn và các quỹ | B79: 8983035331342 | C79: 12143592194353 | D79: 15481689846432 | E79: 20378245999846 | F79: 23932581517576 | G79: 23359557967338 | H79: 28121576823855 | I79: 33176117374577
A80: Vốn góp | B80: 4434961780000 | C80: 4435461780000 | D80: 4532099870000 | E80: 7130654950000 | F80: 14638792800000 | G80: 14633767160000 | H80: 14622441770000 | I80: 14696931770000
A81: Thặng dư vốn cổ phần | B81: 551451995486 | C81: 555206995486 | D81: 558110430986 | E81: 558110430986 | F81: 558110430986 | G81: 558110430986 | H81: 558110430986 | I81: -152995820060
A82: Vốn khác | B82: 1130494084 | C82: 1130494084 | D82: 0 | E82: 0 | F82: 0 | G82: 0 | H82: 0 | I82: 0
A83: Cổ phiếu quỹ | B83: -808864500 | C83: -5658924500 | D83: -6040930000 | E83: -2320000000 | F83: -5025640000 | G83: -9783280000 | H83: -7599680000 | I83: -12364140000
A84: Chênh lệch đánh giá lại tài sản | B84: 0 | C84: 0 | D84: 0 | E84: 0 | F84: 0 | G84: 0 | H84: 0 | I84: 0
A85: Chênh lệch tỷ giá | B85: 446572898 | C85: -28377933 | D85: -1443756225 | E85: 5388425299 | F85: 2261603090 | G85: 3739030306 | H85: 2458384629 | I85: 0
... A105: Chi phí sản xuất, kinh doanh dở dang dài hạn | B105: 0 | C105: 0 | D105: 0 | E105: 0 | F105: 0 | G105: 0 | H105: 0 | I105: 0
A106: Đầu tư nắm giữ đến ngày đáo hạn | F106: 50000000000 | G106: 460000000000 | H106: 0 | I106: 2765156500000
A107: Thiết bị, vật tư, phụ tùng thay thế dài hạn | B107: 0 | C107: 0 | D107: 0 | E107: 0 | F107: 0 | G107: 0 | H107: 0 | I107: 0
A108: Doanh thu chưa thực hiện ngắn hạn | B108: 0 | C108: 333585179 | D108: 308408475 | E108: 0 | F108: 386943692 | G108: 3405793231 | H108: 51807612125 | I108: 536936718444
A109: Quỹ bình ổn giá | B109: 0 | C109: 0 | D109: 0 | E109: 0 | F109: 0 | G109: 0 | H109: 0 | I109: 0
A110: Giao dịch mua bán lại trái phiếu chính phủ | B110: 0 | C110: 0 | D110: 0 | E110: 0 | F110: 0 | G110: 0 | H110: 0 | I110: 0
A111: Người mua trả tiền trước dài hạn | B111: 0 | C111: 0 | D111: 0 | E111: 0 | F111: 0 | G111: 0 | H111: 0 | I111: 0
A112: Chi phí phải trả dài hạn | B112: 0 | C112: 0 | D112: 0 | E112: 0 | F112: 0 | G112: 0 | H112: 0 | I112: 0
A113: Phải trả nội bộ về vốn kinh doanh | B113: 0 | C113: 0 | D113: 0 | E113: 0 | F113: 0 | G113: 0 | H113: 0 | I113: 0
A114: Trái phiếu chuyển đổi | B114: 0 | C114: 0 | D114: 0 | E114: 0 | F114: 0 | G114: 0 | H114: 0 | I114: 0
A115: Cổ phiếu ưu đãi | F115: 0 | G115: 0 | H115: 0 | I115: 0
A116: Cổ phiếu phổ thông | B116: 4434961780000 | C116: 4435461780000 | D116: 4532099870000 | E116: 7130654950000 | F116: 14638792800000 | G116: 14633767160000 | H116: 14622441770000 | I116: 14696931770000
A117: Quyền chọn chuyển đổi trái phiếu | B117: 0 | C117: 0 | D117: 0 | E117: 0 | F117: 0 | G117: 0 | H117: 0 | I117: 0
A118: LNST chưa phân phối lũy kế đến cuối kỳ trước | B118: 1138290716709 | C118: 3315424614555 | D118: 6470785320602 | E118: 7775704885845 | F118: 4624171199065 | G118: 7992654202870 | H118: 8860276825181 | I118: 11034463805990
A119: LNST chưa phân phối kỳ này | B119: 2851313193346 | C119: 3834269547047 | D119: 3918898277243 | E119: 4898869278220 | F119: 4099763027305 | G119: 167669392704 | H119: 3721868441661 | I119: 7033730770169
A120: Xây dựng cơ bản đang dở dang | B120: 256831997207 | C120: 87430438310 | D120: 132620362470 | E120: 79697939172 | F120: 123873978878 | G120: 4493856934 | H120: 24526423340 | I120: 90899467872
A121: Lợi thế thương mại | B121: 552526849066 | C121: 491134976947 | D121: 429743104828 | E121: 368351232709 | F121: 306959360590 | G121: 245567488471 | H121: 0 | I121: 0
A122: Lợi ích cổ đông không kiểm soát | B122: 6249443319 | C122: 7786065614 | D122: 9280633826 | E122: 11838029496 | F122: 14508097130 | G122: 13401030472 | H122: 364020651398 | I122: 576350988478
A123: Nguồn kinh phí đã hình thành TSCĐ | B123: 0 | C123: 0 | D123: 0 | E123: 0 | F123: 0 | G123: 0 | H123: 0 | I123: 0

Sheet income_statement
A1: item | B1: 2018 | C1: 2019 | D1: 2020 | E1: 2021 | F1: 2022 | G1: 2023 | H1: 2024 | I1: 2025
A2: Doanh thu bán hàng và cung cấp dịch vụ | B2: 87738378978636 | C2: 103485046672447 | D2: 109801253690656 | E2: 124141525689948 | F2: 134722248887557 | G2: 119234184825086 | H2: 135225101298992 | I2: 156836115054975
A3: Các khoản giảm trừ doanh thu | B3: -1222091976137 | C3: -1310802695724 | D3: -1255234025244 | E3: -1183419586774 | F3: -1317471297033 | G3: -954396369644 | H3: -883948450190 | I3: -907969435608
A4: Doanh thu thuần | B4: 86516287002499 | C4: 102174243976723 | D4: 108546019665412 | E4: 122958106103174 | F4: 133404777590524 | G4: 118279788455442 | H4: 134341152848802 | I4: 155928145619367
A5: Giá vốn hàng bán | B5: -71224159239435 | C5: -82686444673012 | D5: -84591522392949 | E5: -95325974107640 | F5: -102542735094343 | G5: -95759175291712 | H5: -106841942771781 | I5: -124926268219546
A6: Lợi nhuận gộp | B6: 15292127763064 | C6: 19487799303711 | D6: 23954497272463 | E6: 27632131995534 | F6: 30862042496181 | G6: 22520613163730 | H6: 27499210077021 | I6: 31001877399821
A7: Doanh thu hoạt động tài chính | B7: 342083875229 | C7: 631177854351 | D7: 794121782667 | E7: 1287956026163 | F7: 1313137304323 | G7: 2166963715091 | H7: 2376502605263 | I7: 3107348733939
A8: Chi phí tài chính | B8: -436573150236 | C8: -569754844844 | D8: -594151513751 | E8: -714707225745 | F8: -1382620454532 | G8: -1556146106982 | H8: -1188465609510 | I8: -1542518673463
A9: Chi phí lãi vay | B9: -436416577674 | C9: -568136717134 | D9: -594003821021 | E9: -674427746189 | F9: -1362143909103 | G9: -1447718354797 | H9: -1137236129748 | I9: -1470675593604
A10: Chi phí bán hàng | B10: -9659741188756 | C10: -12437282718212 | D10: -15333798830787 | E10: -17914173302345 | F10: -22336838067678 | G10: -20916710755306 | H10: -19849837609882 | I10: -19330903536858
A11: Chi phí quản lý doanh nghiệp | B11: -1761613900080 | C11: -2073782880058 | D11: -3404431838167 | E11: -3823390074765 | F11: -1881027579714 | G11: -1167651662536 | H11: -3565767583102 | I11: -4596074513172
A12: Lãi/(lỗ) từ hoạt động kinh doanh | B12: 3774182412336 | C12: 5034683431577 | D12: 5412529932954 | E12: 6465606918356 | F12: 6574693698580 | G12: 1047068353997 | H12: 5227045424891 | I12: 8664080489454
A13: Thu nhập khác | B13: 33233337382 | C13: 41557041541 | D13: 43512695471 | E13: 54872797433 | F13: 61606712681 | G13: 36883419051 | H13: 25743895664 | I13: 52777770887
... A26: Lãi/(lỗ) từ công ty liên doanh (từ năm 2015) | B26: -2100986885 | C26: -3473283371 | D26: -3706939471 | E26: -2210500486 | F26: 0 | G26: 0 | H26: -44596454899 | I26: 24351079187

Sheet cash_flow
A1: item | B1: 2018 | C1: 2019 | D1: 2020 | E1: 2021 | F1: 2022 | G1: 2023 | H1: 2024 | I1: 2025
A2: Lợi nhuận/(lỗ) trước thuế | B2: 3786318568918 | C2: 5053447204696 | D2: 5409735407353 | E2: 6471583750543 | F2: 6056355373558 | G2: 689692367896 | H2: 4825763013078 | I2: 8633067583426
A3: Khấu hao TSCĐ và BĐSĐT | B3: 1222868683717 | C3: 1442826938954 | D3: 2195583071035 | E3: 2920713608410 | F3: 3540324726294 | G3: 3351314267883 | H3: 2913419081483 | I3: 1890882108632
A4: Chi phí dự phòng | B4: 126083626828 | C4: 90495782206 | D4: 58366659386 | E4: 179550717177 | F4: -321799366884 | G4: -165930068132 | H4: 220952651591 | I4: 205754863290
A5: Lãi/lỗ chênh lệch tỷ giá hối đoái do đánh giá lại các khoản mục tiền tệ có gốc ngoại tệ | B5: -107059306 | C5: -27160364 | D5: -36874578 | E5: -146653994 | F5: 284374414 | G5: 83631272202 | H5: 25689580954 | I5: 48281410640
A6: Lãi/(lỗ) từ thanh lý tài sản cố định | B6: 0 | C6: 0 | D6: 0 | E6: 0 | F6: 0 | G6: 0 | H6: 0 | I6: 0
A7: (Lãi)/lỗ từ hoạt động đầu tư | B7: -84857279584 | C7: -341194613832 | D7: -557627148536 | E7: -959323580633 | F7: -348599792355 | G7: -1509203341265 | H7: -1729164103487 | I7: -2908766491708
A8: Chi phí lãi vay | B8: 436416577674 | C8: 568136717134 | D8: 594003821021 | E8: 674427746189 | F8: 1362143909103 | G8: 1447718354797 | H8: 1137236129748 | I8: 1470675593604
A9: Thu lãi và cổ tức | B9: 0 | C9: 0 | D9: 0 | E9: 0 | F9: 0 | G9: 0 | H9: 0 | I9: 0
A10: Lợi nhuận/(lỗ) từ hoạt động kinh doanh trước những thay đổi vốn lưu động | B10: 5486723118247 | C10: 6813684868794 | D10: 7700024935681 | E10: 9286805587692 | F10: 10288709224130 | G10: 3897222853381 | H10: 7393896353367 | I10: 9339895067884
A11: (Tăng)/giảm các khoản phải thu | B11: 1246646823981 | C11: -675979882201 | D11: 850493238036 | E11: -827596105467 | F11: -588827639446 | G11: 672440536688 | H11: 151205190961 | I11: -308618709954
A12: (Tăng)/giảm hàng tồn kho | B12: -4672944194460 | C12: -8374797030131 | D12: 6269571171519 | E12: -9923705315353 | F12: 3791937421033 | G12: 4169031757473 | H12: -636927914305 | I12: -5207942331422
A13: Tăng/(giảm) các khoản phải trả | B13: 1331042865781 | C13: 2823942311184 | D13: -1894206905085 | E13: 3781614904801 | F13: -2286756979213 | G13: -3136706601092 | H13: 3581806724649 | I13: 5339106069277
... A42: (Tăng)/giảm chứng khoán kinh doanh | B42: 0 | C42: 0 | D42: 0 | E42: 0 | F42: 0 | G42: 0 | H42: 0 | I42: 0

Sheet chi_so_tai_chinh
A1: Chỉ tiêu | B1: =balance_sheet!B1 | C1: =balance_sheet!C1 | D1: =balance_sheet!D1 | E1: =balance_sheet!E1 | F1: =balance_sheet!F1 | G1: =balance_sheet!G1 | H1: =balance_sheet!H1 | I1: =balance_sheet!I1 | J1: 2026
A2: ROE (LNST CĐ Cty mẹ / VCSH bình quân) | B2: n/a | C2: =IFERROR(C$51/((C$39+B$39)/2),"n/a") | D2: =IFERROR(D$51/((D$39+C$39)/2),"n/a") | E2: =IFERROR(E$51/((E$39+D$39)/2),"n/a") | F2: =IFERROR(F$51/((F$39+E$39)/2),"n/a") | G2: =IFERROR(G$51/((G$39+F$39)/2),"n/a") | H2: =IFERROR(H$51/((H$39+G$39)/2),"n/a") | I2: =IFERROR(I$51/((I$39+H$39)/2),"n/a") | J2: =IFERROR(J$51/((J$39+I$39)/2),"n/a")
A3: ROA (LNST / Tổng tài sản bình quân) | B3: n/a | C3: =IFERROR(C$50/((C$31+B$31)/2),"n/a") | D3: =IFERROR(D$50/((D$31+C$31)/2),"n/a") | E3: =IFERROR(E$50/((E$31+D$31)/2),"n/a") | F3: =IFERROR(F$50/((F$31+E$31)/2),"n/a") | G3: =IFERROR(G$50/((G$31+F$31)/2),"n/a") | H3: =IFERROR(H$50/((H$31+G$31)/2),"n/a") | I3: =IFERROR(I$50/((I$31+H$31)/2),"n/a")
A4: Tăng trưởng LN Cổ đông Cty mẹ | B4: n/a | C4: =IFERROR((C$51-B$51)/ABS(B$51),"n/a") | D4: =IFERROR((D$51-C$51)/ABS(C$51),"n/a") | E4: =IFERROR((E$51-D$51)/ABS(D$51),"n/a") | F4: =IFERROR((F$51-E$51)/ABS(E$51),"n/a") | G4: =IFERROR((G$51-F$51)/ABS(F$51),"n/a") | H4: =IFERROR((H$51-G$51)/ABS(G$51),"n/a") | I4: =IFERROR((I$51-H$51)/ABS(H$51),"n/a") | J4: =IFERROR((J$51-I$51)/ABS(I$51),"n/a")
A5: Tăng trưởng Doanh thu thuần | B5: n/a | C5: =IFERROR((C$43-B$43)/ABS(B$43),"n/a") | D5: =IFERROR((D$43-C$43)/ABS(C$43),"n/a") | E5: =IFERROR((E$43-D$43)/ABS(D$43),"n/a") | F5: =IFERROR((F$43-E$43)/ABS(E$43),"n/a") | G5: =IFERROR((G$43-F$43)/ABS(F$43),"n/a") | H5: =IFERROR((H$43-G$43)/ABS(G$43),"n/a") | I5: =IFERROR((I$43-H$43)/ABS(H$43),"n/a") | J5: =IFERROR((J$43-I$43)/ABS(I$43),"n/a")
A6: Biên lợi nhuận gộp | B6: =IFERROR(B$45/B$43,"n/a") | C6: =IFERROR(C$45/C$43,"n/a") | D6: =IFERROR(D$45/D$43,"n/a") | E6: =IFERROR(E$45/E$43,"n/a") | F6: =IFERROR(F$45/F$43,"n/a") | G6: =IFERROR(G$45/G$43,"n/a") | H6: =IFERROR(H$45/H$43,"n/a") | I6: =IFERROR(I$45/I$43,"n/a")
A7: Biên lợi nhuận ròng | B7: =IFERROR(B$51/B$43,"n/a") | C7: =IFERROR(C$51/C$43,"n/a") | D7: =IFERROR(D$51/D$43,"n/a") | E7: =IFERROR(E$51/E$43,"n/a") | F7: =IFERROR(F$51/F$43,"n/a") | G7: =IFERROR(G$51/G$43,"n/a") | H7: =IFERROR(H$51/H$43,"n/a") | I7: =IFERROR(I$51/I$43,"n/a") | J7: =IFERROR(J$51/J$43,"n/a")
A8: D/E (Nợ vay / Vốn chủ sở hữu) | B8: =IFERROR((B$34+B$36)/B$39,"n/a") | C8: =IFERROR((C$34+C$36)/C$39,"n/a") | D8: =IFERROR((D$34+D$36)/D$39,"n/a") | E8: =IFERROR((E$34+E$36)/E$39,"n/a") | F8: =IFERROR((F$34+F$36)/F$39,"n/a") | G8: =IFERROR((G$34+G$36)/G$39,"n/a") | H8: =IFERROR((H$34+H$36)/H$39,"n/a") | I8: =IFERROR((I$34+I$36)/I$39,"n/a")
A9: - Nợ vay dài hạn/Vốn chủ sở hữu | B9: =IFERROR(B$36/B$39,"n/a") | C9: =IFERROR(C$36/C$39,"n/a") | D9: =IFERROR(D$36/D$39,"n/a") | E9: =IFERROR(E$36/E$39,"n/a") | F9: =IFERROR(F$36/F$39,"n/a") | G9: =IFERROR(G$36/G$39,"n/a") | H9: =IFERROR(H$36/H$39,"n/a") | I9: =IFERROR(I$36/I$39,"n/a")
A10: - Nợ vay ngắn hạn/Vốn chủ sở hữu | B10: =IFERROR(B$34/B$39,"n/a") | C10: =IFERROR(C$34/C$39,"n/a") | D10: =IFERROR(D$34/D$39,"n/a") | E10: =IFERROR(E$34/E$39,"n/a") | F10: =IFERROR(F$34/F$39,"n/a") | G10: =IFERROR(G$34/G$39,"n/a") | H10: =IFERROR(H$34/H$39,"n/a") | I10: =IFERROR(I$34/I$39,"n/a")
A11: Nợ phải trả/Vốn chủ sở hữu | B11: =IFERROR(B$38/B$39,"n/a") | C11: =IFERROR(C$38/C$39,"n/a") | D11: =IFERROR(D$38/D$39,"n/a") | E11: =IFERROR(E$38/E$39,"n/a") | F11: =IFERROR(F$38/F$39,"n/a") | G11: =IFERROR(G$38/G$39,"n/a") | H11: =IFERROR(H$38/H$39,"n/a") | I11: =IFERROR(I$38/I$39,"n/a")
A12: - Nợ dài hạn/Vốn chủ sở hữu | B12: =IFERROR(B$37/B$39,"n/a") | C12: =IFERROR(C$37/C$39,"n/a") | D12: =IFERROR(D$37/D$39,"n/a") | E12: =IFERROR(E$37/E$39,"n/a") | F12: =IFERROR(F$37/F$39,"n/a") | G12: =IFERROR(G$37/G$39,"n/a") | H12: =IFERROR(H$37/H$39,"n/a") | I12: =IFERROR(I$37/I$39,"n/a")
A13: - Nợ ngắn hạn/Vốn chủ sở hữu | B13: =IFERROR(B$35/B$39,"n/a") | C13: =IFERROR(C$35/C$39,"n/a") | D13: =IFERROR(D$35/D$39,"n/a") | E13: =IFERROR(E$35/E$39,"n/a") | F13: =IFERROR(F$35/F$39,"n/a") | G13: =IFERROR(G$35/G$39,"n/a") | H13: =IFERROR(H$35/H$39,"n/a") | I13: =IFERROR(I$35/I$39,"n/a")
A14: Chi phí bán hàng, quản lý/LN gộp | B14: =IFERROR((ABS(B$46)+ABS(B$47))/B$45,"n/a") | C14: =IFERROR((ABS(C$46)+ABS(C$47))/C$45,"n/a") | D14: =IFERROR((ABS(D$46)+ABS(D$47))/D$45,"n/a") | E14: =IFERROR((ABS(E$46)+ABS(E$47))/E$45,"n/a") | F14: =IFERROR((ABS(F$46)+ABS(F$47))/F$45,"n/a") | G14: =IFERROR((ABS(G$46)+ABS(G$47))/G$45,"n/a") | H14: =IFERROR((ABS(H$46)+ABS(H$47))/H$45,"n/a") | I14: =IFERROR((ABS(I$46)+ABS(I$47))/I$45,"n/a")
A15: Chi phí lãi vay/LN từ hoạt động kinh doanh | B15: =IFERROR(ABS(B$49)/B$48,"n/a") | C15: =IFERROR(ABS(C$49)/C$48,"n/a") | D15: =IFERROR(ABS(D$49)/D$48,"n/a") | E15: =IFERROR(ABS(E$49)/E$48,"n/a") | F15: =IFERROR(ABS(F$49)/F$48,"n/a") | G15: =IFERROR(ABS(G$49)/G$48,"n/a") | H15: =IFERROR(ABS(H$49)/H$48,"n/a") | I15: =IFERROR(ABS(I$49)/I$48,"n/a")
A16: Số ngày phải trả (DPO) | B16: n/a | C16: =IFERROR(((C$33+B$33)/2)/ABS(C$44)*365,"n/a") | D16: =IFERROR(((D$33+C$33)/2)/ABS(D$44)*365,"n/a") | E16: =IFERROR(((E$33+D$33)/2)/ABS(E$44)*365,"n/a") | F16: =IFERROR(((F$33+E$33)/2)/ABS(F$44)*365,"n/a") | G16: =IFERROR(((G$33+F$33)/2)/ABS(G$44)*365,"n/a") | H16: =IFERROR(((H$33+G$33)/2)/ABS(H$44)*365,"n/a") | I16: =IFERROR(((I$33+H$33)/2)/ABS(I$44)*365,"n/a")
A17: Số ngày phải thu (DSO) | B17: n/a | C17: =IFERROR(((C$27+B$27)/2)/C$43*365,"n/a") | D17: =IFERROR(((D$27+C$27)/2)/D$43*365,"n/a") | E17: =IFERROR(((E$27+D$27)/2)/E$43*365,"n/a") | F17: =IFERROR(((F$27+E$27)/2)/F$43*365,"n/a") | G17: =IFERROR(((G$27+F$27)/2)/G$43*365,"n/a") | H17: =IFERROR(((H$27+G$27)/2)/H$43*365,"n/a") | I17: =IFERROR(((I$27+H$27)/2)/I$43*365,"n/a")
A18: Số ngày tồn kho (DIO) | B18: n/a | C18: =IFERROR(((C$28+B$28)/2)/ABS(C$44)*365,"n/a") | D18: =IFERROR(((D$28+C$28)/2)/ABS(D$44)*365,"n/a") | E18: =IFERROR(((E$28+D$28)/2)/ABS(E$44)*365,"n/a") | F18: =IFERROR(((F$28+E$28)/2)/ABS(F$44)*365,"n/a") | G18: =IFERROR(((G$28+F$28)/2)/ABS(G$44)*365,"n/a") | H18: =IFERROR(((H$28+G$28)/2)/ABS(H$44)*365,"n/a") | I18: =IFERROR(((I$28+H$28)/2)/ABS(I$44)*365,"n/a")
A19: Tiền và tương đương tiền/Tài sản | B19: =IFERROR(B$26/B$31,"n/a") | C19: =IFERROR(C$26/C$31,"n/a") | D19: =IFERROR(D$26/D$31,"n/a") | E19: =IFERROR(E$26/E$31,"n/a") | F19: =IFERROR(F$26/F$31,"n/a") | G19: =IFERROR(G$26/G$31,"n/a") | H19: =IFERROR(H$26/H$31,"n/a") | I19: =IFERROR(I$26/I$31,"n/a")
A20: Hàng tồn kho/Tài sản | B20: =IFERROR(B$28/B$31,"n/a") | C20: =IFERROR(C$28/C$31,"n/a") | D20: =IFERROR(D$28/D$31,"n/a") | E20: =IFERROR(E$28/E$31,"n/a") | F20: =IFERROR(F$28/F$31,"n/a") | G20: =IFERROR(G$28/G$31,"n/a") | H20: =IFERROR(H$28/H$31,"n/a") | I20: =IFERROR(I$28/I$31,"n/a")
A22: II. DỮ LIỆU TRÍCH XUẤT (tự động dò theo tên khoản mục)
A23: Khoản mục | B23: =balance_sheet!B1 | C23: =balance_sheet!C1 | D23: =balance_sheet!D1 | E23: =balance_sheet!E1 | F23: =balance_sheet!F1 | G23: =balance_sheet!G1 | H23: =balance_sheet!H1 | I23: =balance_sheet!I1
A24: CĐKT
A25: Tài sản
A26: Tiền và tương đương tiền | B26: =IFERROR(INDEX(balance_sheet!$B:$XFD,MATCH("Tiền và tương đương tiền",balance_sheet!$A:$A,0),MATCH(B$23,balance_sheet!$B$1:$XFD$1,0)),"") | C26: =IFERROR(INDEX(balance_sheet!$B:$XFD,MATCH("Tiền và tương đương tiền",balance_sheet!$A:$A,0),MATCH(C$23,balance_sheet!$B$1:$XFD$1,0)),"") | D26: =IFERROR(INDEX(balance_sheet!$B:$XFD,MATCH("Tiền và tương đương tiền",balance_sheet!$A:$A,0),MATCH(D$23,balance_sheet!$B$1:$XFD$1,0)),"") | E26: =IFERROR(INDEX(balance_sheet!$B:$XFD,MATCH("Tiền và tương đương tiền",balance_sheet!$A:$A,0),MATCH(E$23,balance_sheet!$B$1:$XFD$1,0)),"") | F26: =IFERROR(INDEX(balance_sheet!$B:$XFD,MATCH("Tiền và tương đương tiền",balance_sheet!$A:$A,0),MATCH(F$23,balance_sheet!$B$1:$XFD$1,0)),"") | G26: =IFERROR(INDEX(balance_sheet!$B:$XFD,MATCH("Tiền và tương đương tiền",balance_sheet!$A:$A,0),MATCH(G$23,balance_sheet!$B$1:$XFD$1,0)),"") | H26: =IFERROR(INDEX(balance_sheet!$B:$XFD,MATCH("Tiền và tương đương tiền",balance_sheet!$A:$A,0),MATCH(H$23,balance_sheet!$B$1:$XFD$1,0)),"") | I26: =IFERROR(INDEX(balance_sheet!$B:$XFD,MATCH("Tiền và tương đương tiền",balance_sheet!$A:$A,0),MATCH(I$23,balance_sheet!$B$1:$XFD$1,0)),"")
A27: Phải thu khách hàng | B27: =IFERROR(INDEX(balance_sheet!$B:$XFD,MATCH("Phải thu khách hàng",balance_sheet!$A:$A,0),MATCH(B$23,balance_sheet!$B$1:$XFD$1,0)),"") | C27: =IFERROR(INDEX(balance_sheet!$B:$XFD,MATCH("Phải thu khách hàng",balance_sheet!$A:$A,0),MATCH(C$23,balance_sheet!$B$1:$XFD$1,0)),"") | D27: =IFERROR(INDEX(balance_sheet!$B:$XFD,MATCH("Phải thu khách hàng",balance_sheet!$A:$A,0),MATCH(D$23,balance_sheet!$B$1:$XFD$1,0)),"") | E27: =IFERROR(INDEX(balance_sheet!$B:$XFD,MATCH("Phải thu khách hàng",balance_sheet!$A:$A,0),MATCH(E$23,balance_sheet!$B$1:$XFD$1,0)),"") | F27: =IFERROR(INDEX(balance_sheet!$B:$XFD,MATCH("Phải thu khách hàng",balance_sheet!$A:$A,0),MATCH(F$23,balance_sheet!$B$1:$XFD$1,0)),"") | G27: =IFERROR(INDEX(balance_sheet!$B:$XFD,MATCH("Phải thu khách hàng",balance_sheet!$A:$A,0),MATCH(G$23,balance_sheet!$B$1:$XFD$1,0)),"") | H27: =IFERROR(INDEX(balance_sheet!$B:$XFD,MATCH("Phải thu khách hàng",balance_sheet!$A:$A,0),MATCH(H$23,balance_sheet!$B$1:$XFD$1,0)),"") | I27: =IFERROR(INDEX(balance_sheet!$B:$XFD,MATCH("Phải thu khách hàng",balance_sheet!$A:$A,0),MATCH(I$23,balance_sheet!$B$1:$XFD$1,0)),"")
A28: Hàng tồn kho, ròng | B28: =IFERROR(INDEX(balance_sheet!$B:$XFD,MATCH("Hàng tồn kho, ròng",balance_sheet!$A:$A,0),MATCH(B$23,balance_sheet!$B$1:$XFD$1,0)),"") | C28: =IFERROR(INDEX(balance_sheet!$B:$XFD,MATCH("Hàng tồn kho, ròng",balance_sheet!$A:$A,0),MATCH(C$23,balance_sheet!$B$1:$XFD$1,0)),"") | D28: =IFERROR(INDEX(balance_sheet!$B:$XFD,MATCH("Hàng tồn kho, ròng",balance_sheet!$A:$A,0),MATCH(D$23,balance_sheet!$B$1:$XFD$1,0)),"") | E28: =IFERROR(INDEX(balance_sheet!$B:$XFD,MATCH("Hàng tồn kho, ròng",balance_sheet!$A:$A,0),MATCH(E$23,balance_sheet!$B$1:$XFD$1,0)),"") | F28: =IFERROR(INDEX(balance_sheet!$B:$XFD,MATCH("Hàng tồn kho, ròng",balance_sheet!$A:$A,0),MATCH(F$23,balance_sheet!$B$1:$XFD$1,0)),"") | G28: =IFERROR(INDEX(balance_sheet!$B:$XFD,MATCH("Hàng tồn kho, ròng",balance_sheet!$A:$A,0),MATCH(G$23,balance_sheet!$B$1:$XFD$1,0)),"") | H28: =IFERROR(INDEX(balance_sheet!$B:$XFD,MATCH("Hàng tồn kho, ròng",balance_sheet!$A:$A,0),MATCH(H$23,balance_sheet!$B$1:$XFD$1,0)),"") | I28: =IFERROR(INDEX(balance_sheet!$B:$XFD,MATCH("Hàng tồn kho, ròng",balance_sheet!$A:$A,0),MATCH(I$23,balance_sheet!$B$1:$XFD$1,0)),"")
A29: TÀI SẢN NGẮN HẠN | B29: =IFERROR(INDEX(balance_sheet!$B:$XFD,MATCH("TÀI SẢN NGẮN HẠN",balance_sheet!$A:$A,0),MATCH(B$23,balance_sheet!$B$1:$XFD$1,0)),"") | C29: =IFERROR(INDEX(balance_sheet!$B:$XFD,MATCH("TÀI SẢN NGẮN HẠN",balance_sheet!$A:$A,0),MATCH(C$23,balance_sheet!$B$1:$XFD$1,0)),"") | D29: =IFERROR(INDEX(balance_sheet!$B:$XFD,MATCH("TÀI SẢN NGẮN HẠN",balance_sheet!$A:$A,0),MATCH(D$23,balance_sheet!$B$1:$XFD$1,0)),"") | E29: =IFERROR(INDEX(balance_sheet!$B:$XFD,MATCH("TÀI SẢN NGẮN HẠN",balance_sheet!$A:$A,0),MATCH(E$23,balance_sheet!$B$1:$XFD$1,0)),"") | F29: =IFERROR(INDEX(balance_sheet!$B:$XFD,MATCH("TÀI SẢN NGẮN HẠN",balance_sheet!$A:$A,0),MATCH(F$23,balance_sheet!$B$1:$XFD$1,0)),"") | G29: =IFERROR(INDEX(balance_sheet!$B:$XFD,MATCH("TÀI SẢN NGẮN HẠN",balance_sheet!$A:$A,0),MATCH(G$23,balance_sheet!$B$1:$XFD$1,0)),"") | H29: =IFERROR(INDEX(balance_sheet!$B:$XFD,MATCH("TÀI SẢN NGẮN HẠN",balance_sheet!$A:$A,0),MATCH(H$23,balance_sheet!$B$1:$XFD$1,0)),"") | I29: =IFERROR(INDEX(balance_sheet!$B:$XFD,MATCH("TÀI SẢN NGẮN HẠN",balance_sheet!$A:$A,0),MATCH(I$23,balance_sheet!$B$1:$XFD$1,0)),"")
A30: GTCL tài sản cố định vô hình | B30: =IFERROR(INDEX(balance_sheet!$B:$XFD,MATCH("GTCL tài sản cố định vô hình",balance_sheet!$A:$A,0),MATCH(B$23,balance_sheet!$B$1:$XFD$1,0)),"") | C30: =IFERROR(INDEX(balance_sheet!$B:$XFD,MATCH("GTCL tài sản cố định vô hình",balance_sheet!$A:$A,0),MATCH(C$23,balance_sheet!$B$1:$XFD$1,0)),"") | D30: =IFERROR(INDEX(balance_sheet!$B:$XFD,MATCH("GTCL tài sản cố định vô hình",balance_sheet!$A:$A,0),MATCH(D$23,balance_sheet!$B$1:$XFD$1,0)),"") | E30: =IFERROR(INDEX(balance_sheet!$B:$XFD,MATCH("GTCL tài sản cố định vô hình",balance_sheet!$A:$A,0),MATCH(E$23,balance_sheet!$B$1:$XFD$1,0)),"") | F30: =IFERROR(INDEX(balance_sheet!$B:$XFD,MATCH("GTCL tài sản cố định vô hình",balance_sheet!$A:$A,0),MATCH(F$23,balance_sheet!$B$1:$XFD$1,0)),"") | G30: =IFERROR(INDEX(balance_sheet!$B:$XFD,MATCH("GTCL tài sản cố định vô hình",balance_sheet!$A:$A,0),MATCH(G$23,balance_sheet!$B$1:$XFD$1,0)),"") | H30: =IFERROR(INDEX(balance_sheet!$B:$XFD,MATCH("GTCL tài sản cố định vô hình",balance_sheet!$A:$A,0),MATCH(H$23,balance_sheet!$B$1:$XFD$1,0)),"") | I30: =IFERROR(INDEX(balance_sheet!$B:$XFD,MATCH("GTCL tài sản cố định vô hình",balance_sheet!$A:$A,0),MATCH(I$23,balance_sheet!$B$1:$XFD$1,0)),"")
A31: TỔNG CỘNG TÀI SẢN | B31: =IFERROR(INDEX(balance_sheet!$B:$XFD,MATCH("TỔNG CỘNG TÀI SẢN",balance_sheet!$A:$A,0),MATCH(B$23,balance_sheet!$B$1:$XFD$1,0)),"") | C31: =IFERROR(INDEX(balance_sheet!$B:$XFD,MATCH("TỔNG CỘNG TÀI SẢN",balance_sheet!$A:$A,0),MATCH(C$23,balance_sheet!$B$1:$XFD$1,0)),"") | D31: =IFERROR(INDEX(balance_sheet!$B:$XFD,MATCH("TỔNG CỘNG TÀI SẢN",balance_sheet!$A:$A,0),MATCH(D$23,balance_sheet!$B$1:$XFD$1,0)),"") | E31: =IFERROR(INDEX(balance_sheet!$B:$XFD,MATCH("TỔNG CỘNG TÀI SẢN",balance_sheet!$A:$A,0),MATCH(E$23,balance_sheet!$B$1:$XFD$1,0)),"") | F31: =IFERROR(INDEX(balance_sheet!$B:$XFD,MATCH("TỔNG CỘNG TÀI SẢN",balance_sheet!$A:$A,0),MATCH(F$23,balance_sheet!$B$1:$XFD$1,0)),"") | G31: =IFERROR(INDEX(balance_sheet!$B:$XFD,MATCH("TỔNG CỘNG TÀI SẢN",balance_sheet!$A:$A,0),MATCH(G$23,balance_sheet!$B$1:$XFD$1,0)),"") | H31: =IFERROR(INDEX(balance_sheet!$B:$XFD,MATCH("TỔNG CỘNG TÀI SẢN",balance_sheet!$A:$A,0),MATCH(H$23,balance_sheet!$B$1:$XFD$1,0)),"") | I31: =IFERROR(INDEX(balance_sheet!$B:$XFD,MATCH("TỔNG CỘNG TÀI SẢN",balance_sheet!$A:$A,0),MATCH(I$23,balance_sheet!$B$1:$XFD$1,0)),"")
A32: Nguồn vốn
A33: Phải trả người bán | B33: =IFERROR(INDEX(balance_sheet!$B:$XFD,MATCH("Phải trả người bán",balance_sheet!$A:$A,0),MATCH(B$23,balance_sheet!$B$1:$XFD$1,0)),"") | C33: =IFERROR(INDEX(balance_sheet!$B:$XFD,MATCH("Phải trả người bán",balance_sheet!$A:$A,0),MATCH(C$23,balance_sheet!$B$1:$XFD$1,0)),"") | D33: =IFERROR(INDEX(balance_sheet!$B:$XFD,MATCH("Phải trả người bán",balance_sheet!$A:$A,0),MATCH(D$23,balance_sheet!$B$1:$XFD$1,0)),"") | E33: =IFERROR(INDEX(balance_sheet!$B:$XFD,MATCH("Phải trả người bán",balance_sheet!$A:$A,0),MATCH(E$23,balance_sheet!$B$1:$XFD$1,0)),"") | F33: =IFERROR(INDEX(balance_sheet!$B:$XFD,MATCH("Phải trả người bán",balance_sheet!$A:$A,0),MATCH(F$23,balance_sheet!$B$1:$XFD$1,0)),"") | G33: =IFERROR(INDEX(balance_sheet!$B:$XFD,MATCH("Phải trả người bán",balance_sheet!$A:$A,0),MATCH(G$23,balance_sheet!$B$1:$XFD$1,0)),"") | H33: =IFERROR(INDEX(balance_sheet!$B:$XFD,MATCH("Phải trả người bán",balance_sheet!$A:$A,0),MATCH(H$23,balance_sheet!$B$1:$XFD$1,0)),"") | I33: =IFERROR(INDEX(balance_sheet!$B:$XFD,MATCH("Phải trả người bán",balance_sheet!$A:$A,0),MATCH(I$23,balance_sheet!$B$1:$XFD$1,0)),"")
A34: Vay ngắn hạn | B34: =IFERROR(INDEX(balance_sheet!$B:$XFD,MATCH("Vay ngắn hạn",balance_sheet!$A:$A,0),MATCH(B$23,balance_sheet!$B$1:$XFD$1,0)),"") | C34: =IFERROR(INDEX(balance_sheet!$B:$XFD,MATCH("Vay ngắn hạn",balance_sheet!$A:$A,0),MATCH(C$23,balance_sheet!$B$1:$XFD$1,0)),"") | D34: =IFERROR(INDEX(balance_sheet!$B:$XFD,MATCH("Vay ngắn hạn",balance_sheet!$A:$A,0),MATCH(D$23,balance_sheet!$B$1:$XFD$1,0)),"") | E34: =IFERROR(INDEX(balance_sheet!$B:$XFD,MATCH("Vay ngắn hạn",balance_sheet!$A:$A,0),MATCH(E$23,balance_sheet!$B$1:$XFD$1,0)),"") | F34: =IFERROR(INDEX(balance_sheet!$B:$XFD,MATCH("Vay ngắn hạn",balance_sheet!$A:$A,0),MATCH(F$23,balance_sheet!$B$1:$XFD$1,0)),"") | G34: =IFERROR(INDEX(balance_sheet!$B:$XFD,MATCH("Vay ngắn hạn",balance_sheet!$A:$A,0),MATCH(G$23,balance_sheet!$B$1:$XFD$1,0)),"") | H34: =IFERROR(INDEX(balance_sheet!$B:$XFD,MATCH("Vay ngắn hạn",balance_sheet!$A:$A,0),MATCH(H$23,balance_sheet!$B$1:$XFD$1,0)),"") | I34: =IFERROR(INDEX(balance_sheet!$B:$XFD,MATCH("Vay ngắn hạn",balance_sheet!$A:$A,0),MATCH(I$23,balance_sheet!$B$1:$XFD$1,0)),"")
A35: Nợ ngắn hạn | B35: =IFERROR(INDEX(balance_sheet!$B:$XFD,MATCH("Nợ ngắn hạn",balance_sheet!$A:$A,0),MATCH(B$23,balance_sheet!$B$1:$XFD$1,0)),"") | C35: =IFERROR(INDEX(balance_sheet!$B:$XFD,MATCH("Nợ ngắn hạn",balance_sheet!$A:$A,0),MATCH(C$23,balance_sheet!$B$1:$XFD$1,0)),"") | D35: =IFERROR(INDEX(balance_sheet!$B:$XFD,MATCH("Nợ ngắn hạn",balance_sheet!$A:$A,0),MATCH(D$23,balance_sheet!$B$1:$XFD$1,0)),"") | E35: =IFERROR(INDEX(balance_sheet!$B:$XFD,MATCH("Nợ ngắn hạn",balance_sheet!$A:$A,0),MATCH(E$23,balance_sheet!$B$1:$XFD$1,0)),"") | F35: =IFERROR(INDEX(balance_sheet!$B:$XFD,MATCH("Nợ ngắn hạn",balance_sheet!$A:$A,0),MATCH(F$23,balance_sheet!$B$1:$XFD$1,0)),"") | G35: =IFERROR(INDEX(balance_sheet!$B:$XFD,MATCH("Nợ ngắn hạn",balance_sheet!$A:$A,0),MATCH(G$23,balance_sheet!$B$1:$XFD$1,0)),"") | H35: =IFERROR(INDEX(balance_sheet!$B:$XFD,MATCH("Nợ ngắn hạn",balance_sheet!$A:$A,0),MATCH(H$23,balance_sheet!$B$1:$XFD$1,0)),"") | I35: =IFERROR(INDEX(balance_sheet!$B:$XFD,MATCH("Nợ ngắn hạn",balance_sheet!$A:$A,0),MATCH(I$23,balance_sheet!$B$1:$XFD$1,0)),"")
A36: Vay dài hạn | B36: =IFERROR(INDEX(balance_sheet!$B:$XFD,MATCH("Vay dài hạn",balance_sheet!$A:$A,0),MATCH(B$23,balance_sheet!$B$1:$XFD$1,0)),"") | C36: =IFERROR(INDEX(balance_sheet!$B:$XFD,MATCH("Vay dài hạn",balance_sheet!$A:$A,0),MATCH(C$23,balance_sheet!$B$1:$XFD$1,0)),"") | D36: =IFERROR(INDEX(balance_sheet!$B:$XFD,MATCH("Vay dài hạn",balance_sheet!$A:$A,0),MATCH(D$23,balance_sheet!$B$1:$XFD$1,0)),"") | E36: =IFERROR(INDEX(balance_sheet!$B:$XFD,MATCH("Vay dài hạn",balance_sheet!$A:$A,0),MATCH(E$23,balance_sheet!$B$1:$XFD$1,0)),"") | F36: =IFERROR(INDEX(balance_sheet!$B:$XFD,MATCH("Vay dài hạn",balance_sheet!$A:$A,0),MATCH(F$23,balance_sheet!$B$1:$XFD$1,0)),"") | G36: =IFERROR(INDEX(balance_sheet!$B:$XFD,MATCH("Vay dài hạn",balance_sheet!$A:$A,0),MATCH(G$23,balance_sheet!$B$1:$XFD$1,0)),"") | H36: =IFERROR(INDEX(balance_sheet!$B:$XFD,MATCH("Vay dài hạn",balance_sheet!$A:$A,0),MATCH(H$23,balance_sheet!$B$1:$XFD$1,0)),"") | I36: =IFERROR(INDEX(balance_sheet!$B:$XFD,MATCH("Vay dài hạn",balance_sheet!$A:$A,0),MATCH(I$23,balance_sheet!$B$1:$XFD$1,0)),"")
A37: Nợ dài hạn | B37: =IFERROR(INDEX(balance_sheet!$B:$XFD,MATCH("Nợ dài hạn",balance_sheet!$A:$A,0),MATCH(B$23,balance_sheet!$B$1:$XFD$1,0)),"") | C37: =IFERROR(INDEX(balance_sheet!$B:$XFD,MATCH("Nợ dài hạn",balance_sheet!$A:$A,0),MATCH(C$23,balance_sheet!$B$1:$XFD$1,0)),"") | D37: =IFERROR(INDEX(balance_sheet!$B:$XFD,MATCH("Nợ dài hạn",balance_sheet!$A:$A,0),MATCH(D$23,balance_sheet!$B$1:$XFD$1,0)),"") | E37: =IFERROR(INDEX(balance_sheet!$B:$XFD,MATCH("Nợ dài hạn",balance_sheet!$A:$A,0),MATCH(E$23,balance_sheet!$B$1:$XFD$1,0)),"") | F37: =IFERROR(INDEX(balance_sheet!$B:$XFD,MATCH("Nợ dài hạn",balance_sheet!$A:$A,0),MATCH(F$23,balance_sheet!$B$1:$XFD$1,0)),"") | G37: =IFERROR(INDEX(balance_sheet!$B:$XFD,MATCH("Nợ dài hạn",balance_sheet!$A:$A,0),MATCH(G$23,balance_sheet!$B$1:$XFD$1,0)),"") | H37: =IFERROR(INDEX(balance_sheet!$B:$XFD,MATCH("Nợ dài hạn",balance_sheet!$A:$A,0),MATCH(H$23,balance_sheet!$B$1:$XFD$1,0)),"") | I37: =IFERROR(INDEX(balance_sheet!$B:$XFD,MATCH("Nợ dài hạn",balance_sheet!$A:$A,0),MATCH(I$23,balance_sheet!$B$1:$XFD$1,0)),"")
A38: NỢ PHẢI TRẢ | B38: =IFERROR(INDEX(balance_sheet!$B:$XFD,MATCH("NỢ PHẢI TRẢ",balance_sheet!$A:$A,0),MATCH(B$23,balance_sheet!$B$1:$XFD$1,0)),"") | C38: =IFERROR(INDEX(balance_sheet!$B:$XFD,MATCH("NỢ PHẢI TRẢ",balance_sheet!$A:$A,0),MATCH(C$23,balance_sheet!$B$1:$XFD$1,0)),"") | D38: =IFERROR(INDEX(balance_sheet!$B:$XFD,MATCH("NỢ PHẢI TRẢ",balance_sheet!$A:$A,0),MATCH(D$23,balance_sheet!$B$1:$XFD$1,0)),"") | E38: =IFERROR(INDEX(balance_sheet!$B:$XFD,MATCH("NỢ PHẢI TRẢ",balance_sheet!$A:$A,0),MATCH(E$23,balance_sheet!$B$1:$XFD$1,0)),"") | F38: =IFERROR(INDEX(balance_sheet!$B:$XFD,MATCH("NỢ PHẢI TRẢ",balance_sheet!$A:$A,0),MATCH(F$23,balance_sheet!$B$1:$XFD$1,0)),"") | G38: =IFERROR(INDEX(balance_sheet!$B:$XFD,MATCH("NỢ PHẢI TRẢ",balance_sheet!$A:$A,0),MATCH(G$23,balance_sheet!$B$1:$XFD$1,0)),"") | H38: =IFERROR(INDEX(balance_sheet!$B:$XFD,MATCH("NỢ PHẢI TRẢ",balance_sheet!$A:$A,0),MATCH(H$23,balance_sheet!$B$1:$XFD$1,0)),"") | I38: =IFERROR(INDEX(balance_sheet!$B:$XFD,MATCH("NỢ PHẢI TRẢ",balance_sheet!$A:$A,0),MATCH(I$23,balance_sheet!$B$1:$XFD$1,0)),"")
A39: Vốn chủ sở hữu | B39: =IFERROR(INDEX(balance_sheet!$B:$XFD,MATCH("Vốn chủ sở hữu",balance_sheet!$A:$A,0),MATCH(B$23,balance_sheet!$B$1:$XFD$1,0)),"") | C39: =IFERROR(INDEX(balance_sheet!$B:$XFD,MATCH("Vốn chủ sở hữu",balance_sheet!$A:$A,0),MATCH(C$23,balance_sheet!$B$1:$XFD$1,0)),"") | D39: =IFERROR(INDEX(balance_sheet!$B:$XFD,MATCH("Vốn chủ sở hữu",balance_sheet!$A:$A,0),MATCH(D$23,balance_sheet!$B$1:$XFD$1,0)),"") | E39: =IFERROR(INDEX(balance_sheet!$B:$XFD,MATCH("Vốn chủ sở hữu",balance_sheet!$A:$A,0),MATCH(E$23,balance_sheet!$B$1:$XFD$1,0)),"") | F39: =IFERROR(INDEX(balance_sheet!$B:$XFD,MATCH("Vốn chủ sở hữu",balance_sheet!$A:$A,0),MATCH(F$23,balance_sheet!$B$1:$XFD$1,0)),"") | G39: =IFERROR(INDEX(balance_sheet!$B:$XFD,MATCH("Vốn chủ sở hữu",balance_sheet!$A:$A,0),MATCH(G$23,balance_sheet!$B$1:$XFD$1,0)),"") | H39: =IFERROR(INDEX(balance_sheet!$B:$XFD,MATCH("Vốn chủ sở hữu",balance_sheet!$A:$A,0),MATCH(H$23,balance_sheet!$B$1:$XFD$1,0)),"") | I39: =IFERROR(INDEX(balance_sheet!$B:$XFD,MATCH("Vốn chủ sở hữu",balance_sheet!$A:$A,0),MATCH(I$23,balance_sheet!$B$1:$XFD$1,0)),"") | J39: =I39+0.8*J51
A40: Tăng VCSH/LN cổ đông cty mẹ | C40: =(C39-B39)/C51 | D40: =(D39-C39)/D51 | E40: =(E39-D39)/E51 | F40: =(F39-E39)/F51 | G40: =(G39-F39)/G51 | H40: =(H39-G39)/H51 | I40: =(I39-H39)/I51
A41: Lợi ích cổ đông không kiểm soát | B41: =IFERROR(INDEX(balance_sheet!$B:$XFD,MATCH("Lợi ích cổ đông không kiểm soát",balance_sheet!$A:$A,0),MATCH(B$23,balance_sheet!$B$1:$XFD$1,0)),"") | C41: =IFERROR(INDEX(balance_sheet!$B:$XFD,MATCH("Lợi ích cổ đông không kiểm soát",balance_sheet!$A:$A,0),MATCH(C$23,balance_sheet!$B$1:$XFD$1,0)),"") | D41: =IFERROR(INDEX(balance_sheet!$B:$XFD,MATCH("Lợi ích cổ đông không kiểm soát",balance_sheet!$A:$A,0),MATCH(D$23,balance_sheet!$B$1:$XFD$1,0)),"") | E41: =IFERROR(INDEX(balance_sheet!$B:$XFD,MATCH("Lợi ích cổ đông không kiểm soát",balance_sheet!$A:$A,0),MATCH(E$23,balance_sheet!$B$1:$XFD$1,0)),"") | F41: =IFERROR(INDEX(balance_sheet!$B:$XFD,MATCH("Lợi ích cổ đông không kiểm soát",balance_sheet!$A:$A,0),MATCH(F$23,balance_sheet!$B$1:$XFD$1,0)),"") | G41: =IFERROR(INDEX(balance_sheet!$B:$XFD,MATCH("Lợi ích cổ đông không kiểm soát",balance_sheet!$A:$A,0),MATCH(G$23,balance_sheet!$B$1:$XFD$1,0)),"") | H41: =IFERROR(INDEX(balance_sheet!$B:$XFD,MATCH("Lợi ích cổ đông không kiểm soát",balance_sheet!$A:$A,0),MATCH(H$23,balance_sheet!$B$1:$XFD$1,0)),"") | I41: =IFERROR(INDEX(balance_sheet!$B:$XFD,MATCH("Lợi ích cổ đông không kiểm soát",balance_sheet!$A:$A,0),MATCH(I$23,balance_sheet!$B$1:$XFD$1,0)),"")
A42: Kết quả hoạt động kinh doanh
A43: Doanh thu thuần | B43: =IFERROR(INDEX(income_statement!$B:$XFD,MATCH("Doanh thu thuần",income_statement!$A:$A,0),MATCH(B$23,income_statement!$B$1:$XFD$1,0)),"") | C43: =IFERROR(INDEX(income_statement!$B:$XFD,MATCH("Doanh thu thuần",income_statement!$A:$A,0),MATCH(C$23,income_statement!$B$1:$XFD$1,0)),"") | D43: =IFERROR(INDEX(income_statement!$B:$XFD,MATCH("Doanh thu thuần",income_statement!$A:$A,0),MATCH(D$23,income_statement!$B$1:$XFD$1,0)),"") | E43: =IFERROR(INDEX(income_statement!$B:$XFD,MATCH("Doanh thu thuần",income_statement!$A:$A,0),MATCH(E$23,income_statement!$B$1:$XFD$1,0)),"") | F43: =IFERROR(INDEX(income_statement!$B:$XFD,MATCH("Doanh thu thuần",income_statement!$A:$A,0),MATCH(F$23,income_statement!$B$1:$XFD$1,0)),"") | G43: =IFERROR(INDEX(income_statement!$B:$XFD,MATCH("Doanh thu thuần",income_statement!$A:$A,0),MATCH(G$23,income_statement!$B$1:$XFD$1,0)),"") | H43: =IFERROR(INDEX(income_statement!$B:$XFD,MATCH("Doanh thu thuần",income_statement!$A:$A,0),MATCH(H$23,income_statement!$B$1:$XFD$1,0)),"") | I43: =IFERROR(INDEX(income_statement!$B:$XFD,MATCH("Doanh thu thuần",income_statement!$A:$A,0),MATCH(I$23,income_statement!$B$1:$XFD$1,0)),"") | J43: 185000000000000
A44: Giá vốn hàng bán | B44: =IFERROR(INDEX(income_statement!$B:$XFD,MATCH("Giá vốn hàng bán",income_statement!$A:$A,0),MATCH(B$23,income_statement!$B$1:$XFD$1,0)),"") | C44: =IFERROR(INDEX(income_statement!$B:$XFD,MATCH("Giá vốn hàng bán",income_statement!$A:$A,0),MATCH(C$23,income_statement!$B$1:$XFD$1,0)),"") | D44: =IFERROR(INDEX(income_statement!$B:$XFD,MATCH("Giá vốn hàng bán",income_statement!$A:$A,0),MATCH(D$23,income_statement!$B$1:$XFD$1,0)),"") | E44: =IFERROR(INDEX(income_statement!$B:$XFD,MATCH("Giá vốn hàng bán",income_statement!$A:$A,0),MATCH(E$23,income_statement!$B$1:$XFD$1,0)),"") | F44: =IFERROR(INDEX(income_statement!$B:$XFD,MATCH("Giá vốn hàng bán",income_statement!$A:$A,0),MATCH(F$23,income_statement!$B$1:$XFD$1,0)),"") | G44: =IFERROR(INDEX(income_statement!$B:$XFD,MATCH("Giá vốn hàng bán",income_statement!$A:$A,0),MATCH(G$23,income_statement!$B$1:$XFD$1,0)),"") | H44: =IFERROR(INDEX(income_statement!$B:$XFD,MATCH("Giá vốn hàng bán",income_statement!$A:$A,0),MATCH(H$23,income_statement!$B$1:$XFD$1,0)),"") | I44: =IFERROR(INDEX(income_statement!$B:$XFD,MATCH("Giá vốn hàng bán",income_statement!$A:$A,0),MATCH(I$23,income_statement!$B$1:$XFD$1,0)),"")
A45: Lợi nhuận gộp | B45: =IFERROR(INDEX(income_statement!$B:$XFD,MATCH("Lợi nhuận gộp",income_statement!$A:$A,0),MATCH(B$23,income_statement!$B$1:$XFD$1,0)),"") | C45: =IFERROR(INDEX(income_statement!$B:$XFD,MATCH("Lợi nhuận gộp",income_statement!$A:$A,0),MATCH(C$23,income_statement!$B$1:$XFD$1,0)),"") | D45: =IFERROR(INDEX(income_statement!$B:$XFD,MATCH("Lợi nhuận gộp",income_statement!$A:$A,0),MATCH(D$23,income_statement!$B$1:$XFD$1,0)),"") | E45: =IFERROR(INDEX(income_statement!$B:$XFD,MATCH("Lợi nhuận gộp",income_statement!$A:$A,0),MATCH(E$23,income_statement!$B$1:$XFD$1,0)),"") | F45: =IFERROR(INDEX(income_statement!$B:$XFD,MATCH("Lợi nhuận gộp",income_statement!$A:$A,0),MATCH(F$23,income_statement!$B$1:$XFD$1,0)),"") | G45: =IFERROR(INDEX(income_statement!$B:$XFD,MATCH("Lợi nhuận gộp",income_statement!$A:$A,0),MATCH(G$23,income_statement!$B$1:$XFD$1,0)),"") | H45: =IFERROR(INDEX(income_statement!$B:$XFD,MATCH("Lợi nhuận gộp",income_statement!$A:$A,0),MATCH(H$23,income_statement!$B$1:$XFD$1,0)),"") | I45: =IFERROR(INDEX(income_statement!$B:$XFD,MATCH("Lợi nhuận gộp",income_statement!$A:$A,0),MATCH(I$23,income_statement!$B$1:$XFD$1,0)),"")
A46: Chi phí bán hàng | B46: =IFERROR(INDEX(income_statement!$B:$XFD,MATCH("Chi phí bán hàng",income_statement!$A:$A,0),MATCH(B$23,income_statement!$B$1:$XFD$1,0)),"") | C46: =IFERROR(INDEX(income_statement!$B:$XFD,MATCH("Chi phí bán hàng",income_statement!$A:$A,0),MATCH(C$23,income_statement!$B$1:$XFD$1,0)),"") | D46: =IFERROR(INDEX(income_statement!$B:$XFD,MATCH("Chi phí bán hàng",income_statement!$A:$A,0),MATCH(D$23,income_statement!$B$1:$XFD$1,0)),"") | E46: =IFERROR(INDEX(income_statement!$B:$XFD,MATCH("Chi phí bán hàng",income_statement!$A:$A,0),MATCH(E$23,income_statement!$B$1:$XFD$1,0)),"") | F46: =IFERROR(INDEX(income_statement!$B:$XFD,MATCH("Chi phí bán hàng",income_statement!$A:$A,0),MATCH(F$23,income_statement!$B$1:$XFD$1,0)),"") | G46: =IFERROR(INDEX(income_statement!$B:$XFD,MATCH("Chi phí bán hàng",income_statement!$A:$A,0),MATCH(G$23,income_statement!$B$1:$XFD$1,0)),"") | H46: =IFERROR(INDEX(income_statement!$B:$XFD,MATCH("Chi phí bán hàng",income_statement!$A:$A,0),MATCH(H$23,income_statement!$B$1:$XFD$1,0)),"") | I46: =IFERROR(INDEX(income_statement!$B:$XFD,MATCH("Chi phí bán hàng",income_statement!$A:$A,0),MATCH(I$23,income_statement!$B$1:$XFD$1,0)),"")
A47: Chi phí quản lý doanh nghiệp | B47: =IFERROR(INDEX(income_statement!$B:$XFD,MATCH("Chi phí quản lý doanh nghiệp",income_statement!$A:$A,0),MATCH(B$23,income_statement!$B$1:$XFD$1,0)),"") | C47: =IFERROR(INDEX(income_statement!$B:$XFD,MATCH("Chi phí quản lý doanh nghiệp",income_statement!$A:$A,0),MATCH(C$23,income_statement!$B$1:$XFD$1,0)),"") | D47: =IFERROR(INDEX(income_statement!$B:$XFD,MATCH("Chi phí quản lý doanh nghiệp",income_statement!$A:$A,0),MATCH(D$23,income_statement!$B$1:$XFD$1,0)),"") | E47: =IFERROR(INDEX(income_statement!$B:$XFD,MATCH("Chi phí quản lý doanh nghiệp",income_statement!$A:$A,0),MATCH(E$23,income_statement!$B$1:$XFD$1,0)),"") | F47: =IFERROR(INDEX(income_statement!$B:$XFD,MATCH("Chi phí quản lý doanh nghiệp",income_statement!$A:$A,0),MATCH(F$23,income_statement!$B$1:$XFD$1,0)),"") | G47: =IFERROR(INDEX(income_statement!$B:$XFD,MATCH("Chi phí quản lý doanh nghiệp",income_statement!$A:$A,0),MATCH(G$23,income_statement!$B$1:$XFD$1,0)),"") | H47: =IFERROR(INDEX(income_statement!$B:$XFD,MATCH("Chi phí quản lý doanh nghiệp",income_statement!$A:$A,0),MATCH(H$23,income_statement!$B$1:$XFD$1,0)),"") | I47: =IFERROR(INDEX(income_statement!$B:$XFD,MATCH("Chi phí quản lý doanh nghiệp",income_statement!$A:$A,0),MATCH(I$23,income_statement!$B$1:$XFD$1,0)),"")
A48: Lãi/(lỗ) từ hoạt động kinh doanh | B48: =IFERROR(INDEX(income_statement!$B:$XFD,MATCH("Lãi/(lỗ) từ hoạt động kinh doanh",income_statement!$A:$A,0),MATCH(B$23,income_statement!$B$1:$XFD$1,0)),"") | C48: =IFERROR(INDEX(income_statement!$B:$XFD,MATCH("Lãi/(lỗ) từ hoạt động kinh doanh",income_statement!$A:$A,0),MATCH(C$23,income_statement!$B$1:$XFD$1,0)),"") | D48: =IFERROR(INDEX(income_statement!$B:$XFD,MATCH("Lãi/(lỗ) từ hoạt động kinh doanh",income_statement!$A:$A,0),MATCH(D$23,income_statement!$B$1:$XFD$1,0)),"") | E48: =IFERROR(INDEX(income_statement!$B:$XFD,MATCH("Lãi/(lỗ) từ hoạt động kinh doanh",income_statement!$A:$A,0),MATCH(E$23,income_statement!$B$1:$XFD$1,0)),"") | F48: =IFERROR(INDEX(income_statement!$B:$XFD,MATCH("Lãi/(lỗ) từ hoạt động kinh doanh",income_statement!$A:$A,0),MATCH(F$23,income_statement!$B$1:$XFD$1,0)),"") | G48: =IFERROR(INDEX(income_statement!$B:$XFD,MATCH("Lãi/(lỗ) từ hoạt động kinh doanh",income_statement!$A:$A,0),MATCH(G$23,income_statement!$B$1:$XFD$1,0)),"") | H48: =IFERROR(INDEX(income_statement!$B:$XFD,MATCH("Lãi/(lỗ) từ hoạt động kinh doanh",income_statement!$A:$A,0),MATCH(H$23,income_statement!$B$1:$XFD$1,0)),"") | I48: =IFERROR(INDEX(income_statement!$B:$XFD,MATCH("Lãi/(lỗ) từ hoạt động kinh doanh",income_statement!$A:$A,0),MATCH(I$23,income_statement!$B$1:$XFD$1,0)),"")
A49: Chi phí lãi vay | B49: =IFERROR(INDEX(income_statement!$B:$XFD,MATCH("Chi phí lãi vay",income_statement!$A:$A,0),MATCH(B$23,income_statement!$B$1:$XFD$1,0)),"") | C49: =IFERROR(INDEX(income_statement!$B:$XFD,MATCH("Chi phí lãi vay",income_statement!$A:$A,0),MATCH(C$23,income_statement!$B$1:$XFD$1,0)),"") | D49: =IFERROR(INDEX(income_statement!$B:$XFD,MATCH("Chi phí lãi vay",income_statement!$A:$A,0),MATCH(D$23,income_statement!$B$1:$XFD$1,0)),"") | E49: =IFERROR(INDEX(income_statement!$B:$XFD,MATCH("Chi phí lãi vay",income_statement!$A:$A,0),MATCH(E$23,income_statement!$B$1:$XFD$1,0)),"") | F49: =IFERROR(INDEX(income_statement!$B:$XFD,MATCH("Chi phí lãi vay",income_statement!$A:$A,0),MATCH(F$23,income_statement!$B$1:$XFD$1,0)),"") | G49: =IFERROR(INDEX(income_statement!$B:$XFD,MATCH("Chi phí lãi vay",income_statement!$A:$A,0),MATCH(G$23,income_statement!$B$1:$XFD$1,0)),"") | H49: =IFERROR(INDEX(income_statement!$B:$XFD,MATCH("Chi phí lãi vay",income_statement!$A:$A,0),MATCH(H$23,income_statement!$B$1:$XFD$1,0)),"") | I49: =IFERROR(INDEX(income_statement!$B:$XFD,MATCH("Chi phí lãi vay",income_statement!$A:$A,0),MATCH(I$23,income_statement!$B$1:$XFD$1,0)),"")
A50: Lãi/(lỗ) thuần sau thuế | B50: =IFERROR(INDEX(income_statement!$B:$XFD,MATCH("Lãi/(lỗ) thuần sau thuế",income_statement!$A:$A,0),MATCH(B$23,income_statement!$B$1:$XFD$1,0)),"") | C50: =IFERROR(INDEX(income_statement!$B:$XFD,MATCH("Lãi/(lỗ) thuần sau thuế",income_statement!$A:$A,0),MATCH(C$23,income_statement!$B$1:$XFD$1,0)),"") | D50: =IFERROR(INDEX(income_statement!$B:$XFD,MATCH("Lãi/(lỗ) thuần sau thuế",income_statement!$A:$A,0),MATCH(D$23,income_statement!$B$1:$XFD$1,0)),"") | E50: =IFERROR(INDEX(income_statement!$B:$XFD,MATCH("Lãi/(lỗ) thuần sau thuế",income_statement!$A:$A,0),MATCH(E$23,income_statement!$B$1:$XFD$1,0)),"") | F50: =IFERROR(INDEX(income_statement!$B:$XFD,MATCH("Lãi/(lỗ) thuần sau thuế",income_statement!$A:$A,0),MATCH(F$23,income_statement!$B$1:$XFD$1,0)),"") | G50: =IFERROR(INDEX(income_statement!$B:$XFD,MATCH("Lãi/(lỗ) thuần sau thuế",income_statement!$A:$A,0),MATCH(G$23,income_statement!$B$1:$XFD$1,0)),"") | H50: =IFERROR(INDEX(income_statement!$B:$XFD,MATCH("Lãi/(lỗ) thuần sau thuế",income_statement!$A:$A,0),MATCH(H$23,income_statement!$B$1:$XFD$1,0)),"") | I50: =IFERROR(INDEX(income_statement!$B:$XFD,MATCH("Lãi/(lỗ) thuần sau thuế",income_statement!$A:$A,0),MATCH(I$23,income_statement!$B$1:$XFD$1,0)),"") | J50: 9200000000000
A51: Lợi nhuận của Cổ đông của Công ty mẹ | B51: =IFERROR(INDEX(income_statement!$B:$XFD,MATCH("Lợi nhuận của Cổ đông của Công ty mẹ",income_statement!$A:$A,0),MATCH(B$23,income_statement!$B$1:$XFD$1,0)),"") | C51: =IFERROR(INDEX(income_statement!$B:$XFD,MATCH("Lợi nhuận của Cổ đông của Công ty mẹ",income_statement!$A:$A,0),MATCH(C$23,income_statement!$B$1:$XFD$1,0)),"") | D51: =IFERROR(INDEX(income_statement!$B:$XFD,MATCH("Lợi nhuận của Cổ đông của Công ty mẹ",income_statement!$A:$A,0),MATCH(D$23,income_statement!$B$1:$XFD$1,0)),"") | E51: =IFERROR(INDEX(income_statement!$B:$XFD,MATCH("Lợi nhuận của Cổ đông của Công ty mẹ",income_statement!$A:$A,0),MATCH(E$23,income_statement!$B$1:$XFD$1,0)),"") | F51: =IFERROR(INDEX(income_statement!$B:$XFD,MATCH("Lợi nhuận của Cổ đông của Công ty mẹ",income_statement!$A:$A,0),MATCH(F$23,income_statement!$B$1:$XFD$1,0)),"") | G51: =IFERROR(INDEX(income_statement!$B:$XFD,MATCH("Lợi nhuận của Cổ đông của Công ty mẹ",income_statement!$A:$A,0),MATCH(G$23,income_statement!$B$1:$XFD$1,0)),"") | H51: =IFERROR(INDEX(income_statement!$B:$XFD,MATCH("Lợi nhuận của Cổ đông của Công ty mẹ",income_statement!$A:$A,0),MATCH(H$23,income_statement!$B$1:$XFD$1,0)),"") | I51: =IFERROR(INDEX(income_statement!$B:$XFD,MATCH("Lợi nhuận của Cổ đông của Công ty mẹ",income_statement!$A:$A,0),MATCH(I$23,income_statement!$B$1:$XFD$1,0)),"") | J51: 9200000000000
A52: Lưu chuyển tiền tệ
A53: Khấu hao TSCĐ và BĐSĐT | B53: =IFERROR(INDEX(cash_flow!$B:$XFD,MATCH("Khấu hao TSCĐ và BĐSĐT",cash_flow!$A:$A,0),MATCH(B$23,cash_flow!$B$1:$XFD$1,0)),"") | C53: =IFERROR(INDEX(cash_flow!$B:$XFD,MATCH("Khấu hao TSCĐ và BĐSĐT",cash_flow!$A:$A,0),MATCH(C$23,cash_flow!$B$1:$XFD$1,0)),"") | D53: =IFERROR(INDEX(cash_flow!$B:$XFD,MATCH("Khấu hao TSCĐ và BĐSĐT",cash_flow!$A:$A,0),MATCH(D$23,cash_flow!$B$1:$XFD$1,0)),"") | E53: =IFERROR(INDEX(cash_flow!$B:$XFD,MATCH("Khấu hao TSCĐ và BĐSĐT",cash_flow!$A:$A,0),MATCH(E$23,cash_flow!$B$1:$XFD$1,0)),"") | F53: =IFERROR(INDEX(cash_flow!$B:$XFD,MATCH("Khấu hao TSCĐ và BĐSĐT",cash_flow!$A:$A,0),MATCH(F$23,cash_flow!$B$1:$XFD$1,0)),"") | G53: =IFERROR(INDEX(cash_flow!$B:$XFD,MATCH("Khấu hao TSCĐ và BĐSĐT",cash_flow!$A:$A,0),MATCH(G$23,cash_flow!$B$1:$XFD$1,0)),"") | H53: =IFERROR(INDEX(cash_flow!$B:$XFD,MATCH("Khấu hao TSCĐ và BĐSĐT",cash_flow!$A:$A,0),MATCH(H$23,cash_flow!$B$1:$XFD$1,0)),"") | I53: =IFERROR(INDEX(cash_flow!$B:$XFD,MATCH("Khấu hao TSCĐ và BĐSĐT",cash_flow!$A:$A,0),MATCH(I$23,cash_flow!$B$1:$XFD$1,0)),"")
A54: Tiền chi để mua sắm, xây dựng TSCĐ và các tài sản dài hạn khác | B54: =IFERROR(INDEX(cash_flow!$B:$XFD,MATCH("Tiền chi để mua sắm, xây dựng TSCĐ và các tài sản dài hạn khác",cash_flow!$A:$A,0),MATCH(B$23,cash_flow!$B$1:$XFD$1,0)),"") | C54: =IFERROR(INDEX(cash_flow!$B:$XFD,MATCH("Tiền chi để mua sắm, xây dựng TSCĐ và các tài sản dài hạn khác",cash_flow!$A:$A,0),MATCH(C$23,cash_flow!$B$1:$XFD$1,0)),"") | D54: =IFERROR(INDEX(cash_flow!$B:$XFD,MATCH("Tiền chi để mua sắm, xây dựng TSCĐ và các tài sản dài hạn khác",cash_flow!$A:$A,0),MATCH(D$23,cash_flow!$B$1:$XFD$1,0)),"") | E54: =IFERROR(INDEX(cash_flow!$B:$XFD,MATCH("Tiền chi để mua sắm, xây dựng TSCĐ và các tài sản dài hạn khác",cash_flow!$A:$A,0),MATCH(E$23,cash_flow!$B$1:$XFD$1,0)),"") | F54: =IFERROR(INDEX(cash_flow!$B:$XFD,MATCH("Tiền chi để mua sắm, xây dựng TSCĐ và các tài sản dài hạn khác",cash_flow!$A:$A,0),MATCH(F$23,cash_flow!$B$1:$XFD$1,0)),"") | G54: =IFERROR(INDEX(cash_flow!$B:$XFD,MATCH("Tiền chi để mua sắm, xây dựng TSCĐ và các tài sản dài hạn khác",cash_flow!$A:$A,0),MATCH(G$23,cash_flow!$B$1:$XFD$1,0)),"") | H54: =IFERROR(INDEX(cash_flow!$B:$XFD,MATCH("Tiền chi để mua sắm, xây dựng TSCĐ và các tài sản dài hạn khác",cash_flow!$A:$A,0),MATCH(H$23,cash_flow!$B$1:$XFD$1,0)),"") | I54: =IFERROR(INDEX(cash_flow!$B:$XFD,MATCH("Tiền chi để mua sắm, xây dựng TSCĐ và các tài sản dài hạn khác",cash_flow!$A:$A,0),MATCH(I$23,cash_flow!$B$1:$XFD$1,0)),"")
A55: Lưu chuyển tiền tệ ròng từ các hoạt động sản xuất kinh doanh | B55: =IFERROR(INDEX(cash_flow!$B:$XFD,MATCH("Lưu chuyển tiền tệ ròng từ các hoạt động sản xuất kinh doanh",cash_flow!$A:$A,0),MATCH(B$23,cash_flow!$B$1:$XFD$1,0)),"") | C55: =IFERROR(INDEX(cash_flow!$B:$XFD,MATCH("Lưu chuyển tiền tệ ròng từ các hoạt động sản xuất kinh doanh",cash_flow!$A:$A,0),MATCH(C$23,cash_flow!$B$1:$XFD$1,0)),"") | D55: =IFERROR(INDEX(cash_flow!$B:$XFD,MATCH("Lưu chuyển tiền tệ ròng từ các hoạt động sản xuất kinh doanh",cash_flow!$A:$A,0),MATCH(D$23,cash_flow!$B$1:$XFD$1,0)),"") | E55: =IFERROR(INDEX(cash_flow!$B:$XFD,MATCH("Lưu chuyển tiền tệ ròng từ các hoạt động sản xuất kinh doanh",cash_flow!$A:$A,0),MATCH(E$23,cash_flow!$B$1:$XFD$1,0)),"") | F55: =IFERROR(INDEX(cash_flow!$B:$XFD,MATCH("Lưu chuyển tiền tệ ròng từ các hoạt động sản xuất kinh doanh",cash_flow!$A:$A,0),MATCH(F$23,cash_flow!$B$1:$XFD$1,0)),"") | G55: =IFERROR(INDEX(cash_flow!$B:$XFD,MATCH("Lưu chuyển tiền tệ ròng từ các hoạt động sản xuất kinh doanh",cash_flow!$A:$A,0),MATCH(G$23,cash_flow!$B$1:$XFD$1,0)),"") | H55: =IFERROR(INDEX(cash_flow!$B:$XFD,MATCH("Lưu chuyển tiền tệ ròng từ các hoạt động sản xuất kinh doanh",cash_flow!$A:$A,0),MATCH(H$23,cash_flow!$B$1:$XFD$1,0)),"") | I55: =IFERROR(INDEX(cash_flow!$B:$XFD,MATCH("Lưu chuyển tiền tệ ròng từ các hoạt động sản xuất kinh doanh",cash_flow!$A:$A,0),MATCH(I$23,cash_flow!$B$1:$XFD$1,0)),"")
A59: CHỈ SỐ THÊM | B59: 2018 | C59: 2019 | D59: 2020 | E59: 2021 | F59: 2022 | G59: 2023 | H59: 2024 | I59: 2025
A60: Khả năng sinh lời & hiệu quả sử dụng vốn
A61: ROCE | B61: =IFERROR(B$63/(B$31-B$35),"n/a") | C61: =IFERROR(C$63/(C$31-C$35),"n/a") | D61: =IFERROR(D$63/(D$31-D$35),"n/a") | E61: =IFERROR(E$63/(E$31-E$35),"n/a") | F61: =IFERROR(F$63/(F$31-F$35),"n/a") | G61: =IFERROR(G$63/(G$31-G$35),"n/a") | H61: =IFERROR(H$63/(H$31-H$35),"n/a") | I61: =IFERROR(I$63/(I$31-I$35),"n/a")
A62: CROIC | B62: =IFERROR(B$67/(B$31-B$35),"n/a") | C62: =IFERROR(C$67/(C$31-C$35),"n/a") | D62: =IFERROR(D$67/(D$31-D$35),"n/a") | E62: =IFERROR(E$67/(E$31-E$35),"n/a") | F62: =IFERROR(F$67/(F$31-F$35),"n/a") | G62: =IFERROR(G$67/(G$31-G$35),"n/a") | H62: =IFERROR(H$67/(H$31-H$35),"n/a") | I62: =IFERROR(I$67/(I$31-I$35),"n/a")
A63: EBIT | B63: =IFERROR(B$48+ABS(B$49),"n/a") | C63: =IFERROR(C$48+ABS(C$49),"n/a") | D63: =IFERROR(D$48+ABS(D$49),"n/a") | E63: =IFERROR(E$48+ABS(E$49),"n/a") | F63: =IFERROR(F$48+ABS(F$49),"n/a") | G63: =IFERROR(G$48+ABS(G$49),"n/a") | H63: =IFERROR(H$48+ABS(H$49),"n/a") | I63: =IFERROR(I$48+ABS(I$49),"n/a")
A64: EBIT/DT | B64: =IFERROR(B$63/B$43,"n/a") | C64: =IFERROR(C$63/C$43,"n/a") | D64: =IFERROR(D$63/D$43,"n/a") | E64: =IFERROR(E$63/E$43,"n/a") | F64: =IFERROR(F$63/F$43,"n/a") | G64: =IFERROR(G$63/G$43,"n/a") | H64: =IFERROR(H$63/H$43,"n/a") | I64: =IFERROR(I$63/I$43,"n/a")
A65: DT/TS | B65: =IFERROR(B$43/B$31,"n/a") | C65: =IFERROR(C$43/C$31,"n/a") | D65: =IFERROR(D$43/D$31,"n/a") | E65: =IFERROR(E$43/E$31,"n/a") | F65: =IFERROR(F$43/F$31,"n/a") | G65: =IFERROR(G$43/G$31,"n/a") | H65: =IFERROR(H$43/H$31,"n/a") | I65: =IFERROR(I$43/I$31,"n/a")
A66: Dòng tiền & tái đầu tư
A67: FCF | B67: =IFERROR(B$55-ABS(B$54),"n/a") | C67: =IFERROR(C$55-ABS(C$54),"n/a") | D67: =IFERROR(D$55-ABS(D$54),"n/a") | E67: =IFERROR(E$55-ABS(E$54),"n/a") | F67: =IFERROR(F$55-ABS(F$54),"n/a") | G67: =IFERROR(G$55-ABS(G$54),"n/a") | H67: =IFERROR(H$55-ABS(H$54),"n/a") | I67: =IFERROR(I$55-ABS(I$54),"n/a")
A68: FCF/DT | B68: =IFERROR(B$67/B$43,"n/a") | C68: =IFERROR(C$67/C$43,"n/a") | D68: =IFERROR(D$67/D$43,"n/a") | E68: =IFERROR(E$67/E$43,"n/a") | F68: =IFERROR(F$67/F$43,"n/a") | G68: =IFERROR(G$67/G$43,"n/a") | H68: =IFERROR(H$67/H$43,"n/a") | I68: =IFERROR(I$67/I$43,"n/a")
A69: FCF/Nợ ngắn hạn | B69: =IFERROR(B$67/B$35,"n/a") | C69: =IFERROR(C$67/C$35,"n/a") | D69: =IFERROR(D$67/D$35,"n/a") | E69: =IFERROR(E$67/E$35,"n/a") | F69: =IFERROR(F$67/F$35,"n/a") | G69: =IFERROR(G$67/G$35,"n/a") | H69: =IFERROR(H$67/H$35,"n/a") | I69: =IFERROR(I$67/I$35,"n/a")
A70: Capex | B70: =IFERROR(ABS(B$54),"n/a") | C70: =IFERROR(ABS(C$54),"n/a") | D70: =IFERROR(ABS(D$54),"n/a") | E70: =IFERROR(ABS(E$54),"n/a") | F70: =IFERROR(ABS(F$54),"n/a") | G70: =IFERROR(ABS(G$54),"n/a") | H70: =IFERROR(ABS(H$54),"n/a") | I70: =IFERROR(ABS(I$54),"n/a")
A71: Capex/TS | B71: =IFERROR(B$70/B$31,"n/a") | C71: =IFERROR(C$70/C$31,"n/a") | D71: =IFERROR(D$70/D$31,"n/a") | E71: =IFERROR(E$70/E$31,"n/a") | F71: =IFERROR(F$70/F$31,"n/a") | G71: =IFERROR(G$70/G$31,"n/a") | H71: =IFERROR(H$70/H$31,"n/a") | I71: =IFERROR(I$70/I$31,"n/a")
A72: Capex/LNST | B72: =IFERROR(B$70/ABS(B$50),"n/a") | C72: =IFERROR(C$70/ABS(C$50),"n/a") | D72: =IFERROR(D$70/ABS(D$50),"n/a") | E72: =IFERROR(E$70/ABS(E$50),"n/a") | F72: =IFERROR(F$70/ABS(F$50),"n/a") | G72: =IFERROR(G$70/ABS(G$50),"n/a") | H72: =IFERROR(H$70/ABS(H$50),"n/a") | I72: =IFERROR(I$70/ABS(I$50),"n/a")
A73: Chi phí khấu hao/Lợi nhuận gộp | B73: =IFERROR(ABS(B$53)/B$45,"n/a") | C73: =IFERROR(ABS(C$53)/C$45,"n/a") | D73: =IFERROR(ABS(D$53)/D$45,"n/a") | E73: =IFERROR(ABS(E$53)/E$45,"n/a") | F73: =IFERROR(ABS(F$53)/F$45,"n/a") | G73: =IFERROR(ABS(G$53)/G$45,"n/a") | H73: =IFERROR(ABS(H$53)/H$45,"n/a") | I73: =IFERROR(ABS(I$53)/I$45,"n/a")
A74: EBIT/Chi phí lãi vay | B74: =IFERROR(B$63/ABS(B$49),"n/a") | C74: =IFERROR(C$63/ABS(C$49),"n/a") | D74: =IFERROR(D$63/ABS(D$49),"n/a") | E74: =IFERROR(E$63/ABS(E$49),"n/a") | F74: =IFERROR(F$63/ABS(F$49),"n/a") | G74: =IFERROR(G$63/ABS(G$49),"n/a") | H74: =IFERROR(H$63/ABS(H$49),"n/a") | I74: =IFERROR(I$63/ABS(I$49),"n/a")
A75: Vốn lưu động & hiệu quả hoạt động
A76: Vòng quay tiền mặt | B76: =IFERROR(B$17+B$18-B$16,"n/a") | C76: =IFERROR(C$17+C$18-C$16,"n/a") | D76: =IFERROR(D$17+D$18-D$16,"n/a") | E76: =IFERROR(E$17+E$18-E$16,"n/a") | F76: =IFERROR(F$17+F$18-F$16,"n/a") | G76: =IFERROR(G$17+G$18-G$16,"n/a") | H76: =IFERROR(H$17+H$18-H$16,"n/a") | I76: =IFERROR(I$17+I$18-I$16,"n/a")
A77: HTK/DT | B77: =IFERROR(B$28/B$43,"n/a") | C77: =IFERROR(C$28/C$43,"n/a") | D77: =IFERROR(D$28/D$43,"n/a") | E77: =IFERROR(E$28/E$43,"n/a") | F77: =IFERROR(F$28/F$43,"n/a") | G77: =IFERROR(G$28/G$43,"n/a") | H77: =IFERROR(H$28/H$43,"n/a") | I77: =IFERROR(I$28/I$43,"n/a")
A78: HTK/TS | B78: =IFERROR(B$28/B$31,"n/a") | C78: =IFERROR(C$28/C$31,"n/a") | D78: =IFERROR(D$28/D$31,"n/a") | E78: =IFERROR(E$28/E$31,"n/a") | F78: =IFERROR(F$28/F$31,"n/a") | G78: =IFERROR(G$28/G$31,"n/a") | H78: =IFERROR(H$28/H$31,"n/a") | I78: =IFERROR(I$28/I$31,"n/a")
A79: DT/TS | B79: =IFERROR(B$43/B$31,"n/a") | C79: =IFERROR(C$43/C$31,"n/a") | D79: =IFERROR(D$43/D$31,"n/a") | E79: =IFERROR(E$43/E$31,"n/a") | F79: =IFERROR(F$43/F$31,"n/a") | G79: =IFERROR(G$43/G$31,"n/a") | H79: =IFERROR(H$43/H$31,"n/a") | I79: =IFERROR(I$43/I$31,"n/a")
A80: Khả năng thanh toán
A81: (TS ngắn hạn − HTK)/Nợ ngắn hạn | B81: =IFERROR((B$29-B$28)/B$35,"n/a") | C81: =IFERROR((C$29-C$28)/C$35,"n/a") | D81: =IFERROR((D$29-D$28)/D$35,"n/a") | E81: =IFERROR((E$29-E$28)/E$35,"n/a") | F81: =IFERROR((F$29-F$28)/F$35,"n/a") | G81: =IFERROR((G$29-G$28)/G$35,"n/a") | H81: =IFERROR((H$29-H$28)/H$35,"n/a") | I81: =IFERROR((I$29-I$28)/I$35,"n/a")
A82: TS ngắn hạn/Nợ ngắn hạn | B82: =IFERROR(B$29/B$35,"n/a") | C82: =IFERROR(C$29/C$35,"n/a") | D82: =IFERROR(D$29/D$35,"n/a") | E82: =IFERROR(E$29/E$35,"n/a") | F82: =IFERROR(F$29/F$35,"n/a") | G82: =IFERROR(G$29/G$35,"n/a") | H82: =IFERROR(H$29/H$35,"n/a") | I82: =IFERROR(I$29/I$35,"n/a")
A83: Tài sản & cơ cấu tài sản
A84: TSCĐ vô hình | B84: =IFERROR(B$30,"n/a") | C84: =IFERROR(C$30,"n/a") | D84: =IFERROR(D$30,"n/a") | E84: =IFERROR(E$30,"n/a") | F84: =IFERROR(F$30,"n/a") | G84: =IFERROR(G$30,"n/a") | H84: =IFERROR(H$30,"n/a") | I84: =IFERROR(I$30,"n/a")
A85: Tài sản vô hình/Giá trị sổ sách | B85: =IFERROR(B$30/B$39,"n/a") | C85: =IFERROR(C$30/C$39,"n/a") | D85: =IFERROR(D$30/D$39,"n/a") | E85: =IFERROR(E$30/E$39,"n/a") | F85: =IFERROR(F$30/F$39,"n/a") | G85: =IFERROR(G$30/G$39,"n/a") | H85: =IFERROR(H$30/H$39,"n/a") | I85: =IFERROR(I$30/I$39,"n/a")

Sheet Dự báo tăng trưởng
B1: Q1/2026 | C1: Q2/2026 | D1: Q3/2026 | E1: Q4/2026
A2: Số CP | B2: 1475765646 | C2: 1475765646 | D2: 1475765646 | E2: 1475765646
A3: Thị giá | B3: 75100 | C3: 75100 | D3: 75100 | E3: 75100
A4: Vốn hoá | B4: =B2*B3 | C4: =C2*C3 | D4: =D2*D3 | E4: =E2*E3
A6: VCSH | B6: 35933000000000 | C6: 36351000000000 | D6: =B6*(($E$6/B6)^(2/3)) | E6: =chi_so_tai_chinh!J39
A7: LICĐTS | B7: 619000000000 | C7: 672000000000 | D7: =D6*0.02 | E7: =E6*0.02
A8: BV | B8: =B6-B7 | C8: =C6-C7 | D8: =D6-D7 | E8: =E6-E7
A9: BVPS | B9: =B8/B2 | C9: =C8/C2 | D9: =D8/D2 | E9: =E8/E2
A10: PB | B10: =B3/B9 | C10: =C3/C9 | D10: =D3/D9 | E10: =E3/E9
