Workbook

Sheet balance_sheet
A1: item | B1: 2018 | C1: 2019 | D1: 2020 | E1: 2021 | F1: 2022 | G1: 2023 | H1: 2024 | I1: 2025
A2: TÀI SẢN NGẮN HẠN | B2: 4815269284036 | C2: 6173238780511 | D2: 4959999144880 | E2: 10185041534436 | F2: 9326797408285 | G2: 11415308018413 | H2: 14026158730456 | I2: 21787052185671
A3: Tiền và tương đương tiền | B3: 948378394826 | C3: 869649553585 | D3: 701504239398 | E3: 1105209549882 | F3: 745556075005 | G3: 960822549973 | H3: 2097787236988 | I3: 2869851759629
A4: Tiền | B4: 855378394826 | C4: 415978667247 | D4: 551504239398 | E4: 679938797236 | F4: 450488205110 | G4: 514817562060 | H4: 475787236988 | I4: 385251759629
A5: Các khoản tương đương tiền | B5: 93000000000 | C5: 453670886338 | D5: 150000000000 | E5: 425270752646 | F5: 295067869895 | G5: 446004987913 | H5: 1622000000000 | I5: 2484600000000
A6: Đầu tư ngắn hạn | B6: 0 | C6: 0 | D6: 0 | E6: 0 | F6: 0 | G6: 0 | H6: 0 | I6: 0
A7: Đầu tư ngắn hạn | F7: 0 | G7: 0 | H7: 0 | I7: 0
A8: Dự phòng giảm giá | B8: 0 | C8: 0 | D8: 0 | E8: 0 | F8: 0 | G8: 0 | H8: 0 | I8: 0
A9: Các khoản phải thu | B9: 1206756927412 | C9: 1178069210426 | D9: 1498241305903 | E9: 1948474611240 | F9: 538346191905 | G9: 394464296948 | H9: 417127103606 | I9: 728878339921
A10: Phải thu khách hàng | B10: 237824070242 | C10: 294574594760 | D10: 172584643781 | E10: 80725494654 | F10: 89622537320 | G10: 126026140388 | H10: 176150692098 | I10: 233091257926
A11: Trả trước người bán | B11: 144013265281 | C11: 96527158702 | D11: 93596830533 | E11: 128696749438 | F11: 73767134666 | G11: 48902780339 | H11: 43997579646 | I11: 94792455388
A12: Phải thu nội bộ | B12: 0 | C12: 0 | D12: 0 | E12: 0 | F12: 0 | G12: 0 | H12: 0 | I12: 0
A13: Phải thu hợp đồng xây dựng đang thực hiện | B13: 0 | C13: 0 | D13: 0 | E13: 0 | F13: 0 | G13: 0 | H13: 0 | I13: 0
A14: Phải thu khác | B14: 722345486208 | C14: 499067505423 | D14: 405045636978 | E14: 186801082361 | F14: 342099580137 | G14: 227411821380 | H14: 206546170984 | I14: 410499058289
A15: Dự phòng nợ khó đòi | B15: -17784960512 | C15: -34459114652 | D15: -57985805389 | E15: -7748715213 | F15: -7143060218 | G15: -7876445159 | H15: -9567339122 | I15: -9504431682
A16: Hàng tồn kho, ròng | B16: 2506218917201 | C16: 3383542174980 | D16: 1826717690762 | E16: 4930359332607 | F16: 6483827665529 | G16: 8426860753034 | H16: 10234733890772 | I16: 11926663463990
A17: Hàng tồn kho | B17: 2519583804091 | C17: 3399092416117 | D17: 1853134198142 | E17: 4975973822810 | F17: 6525562245058 | G17: 8470079480259 | H17: 10291473307238 | I17: 12012604661865
A18: Dự phòng giảm giá hàng tồn kho | B18: -13364886890 | C18: -15550241137 | D18: -26416507380 | E18: -45614490203 | F18: -41734579529 | G18: -43218727225 | H18: -56739416466 | I18: -85941197875
A19: Tài sản lưu động khác | B19: 0 | C19: 0 | D19: 0 | E19: 0 | F19: 0 | G19: 0 | H19: 0 | I19: 0
... A22: Phải thu thuế khác | B22: 27500 | C22: 1858819 | D22: 1858819 | E22: 232407273 | F22: 22114306031 | G22: 22210188195 | H22: 21546455611 | I22: 22214405075
A23: Tài sản lưu động khác | F23: 0 | G23: 0 | H23: 0 | I23: 0
A24: TÀI SẢN DÀI HẠN | B24: 352400130929 | C24: 420534253911 | D24: 427578741148 | E24: 635298266482 | F24: 1196999526761 | G24: 1683141884191 | H24: 1806391668645 | I24: 1927183984705
A25: Phải thu dài hạn | B25: 84027534483 | C25: 105270293641 | D25: 116400384163 | E25: 136776859874 | F25: 170162186921 | G25: 179315098485 | H25: 182805424079 | I25: 194450060810
A26: Phải thu khách hàng dài hạn | B26: 0 | C26: 0 | D26: 0 | E26: 0 | F26: 0 | G26: 0 | H26: 0 | I26: 0
A27: Phải thu nội bộ dài hạn | B27: 0 | C27: 0 | D27: 0 | E27: 0 | F27: 0 | G27: 0 | H27: 0 | I27: 0
A28: Phải thu dài hạn khác | B28: 84027534483 | C28: 105270293641 | D28: 116400384163 | E28: 136776859874 | F28: 170162186921 | G28: 179315098485 | H28: 182805424079 | I28: 194450060810
A29: Dự phòng phải thu dài hạn | B29: 0 | C29: 0 | D29: 0 | E29: 0 | F29: 0 | G29: 0 | H29: 0 | I29: 0
A30: Tài sản cố định | B30: 45591818347 | C30: 48570958580 | D30: 50627870323 | E30: 448088085056 | F30: 847269560047 | G30: 1307637254001 | H30: 1445982801672 | I30: 1574317843107
A31: GTCL TSCĐ hữu hình | B31: 5154076518 | C31: 6614568303 | D31: 8708246794 | E31: 292481788227 | F31: 675128050014 | G31: 1079496087742 | H31: 1156676461871 | I31: 1196539820561
A32: Nguyên giá TSCĐ hữu hình | B32: 9344459141 | C32: 11190777144 | D32: 14159992286 | E32: 489527414193 | F32: 979182072742 | G32: 1608729339222 | H32: 1915183739839 | I32: 2285328752900
A33: Khấu hao lũy kế TSCĐ hữu hình | B33: -4190382623 | C33: -4576208841 | D33: -5451745492 | E33: -197045625966 | F33: -304054022728 | G33: -529233251480 | H33: -758507277968 | I33: -1088788932339
A34: GTCL tài sản thuê tài chính | B34: 0 | C34: 0 | D34: 0 | E34: 0 | F34: 0 | G34: 0 | H34: 0 | I34: 0
A35: Nguyên giá tài sản thuê tài chính | B35: 0 | C35: 0 | D35: 0 | E35: 0 | F35: 0 | G35: 0 | H35: 0 | I35: 0
... A72: Vay dài hạn | B72: 0 | C72: 0 | D72: 0 | E72: 0 | F72: 0 | G72: 0 | H72: 0 | I72: 0
A73: Thuế thu nhập hoãn lại | F73: 0 | G73: 14902586 | H73: 31681844 | I73: 31681844
A74: Dự phòng trợ cấp thôi việc | B74: 0 | C74: 0 | D74: 0 | E74: 0 | F74: 0 | G74: 0 | H74: 0 | I74: 0
A75: Dự phòng các khoản nợ dài hạn | B75: 0 | C75: 0 | D75: 0 | E75: 0 | F75: 0 | G75: 0 | H75: 0 | I75: 0
A76: Doanh thu chưa thực hiện | B76: 0 | C76: 0 | D76: 0 | E76: 0 | F76: 0 | G76: 0 | H76: 0 | I76: 0
A77: Quỹ phát triển khoa học công nghệ | B77: 0 | C77: 0 | D77: 0 | E77: 0 | F77: 0 | G77: 0 | H77: 0 | I77: 0
A78: Vốn chủ sở hữu | B78: 1158767132623 | C78: 1279363319277 | D78: 1225129904764 | E78: 1679274238761 | F78: 2049335540169 | G78: 1719170578157 | H78: 2119813714328 | I78: 5139070693233
A79: Vốn và các quỹ | B79: 1158767132623 | C79: 1279363319277 | D79: 1225129904764 | E79: 1679274238761 | F79: 2049335540169 | G79: 1719170578157 | H79: 2119813714328 | I79: 5139070693233
A80: Vốn góp | B80: 680000000000 | C80: 789817920000 | D80: 789817920000 | E80: 789817920000 | F80: 1184725350000 | G80: 1362423890000 | H80: 1362423890000 | I80: 1703017850000
A81: Thặng dư vốn cổ phần | B81: 0 | C81: 0 | D81: 0 | E81: 0 | F81: 0 | G81: 0 | H81: 0 | I81: 0
A82: Vốn khác | B82: 0 | C82: 0 | D82: 0 | E82: 0 | F82: 0 | G82: 0 | H82: 0 | I82: 0
A83: Cổ phiếu quỹ | B83: 0 | C83: 0 | D83: 0 | E83: 0 | F83: 0 | G83: 0 | H83: 0 | I83: 0
A84: Chênh lệch đánh giá lại tài sản | B84: 0 | C84: 0 | D84: 0 | E84: 0 | F84: 0 | G84: 0 | H84: 0 | I84: 0
A85: Chênh lệch tỷ giá | B85: 0 | C85: 0 | D85: 0 | E85: 0 | F85: 0 | G85: 0 | H85: 0 | I85: 0
... A105: Chi phí sản xuất, kinh doanh dở dang dài hạn | B105: 0 | C105: 0 | D105: 0 | E105: 0 | F105: 0 | G105: 0 | H105: 0 | I105: 0
A106: Đầu tư nắm giữ đến ngày đáo hạn | F106: 0 | G106: 0 | H106: 0 | I106: 0
A107: Thiết bị, vật tư, phụ tùng thay thế dài hạn | B107: 0 | C107: 0 | D107: 0 | E107: 0 | F107: 0 | G107: 0 | H107: 0 | I107: 0
A108: Doanh thu chưa thực hiện ngắn hạn | B108: 0 | C108: 0 | D108: 0 | E108: 205650000 | F108: 322325273 | G108: 13605024822 | H108: 219923436590 | I108: 498506024698
A109: Quỹ bình ổn giá | B109: 0 | C109: 0 | D109: 0 | E109: 0 | F109: 0 | G109: 0 | H109: 0 | I109: 0
A110: Giao dịch mua bán lại trái phiếu chính phủ | B110: 0 | C110: 0 | D110: 0 | E110: 0 | F110: 0 | G110: 0 | H110: 0 | I110: 0
A111: Người mua trả tiền trước dài hạn | B111: 0 | C111: 0 | D111: 0 | E111: 0 | F111: 0 | G111: 0 | H111: 0 | I111: 0
A112: Chi phí phải trả dài hạn | B112: 0 | C112: 0 | D112: 0 | E112: 0 | F112: 0 | G112: 0 | H112: 0 | I112: 0
A113: Phải trả nội bộ về vốn kinh doanh | B113: 0 | C113: 0 | D113: 0 | E113: 0 | F113: 0 | G113: 0 | H113: 0 | I113: 0
A114: Trái phiếu chuyển đổi | B114: 0 | C114: 0 | D114: 0 | E114: 0 | F114: 0 | G114: 0 | H114: 0 | I114: 0
A115: Cổ phiếu ưu đãi | F115: 0 | G115: 0 | H115: 0 | I115: 0
A116: Cổ phiếu phổ thông | B116: 680000000000 | C116: 789817920000 | D116: 789817920000 | E116: 789817920000 | F116: 1184725350000 | G116: 1362423890000 | H116: 1362423890000 | I116: 1703017850000
A117: Quyền chọn chuyển đổi trái phiếu | B117: 0 | C117: 0 | D117: 0 | E117: 0 | F117: 0 | G117: 0 | H117: 0 | I117: 0
A118: LNST chưa phân phối lũy kế đến cuối kỳ trước | B118: 116454372696 | C118: 282085449452 | D118: 404926443124 | E118: 423908570033 | F118: 437992070152 | G118: 586570809094 | H118: 236975520956 | I118: 197121393961
A119: LNST chưa phân phối kỳ này | B119: 337328996757 | C119: 201822785671 | D119: 18982126909 | E119: 448481826119 | F119: 385513546442 | G119: -349738556772 | H119: 312410869201 | I119: 2271321456541
A120: Xây dựng cơ bản đang dở dang | B120: 0 | C120: 0 | D120: 0 | E120: 90909091 | F120: 1795608000 | G120: 770956800 | H120: 8230000000 | I120: 1411954000
A121: Lợi thế thương mại | B121: 0 | C121: 0 | D121: 0 | E121: 0 | F121: 0 | G121: 0 | H121: 0 | I121: 0
A122: Lợi ích cổ đông không kiểm soát | B122: 24983763170 | C122: 5637164154 | D122: 11403414731 | E122: 17065922609 | F122: 41104573575 | G122: 119914435835 | H122: 208003434171 | I122: 967609992731
A123: Nguồn kinh phí đã hình thành TSCĐ | B123: 0 | C123: 0 | D123: 0 | E123: 0 | F123: 0 | G123: 0 | H123: 0 | I123: 0

Sheet income_statement
A1: item | B1: 2018 | C1: 2019 | D1: 2020 | E1: 2021 | F1: 2022 | G1: 2023 | H1: 2024 | I1: 2025
A2: Doanh thu bán hàng và cung cấp dịch vụ | B2: 15889645872798 | C2: 16988956546078 | D2: 14799952534765 | E2: 22619505421050 | F2: 30276710796279 | G2: 31975613596365 | H2: 40241629282059 | I2: 51232049640567
A3: Các khoản giảm trừ doanh thu | B3: -591311306900 | C3: -354996798915 | D3: -138535502543 | E3: -124544012968 | F3: -110910039609 | G3: -125963979645 | H3: -137136750875 | I3: -149181195799
A4: Doanh thu thuần | B4: 15298334565898 | C4: 16633959747163 | D4: 14661417032222 | E4: 22494961408082 | F4: 30165800756670 | G4: 31849649616720 | H4: 40104492531184 | I4: 51082868444768
A5: Giá vốn hàng bán | B5: -13254725142547 | C5: -14522902581026 | D5: -12620414733505 | E5: -19343448146483 | F5: -25462623377413 | G5: -26688006159054 | H5: -32521431587237 | I5: -41073163986683
A6: Lợi nhuận gộp | B6: 2043609423351 | C6: 2111057166137 | D6: 2041002298717 | E6: 3151513261599 | F6: 4703177379257 | G6: 5161643457666 | H6: 7583060943947 | I6: 10009704458085
A7: Doanh thu hoạt động tài chính | B7: 42866217249 | C7: 78050133404 | D7: 70749420260 | E7: 197580982169 | F7: 173746497842 | G7: 80257624527 | H7: 106913298138 | I7: 287764741779
A8: Chi phí tài chính | B8: -100572817952 | C8: -147964791194 | D8: -133811898461 | E8: -146245489692 | F8: -256319530992 | G8: -292262559450 | H8: -253792623553 | I8: -388683187751
A9: Chi phí lãi vay | B9: -95670507863 | C9: -135183263352 | D9: -113682404790 | E9: -132229176761 | F9: -231527904809 | G9: -284917373606 | H9: -253428831252 | I9: -388595922369
A10: Chi phí bán hàng | B10: -1296274813568 | C10: -1419309973054 | D10: -1565736555190 | E10: -2071124789339 | F10: -3259297597681 | G10: -4169668799072 | H10: -5527210989725 | I10: -7018206246026
A11: Chi phí quản lý doanh nghiệp | B11: -286839549948 | C11: -349010009416 | D11: -397884049877 | E11: -585528444388 | F11: -887338884656 | G11: -1076478805719 | H11: -1365833850070 | I11: -1677744619772
A12: Lãi/(lỗ) từ hoạt động kinh doanh | B12: 402788459132 | C12: 272822525877 | D12: 14319215449 | E12: 546195520349 | F12: 473967863770 | G12: -296509082048 | H12: 543136778737 | I12: 1212835146315
A13: Thu nhập khác | B13: 34150544259 | C13: 5334005795 | D13: 14991747878 | E13: 9425637534 | F13: 16254109001 | G13: 22062244997 | H13: 24090237620 | I13: 29912692698
... A26: Lãi/(lỗ) từ công ty liên doanh (từ năm 2015) | B26: 0 | C26: 0 | D26: 0 | E26: 0 | F26: 0 | G26: 0 | H26: 0 | I26: 0

Sheet cash_flow
A1: item | B1: 2018 | C1: 2019 | D1: 2020 | E1: 2021 | F1: 2022 | G1: 2023 | H1: 2024 | I1: 2025
A2: Lợi nhuận/(lỗ) trước thuế | B2: 434775198367 | C2: 278002659252 | D2: 28427378490 | E2: 554140265577 | F2: 485623413969 | G2: -294181683290 | H2: 526957088186 | I2: 1219117502673
A3: Khấu hao TSCĐ và BĐSĐT | B3: 781002276 | C3: 836635952 | D3: 1372163399 | E3: 71537572161 | F3: 115286135177 | G3: 233071988505 | H3: 318442950010 | I3: 402557018224
A4: Chi phí dự phòng | B4: 14477629465 | C4: 18859508387 | D4: 34392956980 | E4: -31039107353 | F4: -4485565669 | G4: 2521192297 | H4: 17863960788 | I4: 32010999772
A5: Lãi/lỗ chênh lệch tỷ giá hối đoái do đánh giá lại các khoản mục tiền tệ có gốc ngoại tệ | B5: -2380950000 | C5: -1573500000 | D5: -75365966 | E5: 7513094690 | F5: -42532911 | G5: -74512931 | H5: -158409220 | I5: -20360895
A6: Lãi/(lỗ) từ thanh lý tài sản cố định | B6: 0 | C6: 0 | D6: 0 | E6: 0 | F6: 0 | G6: 0 | H6: 0 | I6: 0
A7: (Lãi)/lỗ từ hoạt động đầu tư | B7: -20946487598 | C7: -61193294228 | D7: -55870719645 | E7: -169344292160 | F7: -147853905457 | G7: -50019830875 | H7: -70652632259 | I7: -267669594473
A8: Chi phí lãi vay | B8: 95670507863 | C8: 135183263352 | D8: 113682404790 | E8: 132229176761 | F8: 231527904809 | G8: 284917373606 | H8: 253428831252 | I8: 388595922369
A9: Thu lãi và cổ tức | B9: 0 | C9: 0 | D9: 0 | E9: 0 | F9: 0 | G9: 0 | H9: 0 | I9: 0
A10: Lợi nhuận/(lỗ) từ hoạt động kinh doanh trước những thay đổi vốn lưu động | B10: 522376900373 | C10: 370115272715 | D10: 121928818048 | E10: 565036709676 | F10: 680055449918 | G10: 176234527312 | H10: 1045881788757 | I10: 1774591487670
A11: (Tăng)/giảm các khoản phải thu | B11: -60063346100 | C11: 131185574067 | D11: -79329822257 | E11: 88624032848 | F11: -93023120614 | G11: 27356978357 | H11: 136390770666 | I11: -289450397420
A12: (Tăng)/giảm hàng tồn kho | B12: -790234430865 | C12: -879508612026 | D12: 1545958217975 | E12: -3122839624668 | F12: -1549588422248 | G12: -1944517235201 | H12: -1821393826979 | I12: -1721131354627
A13: Tăng/(giảm) các khoản phải trả | B13: -849889822830 | C13: 554572458872 | D13: 65446926710 | E13: 1387811818622 | F13: 36245882912 | G13: 175960973788 | H13: 1535573066662 | I13: 3488987404115
... A42: (Tăng)/giảm chứng khoán kinh doanh | B42: 0 | C42: 0 | D42: 0 | E42: 0 | F42: 0 | G42: 0 | H42: 0 | I42: 0

Sheet chi_so_tai_chinh
A1: Chỉ tiêu | B1: =balance_sheet!B1 | C1: =balance_sheet!C1 | D1: =balance_sheet!D1 | E1: =balance_sheet!E1 | F1: =balance_sheet!F1 | G1: =balance_sheet!G1 | H1: =balance_sheet!H1 | I1: =balance_sheet!I1 | J1: 2026
A2: ROE (LNST CĐ Cty mẹ / VCSH bình quân) | B2: n/a | C2: =IFERROR(C$52/((C$39+B$39)/2),"n/a") | D2: =IFERROR(D$52/((D$39+C$39)/2),"n/a") | E2: =IFERROR(E$52/((E$39+D$39)/2),"n/a") | F2: =IFERROR(F$52/((F$39+E$39)/2),"n/a") | G2: =IFERROR(G$52/((G$39+F$39)/2),"n/a") | H2: =IFERROR(H$52/((H$39+G$39)/2),"n/a") | I2: =IFERROR(I$52/((I$39+H$39)/2),"n/a")
A3: ROA (LNST / Tổng tài sản bình quân) | B3: n/a | C3: =IFERROR(C$51/((C$31+B$31)/2),"n/a") | D3: =IFERROR(D$51/((D$31+C$31)/2),"n/a") | E3: =IFERROR(E$51/((E$31+D$31)/2),"n/a") | F3: =IFERROR(F$51/((F$31+E$31)/2),"n/a") | G3: =IFERROR(G$51/((G$31+F$31)/2),"n/a") | H3: =IFERROR(H$51/((H$31+G$31)/2),"n/a") | I3: =IFERROR(I$51/((I$31+H$31)/2),"n/a")
A4: Tăng trưởng LN Cổ đông Cty mẹ | B4: n/a | C4: =IFERROR((C$52-B$52)/ABS(B$52),"n/a") | D4: =IFERROR((D$52-C$52)/ABS(C$52),"n/a") | E4: =IFERROR((E$52-D$52)/ABS(D$52),"n/a") | F4: =IFERROR((F$52-E$52)/ABS(E$52),"n/a") | G4: =IFERROR((G$52-F$52)/ABS(F$52),"n/a") | H4: =IFERROR((H$52-G$52)/ABS(G$52),"n/a") | I4: =IFERROR((I$52-H$52)/ABS(H$52),"n/a") | J4: =IFERROR((J$52-I$52)/ABS(I$52),"n/a")
A5: Tăng trưởng Doanh thu thuần | B5: n/a | C5: =IFERROR((C$43-B$43)/ABS(B$43),"n/a") | D5: =IFERROR((D$43-C$43)/ABS(C$43),"n/a") | E5: =IFERROR((E$43-D$43)/ABS(D$43),"n/a") | F5: =IFERROR((F$43-E$43)/ABS(E$43),"n/a") | G5: =IFERROR((G$43-F$43)/ABS(F$43),"n/a") | H5: =IFERROR((H$43-G$43)/ABS(G$43),"n/a") | I5: =IFERROR((I$43-H$43)/ABS(H$43),"n/a") | J5: =IFERROR((J$43-I$43)/ABS(I$43),"n/a")
A6: Biên lợi nhuận gộp | B6: =IFERROR(B$45/B$43,"n/a") | C6: =IFERROR(C$45/C$43,"n/a") | D6: =IFERROR(D$45/D$43,"n/a") | E6: =IFERROR(E$45/E$43,"n/a") | F6: =IFERROR(F$45/F$43,"n/a") | G6: =IFERROR(G$45/G$43,"n/a") | H6: =IFERROR(H$45/H$43,"n/a") | I6: =IFERROR(I$45/I$43,"n/a")
A7: Biên lợi nhuận ròng | B7: =IFERROR(B$52/B$43,"n/a") | C7: =IFERROR(C$52/C$43,"n/a") | D7: =IFERROR(D$52/D$43,"n/a") | E7: =IFERROR(E$52/E$43,"n/a") | F7: =IFERROR(F$52/F$43,"n/a") | G7: =IFERROR(G$52/G$43,"n/a") | H7: =IFERROR(H$52/H$43,"n/a") | I7: =IFERROR(I$52/I$43,"n/a") | J7: =IFERROR(J$52/J$43,"n/a")
A8: D/E (Nợ vay / Vốn chủ sở hữu) | B8: =IFERROR((B$34+B$36)/B$39,"n/a") | C8: =IFERROR((C$34+C$36)/C$39,"n/a") | D8: =IFERROR((D$34+D$36)/D$39,"n/a") | E8: =IFERROR((E$34+E$36)/E$39,"n/a") | F8: =IFERROR((F$34+F$36)/F$39,"n/a") | G8: =IFERROR((G$34+G$36)/G$39,"n/a") | H8: =IFERROR((H$34+H$36)/H$39,"n/a") | I8: =IFERROR((I$34+I$36)/I$39,"n/a")
A9: - Nợ vay dài hạn/Vốn chủ sở hữu | B9: =IFERROR(B$36/B$39,"n/a") | C9: =IFERROR(C$36/C$39,"n/a") | D9: =IFERROR(D$36/D$39,"n/a") | E9: =IFERROR(E$36/E$39,"n/a") | F9: =IFERROR(F$36/F$39,"n/a") | G9: =IFERROR(G$36/G$39,"n/a") | H9: =IFERROR(H$36/H$39,"n/a") | I9: =IFERROR(I$36/I$39,"n/a")
A10: - Nợ vay ngắn hạn/Vốn chủ sở hữu | B10: =IFERROR(B$34/B$39,"n/a") | C10: =IFERROR(C$34/C$39,"n/a") | D10: =IFERROR(D$34/D$39,"n/a") | E10: =IFERROR(E$34/E$39,"n/a") | F10: =IFERROR(F$34/F$39,"n/a") | G10: =IFERROR(G$34/G$39,"n/a") | H10: =IFERROR(H$34/H$39,"n/a") | I10: =IFERROR(I$34/I$39,"n/a")
A11: Nợ phải trả/Vốn chủ sở hữu | B11: =IFERROR(B$38/B$39,"n/a") | C11: =IFERROR(C$38/C$39,"n/a") | D11: =IFERROR(D$38/D$39,"n/a") | E11: =IFERROR(E$38/E$39,"n/a") | F11: =IFERROR(F$38/F$39,"n/a") | G11: =IFERROR(G$38/G$39,"n/a") | H11: =IFERROR(H$38/H$39,"n/a") | I11: =IFERROR(I$38/I$39,"n/a")
A12: - Nợ dài hạn/Vốn chủ sở hữu | B12: =IFERROR(B$37/B$39,"n/a") | C12: =IFERROR(C$37/C$39,"n/a") | D12: =IFERROR(D$37/D$39,"n/a") | E12: =IFERROR(E$37/E$39,"n/a") | F12: =IFERROR(F$37/F$39,"n/a") | G12: =IFERROR(G$37/G$39,"n/a") | H12: =IFERROR(H$37/H$39,"n/a") | I12: =IFERROR(I$37/I$39,"n/a")
A13: - Nợ ngắn hạn/Vốn chủ sở hữu | B13: =IFERROR(B$35/B$39,"n/a") | C13: =IFERROR(C$35/C$39,"n/a") | D13: =IFERROR(D$35/D$39,"n/a") | E13: =IFERROR(E$35/E$39,"n/a") | F13: =IFERROR(F$35/F$39,"n/a") | G13: =IFERROR(G$35/G$39,"n/a") | H13: =IFERROR(H$35/H$39,"n/a") | I13: =IFERROR(I$35/I$39,"n/a")
A14: Chi phí bán hàng, quản lý/LN gộp | B14: =IFERROR((ABS(B$46)+ABS(B$47))/B$45,"n/a") | C14: =IFERROR((ABS(C$46)+ABS(C$47))/C$45,"n/a") | D14: =IFERROR((ABS(D$46)+ABS(D$47))/D$45,"n/a") | E14: =IFERROR((ABS(E$46)+ABS(E$47))/E$45,"n/a") | F14: =IFERROR((ABS(F$46)+ABS(F$47))/F$45,"n/a") | G14: =IFERROR((ABS(G$46)+ABS(G$47))/G$45,"n/a") | H14: =IFERROR((ABS(H$46)+ABS(H$47))/H$45,"n/a") | I14: =IFERROR((ABS(I$46)+ABS(I$47))/I$45,"n/a")
A15: Chi phí lãi vay/LN từ hoạt động kinh doanh | B15: =IFERROR(ABS(B$49)/B$48,"n/a") | C15: =IFERROR(ABS(C$49)/C$48,"n/a") | D15: =IFERROR(ABS(D$49)/D$48,"n/a") | E15: =IFERROR(ABS(E$49)/E$48,"n/a") | F15: =IFERROR(ABS(F$49)/F$48,"n/a") | G15: =IFERROR(ABS(G$49)/G$48,"n/a") | H15: =IFERROR(ABS(H$49)/H$48,"n/a") | I15: =IFERROR(ABS(I$49)/I$48,"n/a")
A16: Số ngày phải trả (DPO) | B16: n/a | C16: =IFERROR(((C$33+B$33)/2)/ABS(C$44)*365,"n/a") | D16: =IFERROR(((D$33+C$33)/2)/ABS(D$44)*365,"n/a") | E16: =IFERROR(((E$33+D$33)/2)/ABS(E$44)*365,"n/a") | F16: =IFERROR(((F$33+E$33)/2)/ABS(F$44)*365,"n/a") | G16: =IFERROR(((G$33+F$33)/2)/ABS(G$44)*365,"n/a") | H16: =IFERROR(((H$33+G$33)/2)/ABS(H$44)*365,"n/a") | I16: =IFERROR(((I$33+H$33)/2)/ABS(I$44)*365,"n/a")
A17: Số ngày phải thu (DSO) | B17: n/a | C17: =IFERROR(((C$27+B$27)/2)/C$43*365,"n/a") | D17: =IFERROR(((D$27+C$27)/2)/D$43*365,"n/a") | E17: =IFERROR(((E$27+D$27)/2)/E$43*365,"n/a") | F17: =IFERROR(((F$27+E$27)/2)/F$43*365,"n/a") | G17: =IFERROR(((G$27+F$27)/2)/G$43*365,"n/a") | H17: =IFERROR(((H$27+G$27)/2)/H$43*365,"n/a") | I17: =IFERROR(((I$27+H$27)/2)/I$43*365,"n/a")
A18: Số ngày tồn kho (DIO) | B18: n/a | C18: =IFERROR(((C$28+B$28)/2)/ABS(C$44)*365,"n/a") | D18: =IFERROR(((D$28+C$28)/2)/ABS(D$44)*365,"n/a") | E18: =IFERROR(((E$28+D$28)/2)/ABS(E$44)*365,"n/a") | F18: =IFERROR(((F$28+E$28)/2)/ABS(F$44)*365,"n/a") | G18: =IFERROR(((G$28+F$28)/2)/ABS(G$44)*365,"n/a") | H18: =IFERROR(((H$28+G$28)/2)/ABS(H$44)*365,"n/a") | I18: =IFERROR(((I$28+H$28)/2)/ABS(I$44)*365,"n/a")
A19: Tiền và tương đương tiền/Tài sản | B19: =IFERROR(B$26/B$31,"n/a") | C19: =IFERROR(C$26/C$31,"n/a") | D19: =IFERROR(D$26/D$31,"n/a") | E19: =IFERROR(E$26/E$31,"n/a") | F19: =IFERROR(F$26/F$31,"n/a") | G19: =IFERROR(G$26/G$31,"n/a") | H19: =IFERROR(H$26/H$31,"n/a") | I19: =IFERROR(I$26/I$31,"n/a")
A20: Hàng tồn kho/Tài sản | B20: =IFERROR(B$28/B$31,"n/a") | C20: =IFERROR(C$28/C$31,"n/a") | D20: =IFERROR(D$28/D$31,"n/a") | E20: =IFERROR(E$28/E$31,"n/a") | F20: =IFERROR(F$28/F$31,"n/a") | G20: =IFERROR(G$28/G$31,"n/a") | H20: =IFERROR(H$28/H$31,"n/a") | I20: =IFERROR(I$28/I$31,"n/a")
A22: II. DỮ LIỆU TRÍCH XUẤT (tự động dò theo tên khoản mục)
A23: Khoản mục | B23: =balance_sheet!B1 | C23: =balance_sheet!C1 | D23: =balance_sheet!D1 | E23: =balance_sheet!E1 | F23: =balance_sheet!F1 | G23: =balance_sheet!G1 | H23: =balance_sheet!H1 | I23: =balance_sheet!I1
A24: CĐKT
A25: Tài sản
A26: Tiền và tương đương tiền | B26: =IFERROR(INDEX(balance_sheet!$B:$I,MATCH("Tiền và tương đương tiền",balance_sheet!$A:$A,0),MATCH(B$23,balance_sheet!$B$1:$I$1,0)),"") | C26: =IFERROR(INDEX(balance_sheet!$B:$I,MATCH("Tiền và tương đương tiền",balance_sheet!$A:$A,0),MATCH(C$23,balance_sheet!$B$1:$I$1,0)),"") | D26: =IFERROR(INDEX(balance_sheet!$B:$I,MATCH("Tiền và tương đương tiền",balance_sheet!$A:$A,0),MATCH(D$23,balance_sheet!$B$1:$I$1,0)),"") | E26: =IFERROR(INDEX(balance_sheet!$B:$I,MATCH("Tiền và tương đương tiền",balance_sheet!$A:$A,0),MATCH(E$23,balance_sheet!$B$1:$I$1,0)),"") | F26: =IFERROR(INDEX(balance_sheet!$B:$I,MATCH("Tiền và tương đương tiền",balance_sheet!$A:$A,0),MATCH(F$23,balance_sheet!$B$1:$I$1,0)),"") | G26: =IFERROR(INDEX(balance_sheet!$B:$I,MATCH("Tiền và tương đương tiền",balance_sheet!$A:$A,0),MATCH(G$23,balance_sheet!$B$1:$I$1,0)),"") | H26: =IFERROR(INDEX(balance_sheet!$B:$I,MATCH("Tiền và tương đương tiền",balance_sheet!$A:$A,0),MATCH(H$23,balance_sheet!$B$1:$I$1,0)),"") | I26: =IFERROR(INDEX(balance_sheet!$B:$I,MATCH("Tiền và tương đương tiền",balance_sheet!$A:$A,0),MATCH(I$23,balance_sheet!$B$1:$I$1,0)),"")
A27: Phải thu khách hàng | B27: =IFERROR(INDEX(balance_sheet!$B:$I,MATCH("Phải thu khách hàng",balance_sheet!$A:$A,0),MATCH(B$23,balance_sheet!$B$1:$I$1,0)),"") | C27: =IFERROR(INDEX(balance_sheet!$B:$I,MATCH("Phải thu khách hàng",balance_sheet!$A:$A,0),MATCH(C$23,balance_sheet!$B$1:$I$1,0)),"") | D27: =IFERROR(INDEX(balance_sheet!$B:$I,MATCH("Phải thu khách hàng",balance_sheet!$A:$A,0),MATCH(D$23,balance_sheet!$B$1:$I$1,0)),"") | E27: =IFERROR(INDEX(balance_sheet!$B:$I,MATCH("Phải thu khách hàng",balance_sheet!$A:$A,0),MATCH(E$23,balance_sheet!$B$1:$I$1,0)),"") | F27: =IFERROR(INDEX(balance_sheet!$B:$I,MATCH("Phải thu khách hàng",balance_sheet!$A:$A,0),MATCH(F$23,balance_sheet!$B$1:$I$1,0)),"") | G27: =IFERROR(INDEX(balance_sheet!$B:$I,MATCH("Phải thu khách hàng",balance_sheet!$A:$A,0),MATCH(G$23,balance_sheet!$B$1:$I$1,0)),"") | H27: =IFERROR(INDEX(balance_sheet!$B:$I,MATCH("Phải thu khách hàng",balance_sheet!$A:$A,0),MATCH(H$23,balance_sheet!$B$1:$I$1,0)),"") | I27: =IFERROR(INDEX(balance_sheet!$B:$I,MATCH("Phải thu khách hàng",balance_sheet!$A:$A,0),MATCH(I$23,balance_sheet!$B$1:$I$1,0)),"")
A28: Hàng tồn kho, ròng | B28: =IFERROR(INDEX(balance_sheet!$B:$I,MATCH("Hàng tồn kho, ròng",balance_sheet!$A:$A,0),MATCH(B$23,balance_sheet!$B$1:$I$1,0)),"") | C28: =IFERROR(INDEX(balance_sheet!$B:$I,MATCH("Hàng tồn kho, ròng",balance_sheet!$A:$A,0),MATCH(C$23,balance_sheet!$B$1:$I$1,0)),"") | D28: =IFERROR(INDEX(balance_sheet!$B:$I,MATCH("Hàng tồn kho, ròng",balance_sheet!$A:$A,0),MATCH(D$23,balance_sheet!$B$1:$I$1,0)),"") | E28: =IFERROR(INDEX(balance_sheet!$B:$I,MATCH("Hàng tồn kho, ròng",balance_sheet!$A:$A,0),MATCH(E$23,balance_sheet!$B$1:$I$1,0)),"") | F28: =IFERROR(INDEX(balance_sheet!$B:$I,MATCH("Hàng tồn kho, ròng",balance_sheet!$A:$A,0),MATCH(F$23,balance_sheet!$B$1:$I$1,0)),"") | G28: =IFERROR(INDEX(balance_sheet!$B:$I,MATCH("Hàng tồn kho, ròng",balance_sheet!$A:$A,0),MATCH(G$23,balance_sheet!$B$1:$I$1,0)),"") | H28: =IFERROR(INDEX(balance_sheet!$B:$I,MATCH("Hàng tồn kho, ròng",balance_sheet!$A:$A,0),MATCH(H$23,balance_sheet!$B$1:$I$1,0)),"") | I28: =IFERROR(INDEX(balance_sheet!$B:$I,MATCH("Hàng tồn kho, ròng",balance_sheet!$A:$A,0),MATCH(I$23,balance_sheet!$B$1:$I$1,0)),"")
A29: TÀI SẢN NGẮN HẠN | B29: =IFERROR(INDEX(balance_sheet!$B:$I,MATCH("TÀI SẢN NGẮN HẠN",balance_sheet!$A:$A,0),MATCH(B$23,balance_sheet!$B$1:$I$1,0)),"") | C29: =IFERROR(INDEX(balance_sheet!$B:$I,MATCH("TÀI SẢN NGẮN HẠN",balance_sheet!$A:$A,0),MATCH(C$23,balance_sheet!$B$1:$I$1,0)),"") | D29: =IFERROR(INDEX(balance_sheet!$B:$I,MATCH("TÀI SẢN NGẮN HẠN",balance_sheet!$A:$A,0),MATCH(D$23,balance_sheet!$B$1:$I$1,0)),"") | E29: =IFERROR(INDEX(balance_sheet!$B:$I,MATCH("TÀI SẢN NGẮN HẠN",balance_sheet!$A:$A,0),MATCH(E$23,balance_sheet!$B$1:$I$1,0)),"") | F29: =IFERROR(INDEX(balance_sheet!$B:$I,MATCH("TÀI SẢN NGẮN HẠN",balance_sheet!$A:$A,0),MATCH(F$23,balance_sheet!$B$1:$I$1,0)),"") | G29: =IFERROR(INDEX(balance_sheet!$B:$I,MATCH("TÀI SẢN NGẮN HẠN",balance_sheet!$A:$A,0),MATCH(G$23,balance_sheet!$B$1:$I$1,0)),"") | H29: =IFERROR(INDEX(balance_sheet!$B:$I,MATCH("TÀI SẢN NGẮN HẠN",balance_sheet!$A:$A,0),MATCH(H$23,balance_sheet!$B$1:$I$1,0)),"") | I29: =IFERROR(INDEX(balance_sheet!$B:$I,MATCH("TÀI SẢN NGẮN HẠN",balance_sheet!$A:$A,0),MATCH(I$23,balance_sheet!$B$1:$I$1,0)),"")
A30: GTCL tài sản cố định vô hình | B30: =IFERROR(INDEX(balance_sheet!$B:$I,MATCH("GTCL tài sản cố định vô hình",balance_sheet!$A:$A,0),MATCH(B$23,balance_sheet!$B$1:$I$1,0)),"") | C30: =IFERROR(INDEX(balance_sheet!$B:$I,MATCH("GTCL tài sản cố định vô hình",balance_sheet!$A:$A,0),MATCH(C$23,balance_sheet!$B$1:$I$1,0)),"") | D30: =IFERROR(INDEX(balance_sheet!$B:$I,MATCH("GTCL tài sản cố định vô hình",balance_sheet!$A:$A,0),MATCH(D$23,balance_sheet!$B$1:$I$1,0)),"") | E30: =IFERROR(INDEX(balance_sheet!$B:$I,MATCH("GTCL tài sản cố định vô hình",balance_sheet!$A:$A,0),MATCH(E$23,balance_sheet!$B$1:$I$1,0)),"") | F30: =IFERROR(INDEX(balance_sheet!$B:$I,MATCH("GTCL tài sản cố định vô hình",balance_sheet!$A:$A,0),MATCH(F$23,balance_sheet!$B$1:$I$1,0)),"") | G30: =IFERROR(INDEX(balance_sheet!$B:$I,MATCH("GTCL tài sản cố định vô hình",balance_sheet!$A:$A,0),MATCH(G$23,balance_sheet!$B$1:$I$1,0)),"") | H30: =IFERROR(INDEX(balance_sheet!$B:$I,MATCH("GTCL tài sản cố định vô hình",balance_sheet!$A:$A,0),MATCH(H$23,balance_sheet!$B$1:$I$1,0)),"") | I30: =IFERROR(INDEX(balance_sheet!$B:$I,MATCH("GTCL tài sản cố định vô hình",balance_sheet!$A:$A,0),MATCH(I$23,balance_sheet!$B$1:$I$1,0)),"")
A31: TỔNG CỘNG TÀI SẢN | B31: =IFERROR(INDEX(balance_sheet!$B:$I,MATCH("TỔNG CỘNG TÀI SẢN",balance_sheet!$A:$A,0),MATCH(B$23,balance_sheet!$B$1:$I$1,0)),"") | C31: =IFERROR(INDEX(balance_sheet!$B:$I,MATCH("TỔNG CỘNG TÀI SẢN",balance_sheet!$A:$A,0),MATCH(C$23,balance_sheet!$B$1:$I$1,0)),"") | D31: =IFERROR(INDEX(balance_sheet!$B:$I,MATCH("TỔNG CỘNG TÀI SẢN",balance_sheet!$A:$A,0),MATCH(D$23,balance_sheet!$B$1:$I$1,0)),"") | E31: =IFERROR(INDEX(balance_sheet!$B:$I,MATCH("TỔNG CỘNG TÀI SẢN",balance_sheet!$A:$A,0),MATCH(E$23,balance_sheet!$B$1:$I$1,0)),"") | F31: =IFERROR(INDEX(balance_sheet!$B:$I,MATCH("TỔNG CỘNG TÀI SẢN",balance_sheet!$A:$A,0),MATCH(F$23,balance_sheet!$B$1:$I$1,0)),"") | G31: =IFERROR(INDEX(balance_sheet!$B:$I,MATCH("TỔNG CỘNG TÀI SẢN",balance_sheet!$A:$A,0),MATCH(G$23,balance_sheet!$B$1:$I$1,0)),"") | H31: =IFERROR(INDEX(balance_sheet!$B:$I,MATCH("TỔNG CỘNG TÀI SẢN",balance_sheet!$A:$A,0),MATCH(H$23,balance_sheet!$B$1:$I$1,0)),"") | I31: =IFERROR(INDEX(balance_sheet!$B:$I,MATCH("TỔNG CỘNG TÀI SẢN",balance_sheet!$A:$A,0),MATCH(I$23,balance_sheet!$B$1:$I$1,0)),"")
A32: Nguồn vốn
A33: Phải trả người bán | B33: =IFERROR(INDEX(balance_sheet!$B:$I,MATCH("Phải trả người bán",balance_sheet!$A:$A,0),MATCH(B$23,balance_sheet!$B$1:$I$1,0)),"") | C33: =IFERROR(INDEX(balance_sheet!$B:$I,MATCH("Phải trả người bán",balance_sheet!$A:$A,0),MATCH(C$23,balance_sheet!$B$1:$I$1,0)),"") | D33: =IFERROR(INDEX(balance_sheet!$B:$I,MATCH("Phải trả người bán",balance_sheet!$A:$A,0),MATCH(D$23,balance_sheet!$B$1:$I$1,0)),"") | E33: =IFERROR(INDEX(balance_sheet!$B:$I,MATCH("Phải trả người bán",balance_sheet!$A:$A,0),MATCH(E$23,balance_sheet!$B$1:$I$1,0)),"") | F33: =IFERROR(INDEX(balance_sheet!$B:$I,MATCH("Phải trả người bán",balance_sheet!$A:$A,0),MATCH(F$23,balance_sheet!$B$1:$I$1,0)),"") | G33: =IFERROR(INDEX(balance_sheet!$B:$I,MATCH("Phải trả người bán",balance_sheet!$A:$A,0),MATCH(G$23,balance_sheet!$B$1:$I$1,0)),"") | H33: =IFERROR(INDEX(balance_sheet!$B:$I,MATCH("Phải trả người bán",balance_sheet!$A:$A,0),MATCH(H$23,balance_sheet!$B$1:$I$1,0)),"") | I33: =IFERROR(INDEX(balance_sheet!$B:$I,MATCH("Phải trả người bán",balance_sheet!$A:$A,0),MATCH(I$23,balance_sheet!$B$1:$I$1,0)),"")
A34: Vay ngắn hạn | B34: =IFERROR(INDEX(balance_sheet!$B:$I,MATCH("Vay ngắn hạn",balance_sheet!$A:$A,0),MATCH(B$23,balance_sheet!$B$1:$I$1,0)),"") | C34: =IFERROR(INDEX(balance_sheet!$B:$I,MATCH("Vay ngắn hạn",balance_sheet!$A:$A,0),MATCH(C$23,balance_sheet!$B$1:$I$1,0)),"") | D34: =IFERROR(INDEX(balance_sheet!$B:$I,MATCH("Vay ngắn hạn",balance_sheet!$A:$A,0),MATCH(D$23,balance_sheet!$B$1:$I$1,0)),"") | E34: =IFERROR(INDEX(balance_sheet!$B:$I,MATCH("Vay ngắn hạn",balance_sheet!$A:$A,0),MATCH(E$23,balance_sheet!$B$1:$I$1,0)),"") | F34: =IFERROR(INDEX(balance_sheet!$B:$I,MATCH("Vay ngắn hạn",balance_sheet!$A:$A,0),MATCH(F$23,balance_sheet!$B$1:$I$1,0)),"") | G34: =IFERROR(INDEX(balance_sheet!$B:$I,MATCH("Vay ngắn hạn",balance_sheet!$A:$A,0),MATCH(G$23,balance_sheet!$B$1:$I$1,0)),"") | H34: =IFERROR(INDEX(balance_sheet!$B:$I,MATCH("Vay ngắn hạn",balance_sheet!$A:$A,0),MATCH(H$23,balance_sheet!$B$1:$I$1,0)),"") | I34: =IFERROR(INDEX(balance_sheet!$B:$I,MATCH("Vay ngắn hạn",balance_sheet!$A:$A,0),MATCH(I$23,balance_sheet!$B$1:$I$1,0)),"")
A35: Nợ ngắn hạn | B35: =IFERROR(INDEX(balance_sheet!$B:$I,MATCH("Nợ ngắn hạn",balance_sheet!$A:$A,0),MATCH(B$23,balance_sheet!$B$1:$I$1,0)),"") | C35: =IFERROR(INDEX(balance_sheet!$B:$I,MATCH("Nợ ngắn hạn",balance_sheet!$A:$A,0),MATCH(C$23,balance_sheet!$B$1:$I$1,0)),"") | D35: =IFERROR(INDEX(balance_sheet!$B:$I,MATCH("Nợ ngắn hạn",balance_sheet!$A:$A,0),MATCH(D$23,balance_sheet!$B$1:$I$1,0)),"") | E35: =IFERROR(INDEX(balance_sheet!$B:$I,MATCH("Nợ ngắn hạn",balance_sheet!$A:$A,0),MATCH(E$23,balance_sheet!$B$1:$I$1,0)),"") | F35: =IFERROR(INDEX(balance_sheet!$B:$I,MATCH("Nợ ngắn hạn",balance_sheet!$A:$A,0),MATCH(F$23,balance_sheet!$B$1:$I$1,0)),"") | G35: =IFERROR(INDEX(balance_sheet!$B:$I,MATCH("Nợ ngắn hạn",balance_sheet!$A:$A,0),MATCH(G$23,balance_sheet!$B$1:$I$1,0)),"") | H35: =IFERROR(INDEX(balance_sheet!$B:$I,MATCH("Nợ ngắn hạn",balance_sheet!$A:$A,0),MATCH(H$23,balance_sheet!$B$1:$I$1,0)),"") | I35: =IFERROR(INDEX(balance_sheet!$B:$I,MATCH("Nợ ngắn hạn",balance_sheet!$A:$A,0),MATCH(I$23,balance_sheet!$B$1:$I$1,0)),"")
A36: Vay dài hạn | B36: =IFERROR(INDEX(balance_sheet!$B:$I,MATCH("Vay dài hạn",balance_sheet!$A:$A,0),MATCH(B$23,balance_sheet!$B$1:$I$1,0)),"") | C36: =IFERROR(INDEX(balance_sheet!$B:$I,MATCH("Vay dài hạn",balance_sheet!$A:$A,0),MATCH(C$23,balance_sheet!$B$1:$I$1,0)),"") | D36: =IFERROR(INDEX(balance_sheet!$B:$I,MATCH("Vay dài hạn",balance_sheet!$A:$A,0),MATCH(D$23,balance_sheet!$B$1:$I$1,0)),"") | E36: =IFERROR(INDEX(balance_sheet!$B:$I,MATCH("Vay dài hạn",balance_sheet!$A:$A,0),MATCH(E$23,balance_sheet!$B$1:$I$1,0)),"") | F36: =IFERROR(INDEX(balance_sheet!$B:$I,MATCH("Vay dài hạn",balance_sheet!$A:$A,0),MATCH(F$23,balance_sheet!$B$1:$I$1,0)),"") | G36: =IFERROR(INDEX(balance_sheet!$B:$I,MATCH("Vay dài hạn",balance_sheet!$A:$A,0),MATCH(G$23,balance_sheet!$B$1:$I$1,0)),"") | H36: =IFERROR(INDEX(balance_sheet!$B:$I,MATCH("Vay dài hạn",balance_sheet!$A:$A,0),MATCH(H$23,balance_sheet!$B$1:$I$1,0)),"") | I36: =IFERROR(INDEX(balance_sheet!$B:$I,MATCH("Vay dài hạn",balance_sheet!$A:$A,0),MATCH(I$23,balance_sheet!$B$1:$I$1,0)),"")
A37: Nợ dài hạn | B37: =IFERROR(INDEX(balance_sheet!$B:$I,MATCH("Nợ dài hạn",balance_sheet!$A:$A,0),MATCH(B$23,balance_sheet!$B$1:$I$1,0)),"") | C37: =IFERROR(INDEX(balance_sheet!$B:$I,MATCH("Nợ dài hạn",balance_sheet!$A:$A,0),MATCH(C$23,balance_sheet!$B$1:$I$1,0)),"") | D37: =IFERROR(INDEX(balance_sheet!$B:$I,MATCH("Nợ dài hạn",balance_sheet!$A:$A,0),MATCH(D$23,balance_sheet!$B$1:$I$1,0)),"") | E37: =IFERROR(INDEX(balance_sheet!$B:$I,MATCH("Nợ dài hạn",balance_sheet!$A:$A,0),MATCH(E$23,balance_sheet!$B$1:$I$1,0)),"") | F37: =IFERROR(INDEX(balance_sheet!$B:$I,MATCH("Nợ dài hạn",balance_sheet!$A:$A,0),MATCH(F$23,balance_sheet!$B$1:$I$1,0)),"") | G37: =IFERROR(INDEX(balance_sheet!$B:$I,MATCH("Nợ dài hạn",balance_sheet!$A:$A,0),MATCH(G$23,balance_sheet!$B$1:$I$1,0)),"") | H37: =IFERROR(INDEX(balance_sheet!$B:$I,MATCH("Nợ dài hạn",balance_sheet!$A:$A,0),MATCH(H$23,balance_sheet!$B$1:$I$1,0)),"") | I37: =IFERROR(INDEX(balance_sheet!$B:$I,MATCH("Nợ dài hạn",balance_sheet!$A:$A,0),MATCH(I$23,balance_sheet!$B$1:$I$1,0)),"")
A38: NỢ PHẢI TRẢ | B38: =IFERROR(INDEX(balance_sheet!$B:$I,MATCH("NỢ PHẢI TRẢ",balance_sheet!$A:$A,0),MATCH(B$23,balance_sheet!$B$1:$I$1,0)),"") | C38: =IFERROR(INDEX(balance_sheet!$B:$I,MATCH("NỢ PHẢI TRẢ",balance_sheet!$A:$A,0),MATCH(C$23,balance_sheet!$B$1:$I$1,0)),"") | D38: =IFERROR(INDEX(balance_sheet!$B:$I,MATCH("NỢ PHẢI TRẢ",balance_sheet!$A:$A,0),MATCH(D$23,balance_sheet!$B$1:$I$1,0)),"") | E38: =IFERROR(INDEX(balance_sheet!$B:$I,MATCH("NỢ PHẢI TRẢ",balance_sheet!$A:$A,0),MATCH(E$23,balance_sheet!$B$1:$I$1,0)),"") | F38: =IFERROR(INDEX(balance_sheet!$B:$I,MATCH("NỢ PHẢI TRẢ",balance_sheet!$A:$A,0),MATCH(F$23,balance_sheet!$B$1:$I$1,0)),"") | G38: =IFERROR(INDEX(balance_sheet!$B:$I,MATCH("NỢ PHẢI TRẢ",balance_sheet!$A:$A,0),MATCH(G$23,balance_sheet!$B$1:$I$1,0)),"") | H38: =IFERROR(INDEX(balance_sheet!$B:$I,MATCH("NỢ PHẢI TRẢ",balance_sheet!$A:$A,0),MATCH(H$23,balance_sheet!$B$1:$I$1,0)),"") | I38: =IFERROR(INDEX(balance_sheet!$B:$I,MATCH("NỢ PHẢI TRẢ",balance_sheet!$A:$A,0),MATCH(I$23,balance_sheet!$B$1:$I$1,0)),"")
A39: Vốn chủ sở hữu | B39: =IFERROR(INDEX(balance_sheet!$B:$I,MATCH("Vốn chủ sở hữu",balance_sheet!$A:$A,0),MATCH(B$23,balance_sheet!$B$1:$I$1,0)),"") | C39: =IFERROR(INDEX(balance_sheet!$B:$I,MATCH("Vốn chủ sở hữu",balance_sheet!$A:$A,0),MATCH(C$23,balance_sheet!$B$1:$I$1,0)),"") | D39: =IFERROR(INDEX(balance_sheet!$B:$I,MATCH("Vốn chủ sở hữu",balance_sheet!$A:$A,0),MATCH(D$23,balance_sheet!$B$1:$I$1,0)),"") | E39: =IFERROR(INDEX(balance_sheet!$B:$I,MATCH("Vốn chủ sở hữu",balance_sheet!$A:$A,0),MATCH(E$23,balance_sheet!$B$1:$I$1,0)),"") | F39: =IFERROR(INDEX(balance_sheet!$B:$I,MATCH("Vốn chủ sở hữu",balance_sheet!$A:$A,0),MATCH(F$23,balance_sheet!$B$1:$I$1,0)),"") | G39: =IFERROR(INDEX(balance_sheet!$B:$I,MATCH("Vốn chủ sở hữu",balance_sheet!$A:$A,0),MATCH(G$23,balance_sheet!$B$1:$I$1,0)),"") | H39: =IFERROR(INDEX(balance_sheet!$B:$I,MATCH("Vốn chủ sở hữu",balance_sheet!$A:$A,0),MATCH(H$23,balance_sheet!$B$1:$I$1,0)),"") | I39: =IFERROR(INDEX(balance_sheet!$B:$I,MATCH("Vốn chủ sở hữu",balance_sheet!$A:$A,0),MATCH(I$23,balance_sheet!$B$1:$I$1,0)),"") | J39: 6096125000000
A40: Tăng VCSH/LN cổ đông cty mẹ | C40: =(C39-B39)/C52 | D40: =(D39-C39)/D52 | E40: =(E39-D39)/E52 | F40: =(F39-E39)/F52 | G40: =(G39-F39)/G52 | H40: =(H39-G39)/H52 | I40: =(I39-H39)/I52
A41: Lợi ích của cổ đông thiểu số | B41: =IFERROR(INDEX(balance_sheet!$B:$I,MATCH("Lợi ích của cổ đông thiểu số",balance_sheet!$A:$A,0),MATCH(B$23,balance_sheet!$B$1:$I$1,0)),"") | C41: =IFERROR(INDEX(balance_sheet!$B:$I,MATCH("Lợi ích của cổ đông thiểu số",balance_sheet!$A:$A,0),MATCH(C$23,balance_sheet!$B$1:$I$1,0)),"") | D41: =IFERROR(INDEX(balance_sheet!$B:$I,MATCH("Lợi ích của cổ đông thiểu số",balance_sheet!$A:$A,0),MATCH(D$23,balance_sheet!$B$1:$I$1,0)),"") | E41: =IFERROR(INDEX(balance_sheet!$B:$I,MATCH("Lợi ích của cổ đông thiểu số",balance_sheet!$A:$A,0),MATCH(E$23,balance_sheet!$B$1:$I$1,0)),"") | F41: =IFERROR(INDEX(balance_sheet!$B:$I,MATCH("Lợi ích của cổ đông thiểu số",balance_sheet!$A:$A,0),MATCH(F$23,balance_sheet!$B$1:$I$1,0)),"") | G41: =IFERROR(INDEX(balance_sheet!$B:$I,MATCH("Lợi ích của cổ đông thiểu số",balance_sheet!$A:$A,0),MATCH(G$23,balance_sheet!$B$1:$I$1,0)),"") | H41: =IFERROR(INDEX(balance_sheet!$B:$I,MATCH("Lợi ích của cổ đông thiểu số",balance_sheet!$A:$A,0),MATCH(H$23,balance_sheet!$B$1:$I$1,0)),"") | I41: =IFERROR(INDEX(balance_sheet!$B:$I,MATCH("Lợi ích của cổ đông thiểu số",balance_sheet!$A:$A,0),MATCH(I$23,balance_sheet!$B$1:$I$1,0)),"")
A42: Kết quả hoạt động kinh doanh
A43: Doanh thu thuần | B43: =IFERROR(INDEX(income_statement!$B:$I,MATCH("Doanh thu thuần",income_statement!$A:$A,0),MATCH(B$23,income_statement!$B$1:$I$1,0)),"") | C43: =IFERROR(INDEX(income_statement!$B:$I,MATCH("Doanh thu thuần",income_statement!$A:$A,0),MATCH(C$23,income_statement!$B$1:$I$1,0)),"") | D43: =IFERROR(INDEX(income_statement!$B:$I,MATCH("Doanh thu thuần",income_statement!$A:$A,0),MATCH(D$23,income_statement!$B$1:$I$1,0)),"") | E43: =IFERROR(INDEX(income_statement!$B:$I,MATCH("Doanh thu thuần",income_statement!$A:$A,0),MATCH(E$23,income_statement!$B$1:$I$1,0)),"") | F43: =IFERROR(INDEX(income_statement!$B:$I,MATCH("Doanh thu thuần",income_statement!$A:$A,0),MATCH(F$23,income_statement!$B$1:$I$1,0)),"") | G43: =IFERROR(INDEX(income_statement!$B:$I,MATCH("Doanh thu thuần",income_statement!$A:$A,0),MATCH(G$23,income_statement!$B$1:$I$1,0)),"") | H43: =IFERROR(INDEX(income_statement!$B:$I,MATCH("Doanh thu thuần",income_statement!$A:$A,0),MATCH(H$23,income_statement!$B$1:$I$1,0)),"") | I43: =IFERROR(INDEX(income_statement!$B:$I,MATCH("Doanh thu thuần",income_statement!$A:$A,0),MATCH(I$23,income_statement!$B$1:$I$1,0)),"") | J43: 59500000000000
A44: Giá vốn hàng bán | B44: =IFERROR(INDEX(income_statement!$B:$I,MATCH("Giá vốn hàng bán",income_statement!$A:$A,0),MATCH(B$23,income_statement!$B$1:$I$1,0)),"") | C44: =IFERROR(INDEX(income_statement!$B:$I,MATCH("Giá vốn hàng bán",income_statement!$A:$A,0),MATCH(C$23,income_statement!$B$1:$I$1,0)),"") | D44: =IFERROR(INDEX(income_statement!$B:$I,MATCH("Giá vốn hàng bán",income_statement!$A:$A,0),MATCH(D$23,income_statement!$B$1:$I$1,0)),"") | E44: =IFERROR(INDEX(income_statement!$B:$I,MATCH("Giá vốn hàng bán",income_statement!$A:$A,0),MATCH(E$23,income_statement!$B$1:$I$1,0)),"") | F44: =IFERROR(INDEX(income_statement!$B:$I,MATCH("Giá vốn hàng bán",income_statement!$A:$A,0),MATCH(F$23,income_statement!$B$1:$I$1,0)),"") | G44: =IFERROR(INDEX(income_statement!$B:$I,MATCH("Giá vốn hàng bán",income_statement!$A:$A,0),MATCH(G$23,income_statement!$B$1:$I$1,0)),"") | H44: =IFERROR(INDEX(income_statement!$B:$I,MATCH("Giá vốn hàng bán",income_statement!$A:$A,0),MATCH(H$23,income_statement!$B$1:$I$1,0)),"") | I44: =IFERROR(INDEX(income_statement!$B:$I,MATCH("Giá vốn hàng bán",income_statement!$A:$A,0),MATCH(I$23,income_statement!$B$1:$I$1,0)),"")
A45: Lợi nhuận gộp | B45: =IFERROR(INDEX(income_statement!$B:$I,MATCH("Lợi nhuận gộp",income_statement!$A:$A,0),MATCH(B$23,income_statement!$B$1:$I$1,0)),"") | C45: =IFERROR(INDEX(income_statement!$B:$I,MATCH("Lợi nhuận gộp",income_statement!$A:$A,0),MATCH(C$23,income_statement!$B$1:$I$1,0)),"") | D45: =IFERROR(INDEX(income_statement!$B:$I,MATCH("Lợi nhuận gộp",income_statement!$A:$A,0),MATCH(D$23,income_statement!$B$1:$I$1,0)),"") | E45: =IFERROR(INDEX(income_statement!$B:$I,MATCH("Lợi nhuận gộp",income_statement!$A:$A,0),MATCH(E$23,income_statement!$B$1:$I$1,0)),"") | F45: =IFERROR(INDEX(income_statement!$B:$I,MATCH("Lợi nhuận gộp",income_statement!$A:$A,0),MATCH(F$23,income_statement!$B$1:$I$1,0)),"") | G45: =IFERROR(INDEX(income_statement!$B:$I,MATCH("Lợi nhuận gộp",income_statement!$A:$A,0),MATCH(G$23,income_statement!$B$1:$I$1,0)),"") | H45: =IFERROR(INDEX(income_statement!$B:$I,MATCH("Lợi nhuận gộp",income_statement!$A:$A,0),MATCH(H$23,income_statement!$B$1:$I$1,0)),"") | I45: =IFERROR(INDEX(income_statement!$B:$I,MATCH("Lợi nhuận gộp",income_statement!$A:$A,0),MATCH(I$23,income_statement!$B$1:$I$1,0)),"")
A46: Chi phí bán hàng | B46: =IFERROR(INDEX(income_statement!$B:$I,MATCH("Chi phí bán hàng",income_statement!$A:$A,0),MATCH(B$23,income_statement!$B$1:$I$1,0)),"") | C46: =IFERROR(INDEX(income_statement!$B:$I,MATCH("Chi phí bán hàng",income_statement!$A:$A,0),MATCH(C$23,income_statement!$B$1:$I$1,0)),"") | D46: =IFERROR(INDEX(income_statement!$B:$I,MATCH("Chi phí bán hàng",income_statement!$A:$A,0),MATCH(D$23,income_statement!$B$1:$I$1,0)),"") | E46: =IFERROR(INDEX(income_statement!$B:$I,MATCH("Chi phí bán hàng",income_statement!$A:$A,0),MATCH(E$23,income_statement!$B$1:$I$1,0)),"") | F46: =IFERROR(INDEX(income_statement!$B:$I,MATCH("Chi phí bán hàng",income_statement!$A:$A,0),MATCH(F$23,income_statement!$B$1:$I$1,0)),"") | G46: =IFERROR(INDEX(income_statement!$B:$I,MATCH("Chi phí bán hàng",income_statement!$A:$A,0),MATCH(G$23,income_statement!$B$1:$I$1,0)),"") | H46: =IFERROR(INDEX(income_statement!$B:$I,MATCH("Chi phí bán hàng",income_statement!$A:$A,0),MATCH(H$23,income_statement!$B$1:$I$1,0)),"") | I46: =IFERROR(INDEX(income_statement!$B:$I,MATCH("Chi phí bán hàng",income_statement!$A:$A,0),MATCH(I$23,income_statement!$B$1:$I$1,0)),"")
A47: Chi phí quản lý doanh nghiệp | B47: =IFERROR(INDEX(income_statement!$B:$I,MATCH("Chi phí quản lý doanh nghiệp",income_statement!$A:$A,0),MATCH(B$23,income_statement!$B$1:$I$1,0)),"") | C47: =IFERROR(INDEX(income_statement!$B:$I,MATCH("Chi phí quản lý doanh nghiệp",income_statement!$A:$A,0),MATCH(C$23,income_statement!$B$1:$I$1,0)),"") | D47: =IFERROR(INDEX(income_statement!$B:$I,MATCH("Chi phí quản lý doanh nghiệp",income_statement!$A:$A,0),MATCH(D$23,income_statement!$B$1:$I$1,0)),"") | E47: =IFERROR(INDEX(income_statement!$B:$I,MATCH("Chi phí quản lý doanh nghiệp",income_statement!$A:$A,0),MATCH(E$23,income_statement!$B$1:$I$1,0)),"") | F47: =IFERROR(INDEX(income_statement!$B:$I,MATCH("Chi phí quản lý doanh nghiệp",income_statement!$A:$A,0),MATCH(F$23,income_statement!$B$1:$I$1,0)),"") | G47: =IFERROR(INDEX(income_statement!$B:$I,MATCH("Chi phí quản lý doanh nghiệp",income_statement!$A:$A,0),MATCH(G$23,income_statement!$B$1:$I$1,0)),"") | H47: =IFERROR(INDEX(income_statement!$B:$I,MATCH("Chi phí quản lý doanh nghiệp",income_statement!$A:$A,0),MATCH(H$23,income_statement!$B$1:$I$1,0)),"") | I47: =IFERROR(INDEX(income_statement!$B:$I,MATCH("Chi phí quản lý doanh nghiệp",income_statement!$A:$A,0),MATCH(I$23,income_statement!$B$1:$I$1,0)),"")
A48: Lãi/(lỗ) từ hoạt động kinh doanh | B48: =IFERROR(INDEX(income_statement!$B:$I,MATCH("Lãi/(lỗ) từ hoạt động kinh doanh",income_statement!$A:$A,0),MATCH(B$23,income_statement!$B$1:$I$1,0)),"") | C48: =IFERROR(INDEX(income_statement!$B:$I,MATCH("Lãi/(lỗ) từ hoạt động kinh doanh",income_statement!$A:$A,0),MATCH(C$23,income_statement!$B$1:$I$1,0)),"") | D48: =IFERROR(INDEX(income_statement!$B:$I,MATCH("Lãi/(lỗ) từ hoạt động kinh doanh",income_statement!$A:$A,0),MATCH(D$23,income_statement!$B$1:$I$1,0)),"") | E48: =IFERROR(INDEX(income_statement!$B:$I,MATCH("Lãi/(lỗ) từ hoạt động kinh doanh",income_statement!$A:$A,0),MATCH(E$23,income_statement!$B$1:$I$1,0)),"") | F48: =IFERROR(INDEX(income_statement!$B:$I,MATCH("Lãi/(lỗ) từ hoạt động kinh doanh",income_statement!$A:$A,0),MATCH(F$23,income_statement!$B$1:$I$1,0)),"") | G48: =IFERROR(INDEX(income_statement!$B:$I,MATCH("Lãi/(lỗ) từ hoạt động kinh doanh",income_statement!$A:$A,0),MATCH(G$23,income_statement!$B$1:$I$1,0)),"") | H48: =IFERROR(INDEX(income_statement!$B:$I,MATCH("Lãi/(lỗ) từ hoạt động kinh doanh",income_statement!$A:$A,0),MATCH(H$23,income_statement!$B$1:$I$1,0)),"") | I48: =IFERROR(INDEX(income_statement!$B:$I,MATCH("Lãi/(lỗ) từ hoạt động kinh doanh",income_statement!$A:$A,0),MATCH(I$23,income_statement!$B$1:$I$1,0)),"")
A49: Chi phí lãi vay | B49: =IFERROR(INDEX(income_statement!$B:$I,MATCH("Chi phí lãi vay",income_statement!$A:$A,0),MATCH(B$23,income_statement!$B$1:$I$1,0)),"") | C49: =IFERROR(INDEX(income_statement!$B:$I,MATCH("Chi phí lãi vay",income_statement!$A:$A,0),MATCH(C$23,income_statement!$B$1:$I$1,0)),"") | D49: =IFERROR(INDEX(income_statement!$B:$I,MATCH("Chi phí lãi vay",income_statement!$A:$A,0),MATCH(D$23,income_statement!$B$1:$I$1,0)),"") | E49: =IFERROR(INDEX(income_statement!$B:$I,MATCH("Chi phí lãi vay",income_statement!$A:$A,0),MATCH(E$23,income_statement!$B$1:$I$1,0)),"") | F49: =IFERROR(INDEX(income_statement!$B:$I,MATCH("Chi phí lãi vay",income_statement!$A:$A,0),MATCH(F$23,income_statement!$B$1:$I$1,0)),"") | G49: =IFERROR(INDEX(income_statement!$B:$I,MATCH("Chi phí lãi vay",income_statement!$A:$A,0),MATCH(G$23,income_statement!$B$1:$I$1,0)),"") | H49: =IFERROR(INDEX(income_statement!$B:$I,MATCH("Chi phí lãi vay",income_statement!$A:$A,0),MATCH(H$23,income_statement!$B$1:$I$1,0)),"") | I49: =IFERROR(INDEX(income_statement!$B:$I,MATCH("Chi phí lãi vay",income_statement!$A:$A,0),MATCH(I$23,income_statement!$B$1:$I$1,0)),"")
A50: Lãi/(lỗ) trước thuế | B50: =IFERROR(INDEX(income_statement!$B:$I,MATCH("Lãi/(lỗ) trước thuế",income_statement!$A:$A,0),MATCH(B$23,income_statement!$B$1:$I$1,0)),"") | C50: =IFERROR(INDEX(income_statement!$B:$I,MATCH("Lãi/(lỗ) trước thuế",income_statement!$A:$A,0),MATCH(C$23,income_statement!$B$1:$I$1,0)),"") | D50: =IFERROR(INDEX(income_statement!$B:$I,MATCH("Lãi/(lỗ) trước thuế",income_statement!$A:$A,0),MATCH(D$23,income_statement!$B$1:$I$1,0)),"") | E50: =IFERROR(INDEX(income_statement!$B:$I,MATCH("Lãi/(lỗ) trước thuế",income_statement!$A:$A,0),MATCH(E$23,income_statement!$B$1:$I$1,0)),"") | F50: =IFERROR(INDEX(income_statement!$B:$I,MATCH("Lãi/(lỗ) trước thuế",income_statement!$A:$A,0),MATCH(F$23,income_statement!$B$1:$I$1,0)),"") | G50: =IFERROR(INDEX(income_statement!$B:$I,MATCH("Lãi/(lỗ) trước thuế",income_statement!$A:$A,0),MATCH(G$23,income_statement!$B$1:$I$1,0)),"") | H50: =IFERROR(INDEX(income_statement!$B:$I,MATCH("Lãi/(lỗ) trước thuế",income_statement!$A:$A,0),MATCH(H$23,income_statement!$B$1:$I$1,0)),"") | I50: =IFERROR(INDEX(income_statement!$B:$I,MATCH("Lãi/(lỗ) trước thuế",income_statement!$A:$A,0),MATCH(I$23,income_statement!$B$1:$I$1,0)),"") | J50: 1550000000000
A51: Lãi/(lỗ) thuần sau thuế | B51: =IFERROR(INDEX(income_statement!$B:$I,MATCH("Lãi/(lỗ) thuần sau thuế",income_statement!$A:$A,0),MATCH(B$23,income_statement!$B$1:$I$1,0)),"") | C51: =IFERROR(INDEX(income_statement!$B:$I,MATCH("Lãi/(lỗ) thuần sau thuế",income_statement!$A:$A,0),MATCH(C$23,income_statement!$B$1:$I$1,0)),"") | D51: =IFERROR(INDEX(income_statement!$B:$I,MATCH("Lãi/(lỗ) thuần sau thuế",income_statement!$A:$A,0),MATCH(D$23,income_statement!$B$1:$I$1,0)),"") | E51: =IFERROR(INDEX(income_statement!$B:$I,MATCH("Lãi/(lỗ) thuần sau thuế",income_statement!$A:$A,0),MATCH(E$23,income_statement!$B$1:$I$1,0)),"") | F51: =IFERROR(INDEX(income_statement!$B:$I,MATCH("Lãi/(lỗ) thuần sau thuế",income_statement!$A:$A,0),MATCH(F$23,income_statement!$B$1:$I$1,0)),"") | G51: =IFERROR(INDEX(income_statement!$B:$I,MATCH("Lãi/(lỗ) thuần sau thuế",income_statement!$A:$A,0),MATCH(G$23,income_statement!$B$1:$I$1,0)),"") | H51: =IFERROR(INDEX(income_statement!$B:$I,MATCH("Lãi/(lỗ) thuần sau thuế",income_statement!$A:$A,0),MATCH(H$23,income_statement!$B$1:$I$1,0)),"") | I51: =IFERROR(INDEX(income_statement!$B:$I,MATCH("Lãi/(lỗ) thuần sau thuế",income_statement!$A:$A,0),MATCH(I$23,income_statement!$B$1:$I$1,0)),"")
A52: Lợi nhuận của Cổ đông của Công ty mẹ | B52: =IFERROR(INDEX(income_statement!$B:$I,MATCH("Lợi nhuận của Cổ đông của Công ty mẹ",income_statement!$A:$A,0),MATCH(B$23,income_statement!$B$1:$I$1,0)),"") | C52: =IFERROR(INDEX(income_statement!$B:$I,MATCH("Lợi nhuận của Cổ đông của Công ty mẹ",income_statement!$A:$A,0),MATCH(C$23,income_statement!$B$1:$I$1,0)),"") | D52: =IFERROR(INDEX(income_statement!$B:$I,MATCH("Lợi nhuận của Cổ đông của Công ty mẹ",income_statement!$A:$A,0),MATCH(D$23,income_statement!$B$1:$I$1,0)),"") | E52: =IFERROR(INDEX(income_statement!$B:$I,MATCH("Lợi nhuận của Cổ đông của Công ty mẹ",income_statement!$A:$A,0),MATCH(E$23,income_statement!$B$1:$I$1,0)),"") | F52: =IFERROR(INDEX(income_statement!$B:$I,MATCH("Lợi nhuận của Cổ đông của Công ty mẹ",income_statement!$A:$A,0),MATCH(F$23,income_statement!$B$1:$I$1,0)),"") | G52: =IFERROR(INDEX(income_statement!$B:$I,MATCH("Lợi nhuận của Cổ đông của Công ty mẹ",income_statement!$A:$A,0),MATCH(G$23,income_statement!$B$1:$I$1,0)),"") | H52: =IFERROR(INDEX(income_statement!$B:$I,MATCH("Lợi nhuận của Cổ đông của Công ty mẹ",income_statement!$A:$A,0),MATCH(H$23,income_statement!$B$1:$I$1,0)),"") | I52: =IFERROR(INDEX(income_statement!$B:$I,MATCH("Lợi nhuận của Cổ đông của Công ty mẹ",income_statement!$A:$A,0),MATCH(I$23,income_statement!$B$1:$I$1,0)),"") | J52: =J50*0.65
A53: LN cổ đông cty mẹ/ LN trước thuế | B53: =B52/B50 | C53: =C52/C50 | D53: =D52/D50 | E53: =E52/E50 | F53: =F52/F50 | G53: =G52/G50 | H53: =H52/H50 | I53: =I52/I50
A54: Lưu chuyển tiền tệ
A55: Khấu hao TSCĐ và BĐSĐT | B55: =IFERROR(INDEX(cash_flow!$B:$I,MATCH("Khấu hao TSCĐ và BĐSĐT",cash_flow!$A:$A,0),MATCH(B$23,cash_flow!$B$1:$I$1,0)),"") | C55: =IFERROR(INDEX(cash_flow!$B:$I,MATCH("Khấu hao TSCĐ và BĐSĐT",cash_flow!$A:$A,0),MATCH(C$23,cash_flow!$B$1:$I$1,0)),"") | D55: =IFERROR(INDEX(cash_flow!$B:$I,MATCH("Khấu hao TSCĐ và BĐSĐT",cash_flow!$A:$A,0),MATCH(D$23,cash_flow!$B$1:$I$1,0)),"") | E55: =IFERROR(INDEX(cash_flow!$B:$I,MATCH("Khấu hao TSCĐ và BĐSĐT",cash_flow!$A:$A,0),MATCH(E$23,cash_flow!$B$1:$I$1,0)),"") | F55: =IFERROR(INDEX(cash_flow!$B:$I,MATCH("Khấu hao TSCĐ và BĐSĐT",cash_flow!$A:$A,0),MATCH(F$23,cash_flow!$B$1:$I$1,0)),"") | G55: =IFERROR(INDEX(cash_flow!$B:$I,MATCH("Khấu hao TSCĐ và BĐSĐT",cash_flow!$A:$A,0),MATCH(G$23,cash_flow!$B$1:$I$1,0)),"") | H55: =IFERROR(INDEX(cash_flow!$B:$I,MATCH("Khấu hao TSCĐ và BĐSĐT",cash_flow!$A:$A,0),MATCH(H$23,cash_flow!$B$1:$I$1,0)),"") | I55: =IFERROR(INDEX(cash_flow!$B:$I,MATCH("Khấu hao TSCĐ và BĐSĐT",cash_flow!$A:$A,0),MATCH(I$23,cash_flow!$B$1:$I$1,0)),"")
A56: Tiền chi để mua sắm, xây dựng TSCĐ và các tài sản dài hạn khác | B56: =IFERROR(INDEX(cash_flow!$B:$I,MATCH("Tiền chi để mua sắm, xây dựng TSCĐ và các tài sản dài hạn khác",cash_flow!$A:$A,0),MATCH(B$23,cash_flow!$B$1:$I$1,0)),"") | C56: =IFERROR(INDEX(cash_flow!$B:$I,MATCH("Tiền chi để mua sắm, xây dựng TSCĐ và các tài sản dài hạn khác",cash_flow!$A:$A,0),MATCH(C$23,cash_flow!$B$1:$I$1,0)),"") | D56: =IFERROR(INDEX(cash_flow!$B:$I,MATCH("Tiền chi để mua sắm, xây dựng TSCĐ và các tài sản dài hạn khác",cash_flow!$A:$A,0),MATCH(D$23,cash_flow!$B$1:$I$1,0)),"") | E56: =IFERROR(INDEX(cash_flow!$B:$I,MATCH("Tiền chi để mua sắm, xây dựng TSCĐ và các tài sản dài hạn khác",cash_flow!$A:$A,0),MATCH(E$23,cash_flow!$B$1:$I$1,0)),"") | F56: =IFERROR(INDEX(cash_flow!$B:$I,MATCH("Tiền chi để mua sắm, xây dựng TSCĐ và các tài sản dài hạn khác",cash_flow!$A:$A,0),MATCH(F$23,cash_flow!$B$1:$I$1,0)),"") | G56: =IFERROR(INDEX(cash_flow!$B:$I,MATCH("Tiền chi để mua sắm, xây dựng TSCĐ và các tài sản dài hạn khác",cash_flow!$A:$A,0),MATCH(G$23,cash_flow!$B$1:$I$1,0)),"") | H56: =IFERROR(INDEX(cash_flow!$B:$I,MATCH("Tiền chi để mua sắm, xây dựng TSCĐ và các tài sản dài hạn khác",cash_flow!$A:$A,0),MATCH(H$23,cash_flow!$B$1:$I$1,0)),"") | I56: =IFERROR(INDEX(cash_flow!$B:$I,MATCH("Tiền chi để mua sắm, xây dựng TSCĐ và các tài sản dài hạn khác",cash_flow!$A:$A,0),MATCH(I$23,cash_flow!$B$1:$I$1,0)),"")
A57: Lưu chuyển tiền tệ ròng từ các hoạt động sản xuất kinh doanh | B57: =IFERROR(INDEX(cash_flow!$B:$I,MATCH("Lưu chuyển tiền tệ ròng từ các hoạt động sản xuất kinh doanh",cash_flow!$A:$A,0),MATCH(B$23,cash_flow!$B$1:$I$1,0)),"") | C57: =IFERROR(INDEX(cash_flow!$B:$I,MATCH("Lưu chuyển tiền tệ ròng từ các hoạt động sản xuất kinh doanh",cash_flow!$A:$A,0),MATCH(C$23,cash_flow!$B$1:$I$1,0)),"") | D57: =IFERROR(INDEX(cash_flow!$B:$I,MATCH("Lưu chuyển tiền tệ ròng từ các hoạt động sản xuất kinh doanh",cash_flow!$A:$A,0),MATCH(D$23,cash_flow!$B$1:$I$1,0)),"") | E57: =IFERROR(INDEX(cash_flow!$B:$I,MATCH("Lưu chuyển tiền tệ ròng từ các hoạt động sản xuất kinh doanh",cash_flow!$A:$A,0),MATCH(E$23,cash_flow!$B$1:$I$1,0)),"") | F57: =IFERROR(INDEX(cash_flow!$B:$I,MATCH("Lưu chuyển tiền tệ ròng từ các hoạt động sản xuất kinh doanh",cash_flow!$A:$A,0),MATCH(F$23,cash_flow!$B$1:$I$1,0)),"") | G57: =IFERROR(INDEX(cash_flow!$B:$I,MATCH("Lưu chuyển tiền tệ ròng từ các hoạt động sản xuất kinh doanh",cash_flow!$A:$A,0),MATCH(G$23,cash_flow!$B$1:$I$1,0)),"") | H57: =IFERROR(INDEX(cash_flow!$B:$I,MATCH("Lưu chuyển tiền tệ ròng từ các hoạt động sản xuất kinh doanh",cash_flow!$A:$A,0),MATCH(H$23,cash_flow!$B$1:$I$1,0)),"") | I57: =IFERROR(INDEX(cash_flow!$B:$I,MATCH("Lưu chuyển tiền tệ ròng từ các hoạt động sản xuất kinh doanh",cash_flow!$A:$A,0),MATCH(I$23,cash_flow!$B$1:$I$1,0)),"")
A61: CHỈ SỐ THÊM | B61: 2018 | C61: 2019 | D61: 2020 | E61: 2021 | F61: 2022 | G61: 2023 | H61: 2024 | I61: 2025
A62: Khả năng sinh lời & hiệu quả sử dụng vốn
A63: ROCE | B63: =IFERROR(B$65/(B$31-B$35),"n/a") | C63: =IFERROR(C$65/(C$31-C$35),"n/a") | D63: =IFERROR(D$65/(D$31-D$35),"n/a") | E63: =IFERROR(E$65/(E$31-E$35),"n/a") | F63: =IFERROR(F$65/(F$31-F$35),"n/a") | G63: =IFERROR(G$65/(G$31-G$35),"n/a") | H63: =IFERROR(H$65/(H$31-H$35),"n/a") | I63: =IFERROR(I$65/(I$31-I$35),"n/a")
A64: CROIC | B64: =IFERROR(B$69/(B$31-B$35),"n/a") | C64: =IFERROR(C$69/(C$31-C$35),"n/a") | D64: =IFERROR(D$69/(D$31-D$35),"n/a") | E64: =IFERROR(E$69/(E$31-E$35),"n/a") | F64: =IFERROR(F$69/(F$31-F$35),"n/a") | G64: =IFERROR(G$69/(G$31-G$35),"n/a") | H64: =IFERROR(H$69/(H$31-H$35),"n/a") | I64: =IFERROR(I$69/(I$31-I$35),"n/a")
A65: EBIT | B65: =IFERROR(B$48+ABS(B$49),"n/a") | C65: =IFERROR(C$48+ABS(C$49),"n/a") | D65: =IFERROR(D$48+ABS(D$49),"n/a") | E65: =IFERROR(E$48+ABS(E$49),"n/a") | F65: =IFERROR(F$48+ABS(F$49),"n/a") | G65: =IFERROR(G$48+ABS(G$49),"n/a") | H65: =IFERROR(H$48+ABS(H$49),"n/a") | I65: =IFERROR(I$48+ABS(I$49),"n/a")
A66: EBIT/DT | B66: =IFERROR(B$65/B$43,"n/a") | C66: =IFERROR(C$65/C$43,"n/a") | D66: =IFERROR(D$65/D$43,"n/a") | E66: =IFERROR(E$65/E$43,"n/a") | F66: =IFERROR(F$65/F$43,"n/a") | G66: =IFERROR(G$65/G$43,"n/a") | H66: =IFERROR(H$65/H$43,"n/a") | I66: =IFERROR(I$65/I$43,"n/a")
A67: DT/TS | B67: =IFERROR(B$43/B$31,"n/a") | C67: =IFERROR(C$43/C$31,"n/a") | D67: =IFERROR(D$43/D$31,"n/a") | E67: =IFERROR(E$43/E$31,"n/a") | F67: =IFERROR(F$43/F$31,"n/a") | G67: =IFERROR(G$43/G$31,"n/a") | H67: =IFERROR(H$43/H$31,"n/a") | I67: =IFERROR(I$43/I$31,"n/a")
A68: Dòng tiền & tái đầu tư
A69: FCF | B69: =IFERROR(B$57-ABS(B$56),"n/a") | C69: =IFERROR(C$57-ABS(C$56),"n/a") | D69: =IFERROR(D$57-ABS(D$56),"n/a") | E69: =IFERROR(E$57-ABS(E$56),"n/a") | F69: =IFERROR(F$57-ABS(F$56),"n/a") | G69: =IFERROR(G$57-ABS(G$56),"n/a") | H69: =IFERROR(H$57-ABS(H$56),"n/a") | I69: =IFERROR(I$57-ABS(I$56),"n/a")
A70: FCF/DT | B70: =IFERROR(B$69/B$43,"n/a") | C70: =IFERROR(C$69/C$43,"n/a") | D70: =IFERROR(D$69/D$43,"n/a") | E70: =IFERROR(E$69/E$43,"n/a") | F70: =IFERROR(F$69/F$43,"n/a") | G70: =IFERROR(G$69/G$43,"n/a") | H70: =IFERROR(H$69/H$43,"n/a") | I70: =IFERROR(I$69/I$43,"n/a")
A71: FCF/Nợ ngắn hạn | B71: =IFERROR(B$69/B$35,"n/a") | C71: =IFERROR(C$69/C$35,"n/a") | D71: =IFERROR(D$69/D$35,"n/a") | E71: =IFERROR(E$69/E$35,"n/a") | F71: =IFERROR(F$69/F$35,"n/a") | G71: =IFERROR(G$69/G$35,"n/a") | H71: =IFERROR(H$69/H$35,"n/a") | I71: =IFERROR(I$69/I$35,"n/a")
A72: Capex | B72: =IFERROR(ABS(B$56),"n/a") | C72: =IFERROR(ABS(C$56),"n/a") | D72: =IFERROR(ABS(D$56),"n/a") | E72: =IFERROR(ABS(E$56),"n/a") | F72: =IFERROR(ABS(F$56),"n/a") | G72: =IFERROR(ABS(G$56),"n/a") | H72: =IFERROR(ABS(H$56),"n/a") | I72: =IFERROR(ABS(I$56),"n/a")
A73: Capex/TS | B73: =IFERROR(B$72/B$31,"n/a") | C73: =IFERROR(C$72/C$31,"n/a") | D73: =IFERROR(D$72/D$31,"n/a") | E73: =IFERROR(E$72/E$31,"n/a") | F73: =IFERROR(F$72/F$31,"n/a") | G73: =IFERROR(G$72/G$31,"n/a") | H73: =IFERROR(H$72/H$31,"n/a") | I73: =IFERROR(I$72/I$31,"n/a")
A74: Capex/LNST | B74: =IFERROR(B$72/ABS(B$51),"n/a") | C74: =IFERROR(C$72/ABS(C$51),"n/a") | D74: =IFERROR(D$72/ABS(D$51),"n/a") | E74: =IFERROR(E$72/ABS(E$51),"n/a") | F74: =IFERROR(F$72/ABS(F$51),"n/a") | G74: =IFERROR(G$72/ABS(G$51),"n/a") | H74: =IFERROR(H$72/ABS(H$51),"n/a") | I74: =IFERROR(I$72/ABS(I$51),"n/a")
A75: Chi phí khấu hao/Lợi nhuận gộp | B75: =IFERROR(ABS(B$55)/B$45,"n/a") | C75: =IFERROR(ABS(C$55)/C$45,"n/a") | D75: =IFERROR(ABS(D$55)/D$45,"n/a") | E75: =IFERROR(ABS(E$55)/E$45,"n/a") | F75: =IFERROR(ABS(F$55)/F$45,"n/a") | G75: =IFERROR(ABS(G$55)/G$45,"n/a") | H75: =IFERROR(ABS(H$55)/H$45,"n/a") | I75: =IFERROR(ABS(I$55)/I$45,"n/a")
A76: EBIT/Chi phí lãi vay | B76: =IFERROR(B$65/ABS(B$49),"n/a") | C76: =IFERROR(C$65/ABS(C$49),"n/a") | D76: =IFERROR(D$65/ABS(D$49),"n/a") | E76: =IFERROR(E$65/ABS(E$49),"n/a") | F76: =IFERROR(F$65/ABS(F$49),"n/a") | G76: =IFERROR(G$65/ABS(G$49),"n/a") | H76: =IFERROR(H$65/ABS(H$49),"n/a") | I76: =IFERROR(I$65/ABS(I$49),"n/a")
A77: Vốn lưu động & hiệu quả hoạt động
A78: Vòng quay tiền mặt | B78: =IFERROR(B$17+B$18-B$16,"n/a") | C78: =IFERROR(C$17+C$18-C$16,"n/a") | D78: =IFERROR(D$17+D$18-D$16,"n/a") | E78: =IFERROR(E$17+E$18-E$16,"n/a") | F78: =IFERROR(F$17+F$18-F$16,"n/a") | G78: =IFERROR(G$17+G$18-G$16,"n/a") | H78: =IFERROR(H$17+H$18-H$16,"n/a") | I78: =IFERROR(I$17+I$18-I$16,"n/a")
A79: HTK/DT | B79: =IFERROR(B$28/B$43,"n/a") | C79: =IFERROR(C$28/C$43,"n/a") | D79: =IFERROR(D$28/D$43,"n/a") | E79: =IFERROR(E$28/E$43,"n/a") | F79: =IFERROR(F$28/F$43,"n/a") | G79: =IFERROR(G$28/G$43,"n/a") | H79: =IFERROR(H$28/H$43,"n/a") | I79: =IFERROR(I$28/I$43,"n/a")
A80: HTK/TS | B80: =IFERROR(B$28/B$31,"n/a") | C80: =IFERROR(C$28/C$31,"n/a") | D80: =IFERROR(D$28/D$31,"n/a") | E80: =IFERROR(E$28/E$31,"n/a") | F80: =IFERROR(F$28/F$31,"n/a") | G80: =IFERROR(G$28/G$31,"n/a") | H80: =IFERROR(H$28/H$31,"n/a") | I80: =IFERROR(I$28/I$31,"n/a")
A81: DT/TS | B81: =IFERROR(B$43/B$31,"n/a") | C81: =IFERROR(C$43/C$31,"n/a") | D81: =IFERROR(D$43/D$31,"n/a") | E81: =IFERROR(E$43/E$31,"n/a") | F81: =IFERROR(F$43/F$31,"n/a") | G81: =IFERROR(G$43/G$31,"n/a") | H81: =IFERROR(H$43/H$31,"n/a") | I81: =IFERROR(I$43/I$31,"n/a")
A82: Khả năng thanh toán
A83: (TS ngắn hạn − HTK)/Nợ ngắn hạn | B83: =IFERROR((B$29-B$28)/B$35,"n/a") | C83: =IFERROR((C$29-C$28)/C$35,"n/a") | D83: =IFERROR((D$29-D$28)/D$35,"n/a") | E83: =IFERROR((E$29-E$28)/E$35,"n/a") | F83: =IFERROR((F$29-F$28)/F$35,"n/a") | G83: =IFERROR((G$29-G$28)/G$35,"n/a") | H83: =IFERROR((H$29-H$28)/H$35,"n/a") | I83: =IFERROR((I$29-I$28)/I$35,"n/a")
A84: TS ngắn hạn/Nợ ngắn hạn | B84: =IFERROR(B$29/B$35,"n/a") | C84: =IFERROR(C$29/C$35,"n/a") | D84: =IFERROR(D$29/D$35,"n/a") | E84: =IFERROR(E$29/E$35,"n/a") | F84: =IFERROR(F$29/F$35,"n/a") | G84: =IFERROR(G$29/G$35,"n/a") | H84: =IFERROR(H$29/H$35,"n/a") | I84: =IFERROR(I$29/I$35,"n/a")
A85: Tài sản & cơ cấu tài sản
A86: TSCĐ vô hình | B86: =IFERROR(B$30,"n/a") | C86: =IFERROR(C$30,"n/a") | D86: =IFERROR(D$30,"n/a") | E86: =IFERROR(E$30,"n/a") | F86: =IFERROR(F$30,"n/a") | G86: =IFERROR(G$30,"n/a") | H86: =IFERROR(H$30,"n/a") | I86: =IFERROR(I$30,"n/a")
A87: Tài sản vô hình/Giá trị sổ sách | B87: =IFERROR(B$30/B$39,"n/a") | C87: =IFERROR(C$30/C$39,"n/a") | D87: =IFERROR(D$30/D$39,"n/a") | E87: =IFERROR(E$30/E$39,"n/a") | F87: =IFERROR(F$30/F$39,"n/a") | G87: =IFERROR(G$30/G$39,"n/a") | H87: =IFERROR(H$30/H$39,"n/a") | I87: =IFERROR(I$30/I$39,"n/a")

Sheet Dự báo tăng trưởng
B1: Q4/2025 | C1: Q1/2026 | D1: Q2/2026 | E1: Q3/2026 | F1: Q4/2026
A2: Số CP | B2: 178815054 | C2: 178815054 | D2: 178815054 | E2: 178815054 | F2: 178815054
A3: Thị giá | B3: 147500 | C3: 147500 | D3: 147500 | E3: 147500 | F3: 147500
A4: Vốn hoá | B4: =B2*B3 | C4: =C2*C3 | D4: =D2*D3 | E4: =E2*E3 | F4: =F2*F3
A6: VCSH | B6: =chi_so_tai_chinh!I39 | C6: 5514000000000 | D6: =$C$6*(($F$6/$C$6)^(1/3)) | E6: =$C$6*(($F$6/$C$6)^(2/3)) | F6: =chi_so_tai_chinh!J39
A7: LICĐKKS | B7: =chi_so_tai_chinh!I41 | C7: =chi_so_tai_chinh!J41 | D7: =chi_so_tai_chinh!K41 | E7: =chi_so_tai_chinh!L41 | F7: =chi_so_tai_chinh!M41
A8: BV | B8: =B6-B7 | C8: =C6-C7 | D8: =D6-D7 | E8: =E6-E7 | F8: =F6-F7
A9: BVPS | B9: =B8/B2 | C9: =C8/C2 | D9: =D8/D2 | E9: =E8/E2 | F9: =F8/F2
A10: PB | B10: =B3/B9 | C10: =C3/C9 | D10: =D3/D9 | E10: =E3/E9 | F10: =F3/F9
A12: DT | B12: =chi_so_tai_chinh!I43 | C12: =$B$12*(($F$12/$B$12)^(1/4)) | D12: =$B$12*(($F$12/$B$12)^(2/4)) | E12: =$B$12*(($F$12/$B$12)^(3/4)) | F12: =chi_so_tai_chinh!J43
A13: DT per share | B13: =B12/C2 | C13: =C12/C2 | D13: =D12/D2 | E13: =E12/E2 | F13: =F12/F2
A14: PS | B14: =C3/B13 | C14: =C4/C12 | D14: =D4/D12 | E14: =E4/E12 | F14: =F4/F12
A16: Earning | B16: =chi_so_tai_chinh!I52 | C16: =$B$16*(($F$16/$B$16)^(1/4)) | D16: =$B$16*(($F$16/$B$16)^(2/4)) | E16: =$B$16*(($F$16/$B$16)^(3/4)) | F16: =chi_so_tai_chinh!J52
A17: EPS | B17: =B16/$F$2 | C17: =C16/$F$2 | D17: =D16/$F$2 | E17: =E16/$F$2 | F17: =F16/$F$2
A18: PE | B18: =$F$3/B17 | C18: =$F$3/C17 | D18: =$F$3/D17 | E18: =$F$3/E17 | F18: =$F$3/F17

Sheet Hiệu quả thực hiện kế hoạch
A1: Chỉ tiêu | B1: 2022 | C1: 2023 | D1: 2024 | E1: 2025 | F1: 2026
A2: Doanh thu kế hoạch | B2: 27000000 | C2: 34000000 | D2: 37300000 | E2: 48100000 | F2: 59500000
A3: Doanh thu thuần về bán hàng và cung cấp dịch vụ | B3: =chi_so_tai_chinh!F43/1000000 | C3: =chi_so_tai_chinh!G43/1000000 | D3: =chi_so_tai_chinh!H43/1000000 | E3: =chi_so_tai_chinh!I43/1000000
A4: %thực hiện | B4: =B3/B2 | C4: =C3/C2 | D4: =D3/D2 | E4: =E3/E2
A5: Lợi nhuận trước thuế kế hoạch | B5: 720000 | C5: 240000 | D5: 125000 | E5: 900000 | F5: 1550000
A6: Lợi nhuận trước thuế thu nhập doanh nghiệp | B6: =chi_so_tai_chinh!F50/1000000 | C6: =chi_so_tai_chinh!G50/1000000 | D6: =chi_so_tai_chinh!H50/1000000 | E6: =chi_so_tai_chinh!I50/1000000
A7: %thực hiện | B7: =B6/B5 | C7: =C6/C5 | D7: =D6/D5 | E7: =E6/E5
A9: Trung vị %thực hiện DT | B9: =MEDIAN(B4:D4)
A10: Trung vị %thực hiện LNST | B10: =MEDIAN(B7:D7)
A12: Tỷ lệ hoàn thành DT trên 95% | B12: =COUNTIF(B4:E4,">=95%")/COUNT(B4:E4)
A13: Tỷ lệ hoàn thành LNST trên 95% | B13: =COUNTIF(B7:F7,">=95%")/COUNT(B7:F7)
